Workbook

Sheet Listas
A1: A | B1: Asistencia
A2: H | B2: Feriado
A3: DR | B3: D. Remunerado
A4: DNR | B4: No Remunerado
A5: F | B5: Falta
A6: N/A | B6: No Remunerado
A7: A/H | B7: Feriado laborado

Sheet Presentación
B1: Días sin planilla | F1: Días con planilla
A2: Nombre | B2: Asistido sin planilla | C2: Basico sin planilla | D2: Viaticos | E2: Total sin planilla (A) | F2: Asistidos planilla | G2: Dominical | H2: Basico mes | I2: Ingreso Quincena | J2: Asignacion familiar | K2: Horas Extras | L2: Bono asistencia | M2: Remuneración Bruta | N2: Descuento Comedor | O2: Descuento AFP | P2: Remuneración Neta (B) | Q2: Movilidad (C) | R2: Viaticos (D) | S2: Total a pagar (A+B+C+D)
A3: FARROÑAN YOVERA LUIS ALBERTO | B3: =+VLOOKUP($A$3,'Planilla Mensual'!$D:$BC,15,FALSE) -> 80 | C3: =+VLOOKUP($A$3,'Planilla Mensual'!$D:$BC,14,FALSE) -> 1300 | E3: =+(C3+D3)*B3 -> 104000 | F3: =+VLOOKUP($A$3,'Planilla Mensual'!$D:$BC,18,FALSE) -> 2 | G3: =+VLOOKUP($A$3,'Planilla Mensual'!$D:$BC,19,FALSE) -> 10 | H3: =+VLOOKUP($A$3,'Planilla Mensual'!$D:$BC,13,FALSE) -> SI | I3: =+H3/30*(G3+F3) -> #VALUE! | J3: =+VLOOKUP($A$3,'Planilla Mensual'!$D:$BC,27,FALSE) -> 476.66667 | K3: =+VLOOKUP($A$3,'Planilla Mensual'!$D:$BC,30,FALSE) -> 100 | L3: =+VLOOKUP($A$3,'Planilla Mensual'!$D:$BC,29,FALSE) -> 0 | M3: =+SUM(I3:L3) -> #VALUE! | N3: =+SUMIF('Planilla Mensual'!$D:$D,Presentación!$A$3,'Planilla Mensual'!AQ:AQ) -> 280 | O3: =+SUMIF('Planilla Mensual'!$D:$D,Presentación!$A$3,'Planilla Mensual'!AR:AR)-N3 -> 85.63505 | P3: =+M3-O3-N3 -> #VALUE! | Q3: =+VLOOKUP($A$3,'Planilla Mensual'!$D:$BC,32,FALSE) -> 753.16667 | R3: =+VLOOKUP($A$3,'Planilla Mensual'!$D:$BC,33,FALSE) -> 80 | S3: =+R3+Q3+P3+E3 -> #VALUE!
M9: =1300/206 -> 6.3106796
I10: Sueldo Bruto | J10: 2700 | M10: =+M9*1.25 -> 7.8883495
I11: AFP | J11: 190 | M11: =+M9*1.35 -> 8.5194175
I12: Alimentación | J12: =30*26 -> 780
I13: Sueldo Neto | J13: =+J10-J11-J12 -> 1730
I14: Quincena | J14: =+J13/2 -> 865
M15: =25*8 -> 200
M16: =25*30 -> 750

Sheet Planilla Mensual
M1: Periodo | S1: Sin planilla | V1: Planilla | AJ1: No remunerativo | AL1: Aportes del trabajador | AP1: Adelantos y descuentos | AU1: Aporte empleador
A2: Valor HE | B2: TIPO | C2: DNI | D2: Apellidos y nombres | E2: F. Nacimiento | F2: Puesto | G2: AFP/ONP | H2: CUSPP | I2: Banco | J2: Cuenta | K2: CCI | L2: F. Ingreso | M2: F. INICIO | N2: F.FIN | O2: Periodo | P2: Asig Familiar (SI/NO) | Q2: Basico | R2: Basico sin planilla | S2: Asistencia | T2: Descanso pagado | U2: No remunerado | V2: Dias Trab | W2: Días descanso pagado | X2: Feriado | Y2: Feriado laborado | Z2: Dias no laborados | AA2: Falta Descuento bono | AB2: TOTAL | AC2: Horas extras | AD2: Monto basico | AE2: Monto Asig | AF2: Feriado laborado | AG2: Bono asistencia | AH2: Bono Horas | AI2: Rem Bruta | AJ2: Movilidad | AK2: Viaticos | AL2: AFP (10%) | AM2: Seg. AFP (1.37%) | AN2: ONP | AO2: Renta 5ta | AP2: Otros Descuentos | AQ2: Adelantos viaticos | AR2: Total descuentos | AS2: Neto | AT2: Total No Rem | AU2: EsSalud (9%) | AV2: Total a Pagar Planilla | AX2: Extra mes | AY2: Extra pagar | AZ2: Basico Sin planilla | BA2: Viaticos sin planilla | BB2: Hora Extra | BC2: Total Trabajador | BD2: Costo Empresa
B3: PLANILLA | C3: 42878934 | D3: REQUELME BACON CESAR DAVID | E3: 31058 | F3: Operador de Maquinaria Agricola N3 | G3: SPP INTEGRA | H3: 610561CRBUO0 | I3: BCP | J3: 57016231766077 | L3: 46128 | M3: 46128 | N3: 46142 | O3: =+TEXT(M3,"mmmm")&" - "&YEAR(M3)&MONTH(M3) -> Abril - 20264 | P3: SI | Q3: 1300 | S3: 0 | T3: 0 | U3: 0 | V3: 9 | W3: 5 | X3: =+COUNTIFS('BD Asistencia'!$E:$E,"F",'BD Asistencia'!$C:$C,'Planilla Mensual'!$D3,'BD Asistencia'!$D:$D,">="&'Planilla Mensual'!M3,'BD Asistencia'!$D:$D,"<="&'Planilla Mensual'!N3) -> 0 | Y3: =+COUNTIFS('BD Asistencia'!$E:$E,"F/A",'BD Asistencia'!$C:$C,'Planilla Mensual'!$D3,'BD Asistencia'!$D:$D,">="&'Planilla Mensual'!M3,'BD Asistencia'!$D:$D,"<="&'Planilla Mensual'!N3) -> 0 | Z3: 1 | AB3: =+SUM(S3:Z3) -> 15 | AD3: =+Q3/30*SUM(V3:Y3) -> 606.66667 | AE3: =IF(P3="SI",113,0) -> 113 | AF3: =+(Q3/30*Y3)*2 -> 0 | AG3: 200 | AI3: =+SUM(AD3:AG3) -> 919.66667 | AJ3: =+V3*IF(RIGHT(F3,2)="N3",16,IF(RIGHT(F3,2)="N2",8,4)) -> 144 | AK3: =V3*30 -> 270 | AL3: =IF(G3="ONP",0,AI3*0.1) -> 91.966667 | AM3: =IF(G3="ONP",0,AI3*1.37%) -> 12.599433 | AN3: =+IF(G3="ONP",AI3*0.13,0) -> 0 | AO3: 0 | AP3: 250 | AQ3: 140 | AS3: =AI3-SUM(AL3:AQ3) -> 425.10057 | AT3: =AJ3+AK3 -> 414 | AU3: =IF(AI3*0.09<1130*0.09,1130*0.09,AI3*0.09) -> 101.7 | AV3: =AS3+AT3 -> 839.10057 | AX3: =+IF(RIGHT(F3,2)="N3",300,0) -> 300 | AY3: 150 | AZ3: =+R3*S3 -> 0 | BA3: =+S3*30 -> 0 | BC3: =+AY3+AV3+AZ3+BA3 -> 989.10057 | BD3: =AI3+AU3+AT3+AY3+AZ3+BA3 -> 1585.3667
A4: 15 | B4: PLANILLA | C4: 42878934 | D4: REQUELME BACON CESAR DAVID | E4: 31058 | F4: Operador de Maquinaria Agricola N3 | G4: SPP INTEGRA | H4: 610561CRBUO0 | I4: BCP | J4: 57016231766077 | L4: 46128 | M4: 46143 | N4: 46157 | O4: =+TEXT(M4,"mmmm")&" - "&YEAR(M4)&MONTH(M4) -> Mayo - 20265 | P4: SI | Q4: 1300 | S4: =+COUNTIFS('BD Asistencia'!$E:$E,"A",'BD Asistencia'!$C:$C,'Planilla Mensual'!$D4,'BD Asistencia'!$D:$D,"<"&'Planilla Mensual'!L4) -> 0 | T4: =+COUNTIFS('BD Asistencia'!$E:$E,"DR",'BD Asistencia'!$C:$C,'Planilla Mensual'!$D4,'BD Asistencia'!$D:$D,"<"&L4) -> 0 | U4: =+COUNTIFS('BD Asistencia'!$H:$H,"NO REMUNERADO",'BD Asistencia'!$C:$C,'Planilla Mensual'!$D4,'BD Asistencia'!$D:$D,"<"&L4) -> 0 | V4: =+COUNTIFS('BD Asistencia'!$E:$E,"A",'BD Asistencia'!$C:$C,'Planilla Mensual'!$D4,'BD Asistencia'!$D:$D,">="&'Planilla Mensual'!M4,'BD Asistencia'!$D:$D,"<="&'Planilla Mensual'!N4)-S4 -> 13 | W4: =+COUNTIFS('BD Asistencia'!$E:$E,"DR",'BD Asistencia'!$C:$C,'Planilla Mensual'!$D4,'BD Asistencia'!$D:$D,">="&'Planilla Mensual'!M4,'BD Asistencia'!$D:$D,"<="&'Planilla Mensual'!N4)-T4 -> 1 | X4: =+COUNTIFS('BD Asistencia'!$E:$E,"h",'BD Asistencia'!$C:$C,'Planilla Mensual'!$D4,'BD Asistencia'!$D:$D,">="&'Planilla Mensual'!M4,'BD Asistencia'!$D:$D,"<="&'Planilla Mensual'!N4) -> 1 | Y4: =+COUNTIFS('BD Asistencia'!$E:$E,"h/A",'BD Asistencia'!$C:$C,'Planilla Mensual'!$D4,'BD Asistencia'!$D:$D,">="&'Planilla Mensual'!M4,'BD Asistencia'!$D:$D,"<="&'Planilla Mensual'!N4) -> 0 | Z4: =+COUNTIFS('BD Asistencia'!$H:$H,"NO REMUNERADO",'BD Asistencia'!$C:$C,'Planilla Mensual'!$D4,'BD Asistencia'!$D:$D,">="&'Planilla Mensual'!M4,'BD Asistencia'!$D:$D,"<="&'Planilla Mensual'!N4)-U4 -> 0 | AA4: =+COUNTIFS('BD Asistencia'!$E:$E,"F",'BD Asistencia'!$C:$C,'Planilla Mensual'!$D4,'BD Asistencia'!$D:$D,">="&'Planilla Mensual'!M4,'BD Asistencia'!$D:$D,"<="&'Planilla Mensual'!N4) -> 0 | AB4: =+SUM(S4:AA4) -> 15 | AC4: 6 | AD4: =+Q4/30*SUM(V4:Y4) -> 650 | AE4: =IF(P4="SI",113/2,0) -> 56.5 | AF4: =+(Q4/30*Y4)*2 -> 0 | AG4: 200 | AH4: =+AC4*A4 -> 90 | AI4: =+SUM(AD4:AH4) -> 996.5 | AJ4: =+V4*IF(RIGHT(F4,2)="N3",16,IF(RIGHT(F4,2)="N2",8,4)) -> 208 | AK4: =V4*30 -> 390 | AL4: =IF(G4="ONP",0,AI4*0.1) -> 99.65 | AM4: =IF(G4="ONP",0,AI4*1.37%) -> 13.65205 | AN4: =+IF(G4="ONP",AI4*0.13,0) -> 0 | AO4: 0 | AP4: 250 | AQ4: 0 | AR4: =+SUM(AL4:AQ4) -> 363.30205 | AS4: =AI4-SUM(AL4:AQ4) -> 633.19795 | AT4: =AJ4+AK4 -> 598 | AV4: =AS4+AT4 -> 1231.1979 | AX4: =+IF(RIGHT(F4,2)="N3",300,0) -> 300 | AY4: =+AX4/30*SUM(V4:Y4) -> 150 | AZ4: =+R4*S4 -> 0 | BA4: =+S4*30 -> 0 | BC4: =+AY4+AV4+AZ4+BA4+BB4 -> 1381.1979 | BD4: =AI4+AU4+AT4+AY4+AZ4+BA4+BB4 -> 1744.5 | BE4: =(BC4+AQ4)/(V4+S4) -> 106.246 | BF4: =+BE4*26 -> 2762.3959 | BG4: =(AV4+AY4+SUM(AL4:AQ4))/(V4+W4) -> 124.60714 | BH4: =+(AZ4+BA4)/(S4+T4) -> #DIV/0! | BI4: =+BD4/V4 -> 134.19231 | BJ4: =180*2 -> 360 | BK4: =+BC4-BJ4 -> 1021.1979
A5: 15 | B5: PLANILLA | C5: 70751973 | D5: CONCEPCIÓN ZEVALLOS ARMANDO | E5: 34913 | F5: Operador de Maquinaria Agricola N3 | G5: ONP | I5: BCP | J5: 57071021755000 | L5: 46146 | M5: 46143 | N5: 46157 | O5: =+TEXT(M5,"mmmm")&" - "&YEAR(M5)&MONTH(M5) -> Mayo - 20265 | P5: SI | Q5: 1300 | R5: 110 | S5: =+COUNTIFS('BD Asistencia'!$E:$E,"A",'BD Asistencia'!$C:$C,'Planilla Mensual'!$D5,'BD Asistencia'!$D:$D,"<"&'Planilla Mensual'!L5) -> 2 | T5: =+COUNTIFS('BD Asistencia'!$E:$E,"DR",'BD Asistencia'!$C:$C,'Planilla Mensual'!$D5,'BD Asistencia'!$D:$D,"<"&L5) -> 0 | U5: =+COUNTIFS('BD Asistencia'!$H:$H,"NO REMUNERADO",'BD Asistencia'!$C:$C,'Planilla Mensual'!$D5,'BD Asistencia'!$D:$D,"<"&L5) -> 1 | V5: =+COUNTIFS('BD Asistencia'!$E:$E,"A",'BD Asistencia'!$C:$C,'Planilla Mensual'!$D5,'BD Asistencia'!$D:$D,">="&'Planilla Mensual'!M5,'BD Asistencia'!$D:$D,"<="&'Planilla Mensual'!N5)-S5 -> 11 | W5: =+COUNTIFS('BD Asistencia'!$E:$E,"DR",'BD Asistencia'!$C:$C,'Planilla Mensual'!$D5,'BD Asistencia'!$D:$D,">="&'Planilla Mensual'!M5,'BD Asistencia'!$D:$D,"<="&'Planilla Mensual'!N5)-T5 -> 1 | X5: =+COUNTIFS('BD Asistencia'!$E:$E,"h",'BD Asistencia'!$C:$C,'Planilla Mensual'!$D5,'BD Asistencia'!$D:$D,">="&'Planilla Mensual'!M5,'BD Asistencia'!$D:$D,"<="&'Planilla Mensual'!N5) -> 0 | Y5: =+COUNTIFS('BD Asistencia'!$E:$E,"h/A",'BD Asistencia'!$C:$C,'Planilla Mensual'!$D5,'BD Asistencia'!$D:$D,">="&'Planilla Mensual'!M5,'BD Asistencia'!$D:$D,"<="&'Planilla Mensual'!N5) -> 0 | Z5: =+COUNTIFS('BD Asistencia'!$H:$H,"NO REMUNERADO",'BD Asistencia'!$C:$C,'Planilla Mensual'!$D5,'BD Asistencia'!$D:$D,">="&'Planilla Mensual'!M5,'BD Asistencia'!$D:$D,"<="&'Planilla Mensual'!N5)-U5 -> 0 | AA5: =+COUNTIFS('BD Asistencia'!$E:$E,"F",'BD Asistencia'!$C:$C,'Planilla Mensual'!$D5,'BD Asistencia'!$D:$D,">="&'Planilla Mensual'!M5,'BD Asistencia'!$D:$D,"<="&'Planilla Mensual'!N5) -> 0 | AB5: =+SUM(S5:AA5) -> 15 | AC5: 0.8 | AD5: =+Q5/30*SUM(V5:Y5) -> 520 | AE5: =IF(P5="SI",113/2,0) -> 56.5 | AF5: =+(Q5/30*Y5)*2 -> 0 | AG5: 200 | AH5: =+AC5*A5 -> 12 | AI5: =+SUM(AD5:AH5) -> 788.5 | AJ5: =+V5*IF(RIGHT(F5,2)="N3",16,IF(RIGHT(F5,2)="N2",8,4)) -> 176 | AK5: =V5*30 -> 330 | AL5: =IF(G5="ONP",0,AI5*0.1) -> 0 | AM5: =IF(G5="ONP",0,AI5*1.37%) -> 0 | AN5: =+IF(G5="ONP",AI5*0.13,0) -> 102.505 | AO5: 0 | AQ5: 0 | AR5: =+SUM(AL5:AQ5) -> 102.505 | AS5: =AI5-SUM(AL5:AQ5) -> 685.995 | AT5: =AJ5+AK5 -> 506 | AV5: =AS5+AT5 -> 1191.995 | AX5: =+IF(RIGHT(F5,2)="N3",300,0) -> 300 | AY5: =+AX5/30*SUM(V5:Y5) -> 120 | AZ5: =+R5*S5 -> 220 | BA5: =+S5*30 -> 60 | BC5: =+AY5+AV5+AZ5+BA5+BB5 -> 1591.995 | BD5: =AI5+AU5+AT5+AY5+AZ5+BA5+BB5 -> 1694.5 | BE5: =(BC5+AQ5)/(V5+S5) -> 122.46115 | BF5: =+BE5*26 -> 3183.99 | BG5: =(AV5+AY5+SUM(AL5:AQ5))/V5 -> 128.59091 | BH5: =+(AZ5+BA5)/(S5+T5) -> 140 | BI5: =+BD5/V5 -> 154.04545 | BJ5: =180*2 -> 360 | BK5: =+BC5-BJ5 -> 1231.995
A6: 15 | B6: PLANILLA | C6: 75792147 | D6: TERRONES JARA FREDY | E6: 38228 | F6: Operador de Maquinaria Agricola N3 | G6: SPP INTEGRA | H6: 682261FTJRA0 | I6: BCP | J6: 57098711252088 | L6: 46146 | M6: 46143 | N6: 46157 | O6: =+TEXT(M6,"mmmm")&" - "&YEAR(M6)&MONTH(M6) -> Mayo - 20265 | P6: NO | Q6: 1300 | R6: 120 | S6: =+COUNTIFS('BD Asistencia'!$E:$E,"A",'BD Asistencia'!$C:$C,'Planilla Mensual'!$D6,'BD Asistencia'!$D:$D,"<"&'Planilla Mensual'!L6) -> 1 | T6: =+COUNTIFS('BD Asistencia'!$E:$E,"DR",'BD Asistencia'!$C:$C,'Planilla Mensual'!$D6,'BD Asistencia'!$D:$D,"<"&L6) -> 0 | U6: =+COUNTIFS('BD Asistencia'!$H:$H,"NO REMUNERADO",'BD Asistencia'!$C:$C,'Planilla Mensual'!$D6,'BD Asistencia'!$D:$D,"<"&L6) -> 2 | V6: 11 | W6: =+COUNTIFS('BD Asistencia'!$E:$E,"DR",'BD Asistencia'!$C:$C,'Planilla Mensual'!$D6,'BD Asistencia'!$D:$D,">="&'Planilla Mensual'!M6,'BD Asistencia'!$D:$D,"<="&'Planilla Mensual'!N6)-T6 -> 1 | X6: =+COUNTIFS('BD Asistencia'!$E:$E,"h",'BD Asistencia'!$C:$C,'Planilla Mensual'!$D6,'BD Asistencia'!$D:$D,">="&'Planilla Mensual'!M6,'BD Asistencia'!$D:$D,"<="&'Planilla Mensual'!N6) -> 0 | Y6: =+COUNTIFS('BD Asistencia'!$E:$E,"h/A",'BD Asistencia'!$C:$C,'Planilla Mensual'!$D6,'BD Asistencia'!$D:$D,">="&'Planilla Mensual'!M6,'BD Asistencia'!$D:$D,"<="&'Planilla Mensual'!N6) -> 0 | Z6: =+COUNTIFS('BD Asistencia'!$H:$H,"NO REMUNERADO",'BD Asistencia'!$C:$C,'Planilla Mensual'!$D6,'BD Asistencia'!$D:$D,">="&'Planilla Mensual'!M6,'BD Asistencia'!$D:$D,"<="&'Planilla Mensual'!N6)-U6 -> 0 | AA6: =+COUNTIFS('BD Asistencia'!$E:$E,"F",'BD Asistencia'!$C:$C,'Planilla Mensual'!$D6,'BD Asistencia'!$D:$D,">="&'Planilla Mensual'!M6,'BD Asistencia'!$D:$D,"<="&'Planilla Mensual'!N6) -> 0 | AB6: =+SUM(S6:AA6) -> 15 | AC6: 6.3 | AD6: =+Q6/30*SUM(V6:Y6) -> 520 | AE6: =IF(P6="SI",113/2,0) -> 0 | AF6: =+(Q6/30*Y6)*2 -> 0 | AG6: 200 | AH6: =+AC6*A6 -> 94.5 | AI6: =+SUM(AD6:AH6) -> 814.5 | AJ6: =+V6*IF(RIGHT(F6,2)="N3",16,IF(RIGHT(F6,2)="N2",8,4)) -> 176 | AK6: =V6*30 -> 330 | AL6: =IF(G6="ONP",0,AI6*0.1) -> 81.45 | AM6: =IF(G6="ONP",0,AI6*1.37%) -> 11.15865 | AN6: =+IF(G6="ONP",AI6*0.13,0) -> 0 | AO6: 0 | AQ6: 0 | AR6: =+SUM(AL6:AQ6) -> 92.60865 | AS6: =AI6-SUM(AL6:AQ6) -> 721.89135 | AT6: =AJ6+AK6 -> 506 | AV6: =AS6+AT6 -> 1227.8913 | AX6: =+IF(RIGHT(F6,2)="N3",300,0) -> 300 | AY6: =+AX6/30*SUM(V6:Y6) -> 120 | AZ6: =+R6*S6 -> 120 | BA6: =+S6*30 -> 30 | BC6: =+AY6+AV6+AZ6+BA6+BB6 -> 1497.8913 | BD6: =AI6+AU6+AT6+AY6+AZ6+BA6+BB6 -> 1590.5 | BE6: =(BC6+AQ6)/(V6+S6) -> 124.82428 | BF6: =+BE6*26 -> 3245.4313 | BG6: =(AV6+AY6+SUM(AL6:AQ6))/V6 -> 130.95455 | BH6: =+(AZ6+BA6)/(S6+T6) -> 150 | BI6: =+BD6/V6 -> 144.59091 | BJ6: =180*2 -> 360 | BK6: =+BC6-BJ6 -> 1137.8913
A7: 15 | B7: PLANILLA | C7: 74242456 | D7: MONTOYA NAMOC JORGE LUIS | E7: 37386 | F7: Operador de Maquinaria Agricola N3 | G7: SPP INTEGRA | H7: 673841JMNTO4 | I7: BCP | J7: 57016070300081 | L7: 46146 | M7: 46143 | N7: 46157 | O7: =+TEXT(M7,"mmmm")&" - "&YEAR(M7)&MONTH(M7) -> Mayo - 20265 | P7: NO | Q7: 1300 | R7: 110 | S7: =+COUNTIFS('BD Asistencia'!$E:$E,"A",'BD Asistencia'!$C:$C,'Planilla Mensual'!$D7,'BD Asistencia'!$D:$D,"<"&'Planilla Mensual'!L7) -> 2 | T7: =+COUNTIFS('BD Asistencia'!$E:$E,"DR",'BD Asistencia'!$C:$C,'Planilla Mensual'!$D7,'BD Asistencia'!$D:$D,"<"&L7) -> 0 | U7: =+COUNTIFS('BD Asistencia'!$H:$H,"NO REMUNERADO",'BD Asistencia'!$C:$C,'Planilla Mensual'!$D7,'BD Asistencia'!$D:$D,"<"&L7) -> 1 | V7: =+COUNTIFS('BD Asistencia'!$E:$E,"A",'BD Asistencia'!$C:$C,'Planilla Mensual'!$D7,'BD Asistencia'!$D:$D,">="&'Planilla Mensual'!M7,'BD Asistencia'!$D:$D,"<="&'Planilla Mensual'!N7)-S7 -> 11 | W7: =+COUNTIFS('BD Asistencia'!$E:$E,"DR",'BD Asistencia'!$C:$C,'Planilla Mensual'!$D7,'BD Asistencia'!$D:$D,">="&'Planilla Mensual'!M7,'BD Asistencia'!$D:$D,"<="&'Planilla Mensual'!N7)-T7 -> 1 | X7: =+COUNTIFS('BD Asistencia'!$E:$E,"h",'BD Asistencia'!$C:$C,'Planilla Mensual'!$D7,'BD Asistencia'!$D:$D,">="&'Planilla Mensual'!M7,'BD Asistencia'!$D:$D,"<="&'Planilla Mensual'!N7) -> 0 | Y7: =+COUNTIFS('BD Asistencia'!$E:$E,"h/A",'BD Asistencia'!$C:$C,'Planilla Mensual'!$D7,'BD Asistencia'!$D:$D,">="&'Planilla Mensual'!M7,'BD Asistencia'!$D:$D,"<="&'Planilla Mensual'!N7) -> 0 | Z7: =+COUNTIFS('BD Asistencia'!$H:$H,"NO REMUNERADO",'BD Asistencia'!$C:$C,'Planilla Mensual'!$D7,'BD Asistencia'!$D:$D,">="&'Planilla Mensual'!M7,'BD Asistencia'!$D:$D,"<="&'Planilla Mensual'!N7)-U7 -> 0 | AA7: =+COUNTIFS('BD Asistencia'!$E:$E,"F",'BD Asistencia'!$C:$C,'Planilla Mensual'!$D7,'BD Asistencia'!$D:$D,">="&'Planilla Mensual'!M7,'BD Asistencia'!$D:$D,"<="&'Planilla Mensual'!N7) -> 0 | AB7: =+SUM(S7:AA7) -> 15 | AC7: 0.8 | AD7: =+Q7/30*SUM(V7:Y7) -> 520 | AE7: =IF(P7="SI",113/2,0) -> 0 | AF7: =+(Q7/30*Y7)*2 -> 0 | AG7: 200 | AH7: =+AC7*A7 -> 12 | AI7: =+SUM(AD7:AH7) -> 732 | AJ7: =+V7*IF(RIGHT(F7,2)="N3",16,IF(RIGHT(F7,2)="N2",8,4)) -> 176 | AK7: =V7*30 -> 330 | AL7: =IF(G7="ONP",0,AI7*0.1) -> 73.2 | AM7: =IF(G7="ONP",0,AI7*1.37%) -> 10.0284 | AN7: =+IF(G7="ONP",AI7*0.13,0) -> 0 | AO7: 0 | AQ7: 0 | AR7: =+SUM(AL7:AQ7) -> 83.2284 | AS7: =AI7-SUM(AL7:AQ7) -> 648.7716 | AT7: =AJ7+AK7 -> 506 | AV7: =AS7+AT7 -> 1154.7716 | AX7: =+IF(RIGHT(F7,2)="N3",300,0) -> 300 | AY7: =+AX7/30*SUM(V7:Y7) -> 120 | AZ7: =+R7*S7 -> 220 | BA7: =+S7*30 -> 60 | BC7: =+AY7+AV7+AZ7+BA7+BB7 -> 1554.7716 | BD7: =AI7+AU7+AT7+AY7+AZ7+BA7+BB7 -> 1638 | BE7: =(BC7+AQ7)/(V7+S7) -> 119.59782 | BF7: =+BE7*26 -> 3109.5432 | BG7: =(AV7+AY7+SUM(AL7:AQ7))/V7 -> 123.45455 | BH7: =+(AZ7+BA7)/(S7+T7) -> 140 | BI7: =+BD7/V7 -> 148.90909 | BJ7: =180*2 -> 360 | BK7: =+BC7-BJ7 -> 1194.7716
A8: 15 | B8: PLANILLA | C8: 48787545 | D8: DIAZ DIAZ JUNNIOR | E8: 34609 | F8: Operador de Maquinaria Agricola N3 | G8: SPP PRIMA | H8: 646071JDDZZ4 | I8: BCP | J8: 30071590047060 | L8: 46146 | M8: 46143 | N8: 46157 | O8: =+TEXT(M8,"mmmm")&" - "&YEAR(M8)&MONTH(M8) -> Mayo - 20265 | P8: SI | Q8: 1300 | R8: 100 | S8: =+COUNTIFS('BD Asistencia'!$E:$E,"A",'BD Asistencia'!$C:$C,'Planilla Mensual'!$D8,'BD Asistencia'!$D:$D,"<"&'Planilla Mensual'!L8) -> 1 | T8: =+COUNTIFS('BD Asistencia'!$E:$E,"DR",'BD Asistencia'!$C:$C,'Planilla Mensual'!$D8,'BD Asistencia'!$D:$D,"<"&L8) -> 0 | U8: =+COUNTIFS('BD Asistencia'!$H:$H,"NO REMUNERADO",'BD Asistencia'!$C:$C,'Planilla Mensual'!$D8,'BD Asistencia'!$D:$D,"<"&L8) -> 2 | V8: 11 | W8: =+COUNTIFS('BD Asistencia'!$E:$E,"DR",'BD Asistencia'!$C:$C,'Planilla Mensual'!$D8,'BD Asistencia'!$D:$D,">="&'Planilla Mensual'!M8,'BD Asistencia'!$D:$D,"<="&'Planilla Mensual'!N8)-T8 -> 1 | X8: =+COUNTIFS('BD Asistencia'!$E:$E,"h",'BD Asistencia'!$C:$C,'Planilla Mensual'!$D8,'BD Asistencia'!$D:$D,">="&'Planilla Mensual'!M8,'BD Asistencia'!$D:$D,"<="&'Planilla Mensual'!N8) -> 0 | Y8: =+COUNTIFS('BD Asistencia'!$E:$E,"h/A",'BD Asistencia'!$C:$C,'Planilla Mensual'!$D8,'BD Asistencia'!$D:$D,">="&'Planilla Mensual'!M8,'BD Asistencia'!$D:$D,"<="&'Planilla Mensual'!N8) -> 0 | Z8: =+COUNTIFS('BD Asistencia'!$H:$H,"NO REMUNERADO",'BD Asistencia'!$C:$C,'Planilla Mensual'!$D8,'BD Asistencia'!$D:$D,">="&'Planilla Mensual'!M8,'BD Asistencia'!$D:$D,"<="&'Planilla Mensual'!N8)-U8 -> 0 | AA8: =+COUNTIFS('BD Asistencia'!$E:$E,"F",'BD Asistencia'!$C:$C,'Planilla Mensual'!$D8,'BD Asistencia'!$D:$D,">="&'Planilla Mensual'!M8,'BD Asistencia'!$D:$D,"<="&'Planilla Mensual'!N8) -> 0 | AB8: =+SUM(S8:AA8) -> 15 | AC8: 4.5 | AD8: =+Q8/30*SUM(V8:Y8) -> 520 | AE8: =IF(P8="SI",113/2,0) -> 56.5 | AF8: =+(Q8/30*Y8)*2 -> 0 | AG8: 200 | AH8: =+AC8*A8 -> 67.5 | AI8: =+SUM(AD8:AH8) -> 844 | AJ8: =+V8*IF(RIGHT(F8,2)="N3",16,IF(RIGHT(F8,2)="N2",8,4)) -> 176 | AK8: =V8*30 -> 330 | AL8: =IF(G8="ONP",0,AI8*0.1) -> 84.4 | AM8: =IF(G8="ONP",0,AI8*1.37%) -> 11.5628 | AN8: =+IF(G8="ONP",AI8*0.13,0) -> 0 | AO8: 0 | AQ8: 0 | AR8: =+SUM(AL8:AQ8) -> 95.9628 | AS8: =AI8-SUM(AL8:AQ8) -> 748.0372 | AT8: =AJ8+AK8 -> 506 | AV8: =AS8+AT8 -> 1254.0372 | AX8: =+IF(RIGHT(F8,2)="N3",300,0) -> 300 | AY8: =+AX8/30*SUM(V8:Y8) -> 120 | AZ8: =+R8*S8 -> 100 | BA8: =+S8*30 -> 30 | BC8: =+AY8+AV8+AZ8+BA8+BB8 -> 1504.0372 | BD8: =AI8+AU8+AT8+AY8+AZ8+BA8+BB8 -> 1600 | BE8: =(BC8+AQ8)/(V8+S8) -> 125.33643 | BF8: =+BE8*26 -> 3258.7473 | BG8: =(AV8+AY8+SUM(AL8:AQ8))/V8 -> 133.63636 | BH8: =+(AZ8+BA8)/(S8+T8) -> 130 | BI8: =+BD8/V8 -> 145.45455 | BJ8: =180*2 -> 360 | BK8: =+BC8-BJ8 -> 1144.0372
A9: 15 | B9: PLANILLA | C9: 73814026 | D9: SIFUENTES PAREDES EDUARDO JAVIER | E9: 36718 | F9: Operador de Maquinaria Agricola N1 | G9: SPP INTEGRA | H9: 667161ESPUE1 | I9: BCP | J9: 19277856288012 | L9: 46146 | M9: 46143 | N9: 46157 | O9: =+TEXT(M9,"mmmm")&" - "&YEAR(M9)&MONTH(M9) -> Mayo - 20265 | P9: SI | Q9: 1200 | R9: 80 | S9: =+COUNTIFS('BD Asistencia'!$E:$E,"A",'BD Asistencia'!$C:$C,'Planilla Mensual'!$D9,'BD Asistencia'!$D:$D,"<"&'Planilla Mensual'!L9) -> 2 | T9: =+COUNTIFS('BD Asistencia'!$E:$E,"DR",'BD Asistencia'!$C:$C,'Planilla Mensual'!$D9,'BD Asistencia'!$D:$D,"<"&L9) -> 0 | U9: =+COUNTIFS('BD Asistencia'!$H:$H,"NO REMUNERADO",'BD Asistencia'!$C:$C,'Planilla Mensual'!$D9,'BD Asistencia'!$D:$D,"<"&L9) -> 1 | V9: =+COUNTIFS('BD Asistencia'!$E:$E,"A",'BD Asistencia'!$C:$C,'Planilla Mensual'!$D9,'BD Asistencia'!$D:$D,">="&'Planilla Mensual'!M9,'BD Asistencia'!$D:$D,"<="&'Planilla Mensual'!N9)-S9 -> 11 | W9: =+COUNTIFS('BD Asistencia'!$E:$E,"DR",'BD Asistencia'!$C:$C,'Planilla Mensual'!$D9,'BD Asistencia'!$D:$D,">="&'Planilla Mensual'!M9,'BD Asistencia'!$D:$D,"<="&'Planilla Mensual'!N9)-T9 -> 1 | X9: =+COUNTIFS('BD Asistencia'!$E:$E,"h",'BD Asistencia'!$C:$C,'Planilla Mensual'!$D9,'BD Asistencia'!$D:$D,">="&'Planilla Mensual'!M9,'BD Asistencia'!$D:$D,"<="&'Planilla Mensual'!N9) -> 0 | Y9: =+COUNTIFS('BD Asistencia'!$E:$E,"h/A",'BD Asistencia'!$C:$C,'Planilla Mensual'!$D9,'BD Asistencia'!$D:$D,">="&'Planilla Mensual'!M9,'BD Asistencia'!$D:$D,"<="&'Planilla Mensual'!N9) -> 0 | Z9: =+COUNTIFS('BD Asistencia'!$H:$H,"NO REMUNERADO",'BD Asistencia'!$C:$C,'Planilla Mensual'!$D9,'BD Asistencia'!$D:$D,">="&'Planilla Mensual'!M9,'BD Asistencia'!$D:$D,"<="&'Planilla Mensual'!N9)-U9 -> 0 | AA9: =+COUNTIFS('BD Asistencia'!$E:$E,"F",'BD Asistencia'!$C:$C,'Planilla Mensual'!$D9,'BD Asistencia'!$D:$D,">="&'Planilla Mensual'!M9,'BD Asistencia'!$D:$D,"<="&'Planilla Mensual'!N9) -> 0 | AB9: =+SUM(S9:AA9) -> 15 | AD9: =+Q9/30*SUM(V9:Y9) -> 480 | AE9: =IF(P9="SI",113/2,0) -> 56.5 | AF9: =+(Q9/30*Y9)*2 -> 0 | AG9: 200 | AH9: =+AC9*A9 -> 0 | AI9: =+SUM(AD9:AH9) -> 736.5 | AJ9: =+V9*IF(RIGHT(F9,2)="N3",16,IF(RIGHT(F9,2)="N2",8,4)) -> 44 | AK9: =V9*30 -> 330 | AL9: =IF(G9="ONP",0,AI9*0.1) -> 73.65 | AM9: =IF(G9="ONP",0,AI9*1.37%) -> 10.09005 | AN9: =+IF(G9="ONP",AI9*0.13,0) -> 0 | AO9: 0 | AQ9: 0 | AR9: =+SUM(AL9:AQ9) -> 83.74005 | AS9: =AI9-SUM(AL9:AQ9) -> 652.75995 | AT9: =AJ9+AK9 -> 374 | AV9: =AS9+AT9 -> 1026.76 | AX9: =+IF(RIGHT(F9,2)="N3",300,0) -> 0 | AY9: =+AX9/30*SUM(V9:Y9) -> 0 | AZ9: =+R9*(S9+T9) -> 160 | BA9: =+S9*30 -> 60 | BC9: =+AY9+AV9+AZ9+BA9+BB9 -> 1246.76 | BD9: =AI9+AU9+AT9+AY9+AZ9+BA9+BB9 -> 1330.5 | BE9: =(BC9+AQ9)/(V9+S9) -> 95.904612 | BF9: =+BE9*26 -> 2493.5199 | BG9: =(AV9+AY9+SUM(AL9:AQ9))/V9 -> 100.95455 | BH9: =+(AZ9+BA9)/(S9+T9) -> 110 | BI9: =+BD9/V9 -> 120.95455 | BJ9: =180*2 -> 360 | BK9: =+BC9-BJ9 -> 886.75995
A10: 15 | B10: PLANILLA | C10: 80780158 | D10: TERRONES JARA LEYDER | E10: 39304 | F10: Operador de Maquinaria Agricola N1 | G10: ONP | I10: BCP | J10: 45016550233040 | L10: 46146 | M10: 46143 | N10: 46157 | O10: =+TEXT(M10,"mmmm")&" - "&YEAR(M10)&MONTH(M10) -> Mayo - 20265 | P10: NO | Q10: 1200 | R10: 80 | S10: =+COUNTIFS('BD Asistencia'!$E:$E,"A",'BD Asistencia'!$C:$C,'Planilla Mensual'!$D10,'BD Asistencia'!$D:$D,"<"&'Planilla Mensual'!L10) -> 1 | T10: =+COUNTIFS('BD Asistencia'!$E:$E,"DR",'BD Asistencia'!$C:$C,'Planilla Mensual'!$D10,'BD Asistencia'!$D:$D,"<"&L10) -> 0 | U10: =+COUNTIFS('BD Asistencia'!$H:$H,"NO REMUNERADO",'BD Asistencia'!$C:$C,'Planilla Mensual'!$D10,'BD Asistencia'!$D:$D,"<"&L10) -> 2 | V10: 11 | W10: =+COUNTIFS('BD Asistencia'!$E:$E,"DR",'BD Asistencia'!$C:$C,'Planilla Mensual'!$D10,'BD Asistencia'!$D:$D,">="&'Planilla Mensual'!M10,'BD Asistencia'!$D:$D,"<="&'Planilla Mensual'!N10)-T10 -> 1 | X10: =+COUNTIFS('BD Asistencia'!$E:$E,"h",'BD Asistencia'!$C:$C,'Planilla Mensual'!$D10,'BD Asistencia'!$D:$D,">="&'Planilla Mensual'!M10,'BD Asistencia'!$D:$D,"<="&'Planilla Mensual'!N10) -> 0 | Y10: =+COUNTIFS('BD Asistencia'!$E:$E,"h/A",'BD Asistencia'!$C:$C,'Planilla Mensual'!$D10,'BD Asistencia'!$D:$D,">="&'Planilla Mensual'!M10,'BD Asistencia'!$D:$D,"<="&'Planilla Mensual'!N10) -> 0 | Z10: =+COUNTIFS('BD Asistencia'!$H:$H,"NO REMUNERADO",'BD Asistencia'!$C:$C,'Planilla Mensual'!$D10,'BD Asistencia'!$D:$D,">="&'Planilla Mensual'!M10,'BD Asistencia'!$D:$D,"<="&'Planilla Mensual'!N10)-U10 -> 0 | AA10: =+COUNTIFS('BD Asistencia'!$E:$E,"F",'BD Asistencia'!$C:$C,'Planilla Mensual'!$D10,'BD Asistencia'!$D:$D,">="&'Planilla Mensual'!M10,'BD Asistencia'!$D:$D,"<="&'Planilla Mensual'!N10) -> 0 | AB10: =+SUM(S10:AA10) -> 15 | AD10: =+Q10/30*SUM(V10:Y10) -> 480 | AE10: =IF(P10="SI",113/2,0) -> 0 | AF10: =+(Q10/30*Y10)*2 -> 0 | AG10: 200 | AH10: =+AC10*A10 -> 0 | AI10: =+SUM(AD10:AH10) -> 680 | AJ10: =+V10*IF(RIGHT(F10,2)="N3",16,IF(RIGHT(F10,2)="N2",8,4)) -> 44 | AK10: =V10*30 -> 330 | AL10: =IF(G10="ONP",0,AI10*0.1) -> 0 | AM10: =IF(G10="ONP",0,AI10*1.37%) -> 0 | AN10: =+IF(G10="ONP",AI10*0.13,0) -> 88.4 | AO10: 0 | AP10: 75 | AQ10: 0 | AR10: =+SUM(AL10:AQ10) -> 163.4 | AS10: =AI10-SUM(AL10:AQ10) -> 516.6 | AT10: =AJ10+AK10 -> 374 | AV10: =AS10+AT10 -> 890.6 | AX10: =+IF(RIGHT(F10,2)="N3",300,0) -> 0 | AY10: =+AX10/30*SUM(V10:Y10) -> 0 | AZ10: =+R10*(S10+T10) -> 80 | BA10: =+S10*30 -> 30 | BC10: =+AY10+AV10+AZ10+BA10+BB10 -> 1000.6 | BD10: =AI10+AU10+AT10+AY10+AZ10+BA10+BB10 -> 1164 | BE10: =(BC10+AQ10)/(V10+S10) -> 83.383333 | BF10: =+BE10*26 -> 2167.9667 | BG10: =(AV10+AY10+SUM(AL10:AQ10))/V10 -> 95.818182 | BH10: =+(AZ10+BA10)/(S10+T10) -> 110 | BI10: =+BD10/V10 -> 105.81818 | BJ10: =180*2 -> 360 | BK10: =+BC10-BJ10 -> 640.6
A11: 10 | B11: PLANILLA | C11: 73322149 | D11: CALLE HUAMAN LEODAN JOEL | E11: 35920 | F11: Operador de Maquinaria Agricola N3 | G11: SPP PRIMA | H11: 659181LCHLM9 | I11: SCOTIABANK | J11: 8330769627 | K11: 00972420833076962762 | L11: 46146 | M11: 46143 | N11: 46157 | O11: =+TEXT(M11,"mmmm")&" - "&YEAR(M11)&MONTH(M11) -> Mayo - 20265 | P11: SI | Q11: 1300 | R11: 100 | S11: =+COUNTIFS('BD Asistencia'!$E:$E,"A",'BD Asistencia'!$C:$C,'Planilla Mensual'!$D11,'BD Asistencia'!$D:$D,"<"&'Planilla Mensual'!L11) -> 1 | T11: =+COUNTIFS('BD Asistencia'!$E:$E,"DR",'BD Asistencia'!$C:$C,'Planilla Mensual'!$D11,'BD Asistencia'!$D:$D,"<"&L11) -> 0 | U11: =+COUNTIFS('BD Asistencia'!$H:$H,"NO REMUNERADO",'BD Asistencia'!$C:$C,'Planilla Mensual'!$D11,'BD Asistencia'!$D:$D,"<"&L11) -> 2 | V11: =+COUNTIFS('BD Asistencia'!$E:$E,"A",'BD Asistencia'!$C:$C,'Planilla Mensual'!$D11,'BD Asistencia'!$D:$D,">="&'Planilla Mensual'!M11,'BD Asistencia'!$D:$D,"<="&'Planilla Mensual'!N11)-S11 -> 11 | W11: =+COUNTIFS('BD Asistencia'!$E:$E,"DR",'BD Asistencia'!$C:$C,'Planilla Mensual'!$D11,'BD Asistencia'!$D:$D,">="&'Planilla Mensual'!M11,'BD Asistencia'!$D:$D,"<="&'Planilla Mensual'!N11)-T11 -> 1 | X11: =+COUNTIFS('BD Asistencia'!$E:$E,"h",'BD Asistencia'!$C:$C,'Planilla Mensual'!$D11,'BD Asistencia'!$D:$D,">="&'Planilla Mensual'!M11,'BD Asistencia'!$D:$D,"<="&'Planilla Mensual'!N11) -> 0 | Y11: =+COUNTIFS('BD Asistencia'!$E:$E,"h/A",'BD Asistencia'!$C:$C,'Planilla Mensual'!$D11,'BD Asistencia'!$D:$D,">="&'Planilla Mensual'!M11,'BD Asistencia'!$D:$D,"<="&'Planilla Mensual'!N11) -> 0 | Z11: =+COUNTIFS('BD Asistencia'!$H:$H,"NO REMUNERADO",'BD Asistencia'!$C:$C,'Planilla Mensual'!$D11,'BD Asistencia'!$D:$D,">="&'Planilla Mensual'!M11,'BD Asistencia'!$D:$D,"<="&'Planilla Mensual'!N11)-U11 -> 0 | AA11: =+COUNTIFS('BD Asistencia'!$E:$E,"F",'BD Asistencia'!$C:$C,'Planilla Mensual'!$D11,'BD Asistencia'!$D:$D,">="&'Planilla Mensual'!M11,'BD Asistencia'!$D:$D,"<="&'Planilla Mensual'!N11) -> 0 | AB11: =+SUM(S11:AA11) -> 15 | AC11: 5.5 | AD11: =+Q11/30*SUM(V11:Y11) -> 520 | AE11: =IF(P11="SI",113/2,0) -> 56.5 | AF11: =+(Q11/30*Y11)*2 -> 0 | AG11: 200 | AH11: =+AC11*A11 -> 55 | AI11: =+SUM(AD11:AH11) -> 831.5 | AJ11: =+V11*IF(RIGHT(F11,2)="N3",16,IF(RIGHT(F11,2)="N2",8,4)) -> 176 | AK11: =V11*30 -> 330 | AL11: =IF(G11="ONP",0,AI11*0.1) -> 83.15 | AM11: =IF(G11="ONP",0,AI11*1.37%) -> 11.39155 | AN11: =+IF(G11="ONP",AI11*0.13,0) -> 0 | AO11: 0 | AQ11: 40 | AR11: =+SUM(AL11:AQ11) -> 134.54155 | AS11: =AI11-SUM(AL11:AQ11) -> 696.95845 | AT11: =AJ11+AK11 -> 506 | AV11: =AS11+AT11 -> 1202.9585 | AX11: =+IF(RIGHT(F11,2)="N3",300,0) -> 300 | AY11: =+AX11/30*SUM(V11:Y11) -> 120 | AZ11: =+R11*(S11+T11) -> 100 | BA11: 0 | BC11: =+AY11+AV11+AZ11+BA11+BB11 -> 1422.9585 | BD11: =AI11+AU11+AT11+AY11+AZ11+BA11+BB11 -> 1557.5 | BE11: =(BC11+AQ11)/(V11+S11) -> 121.9132 | BF11: =+BE11*26 -> 3169.7433 | BG11: =(AV11+AY11+SUM(AL11:AQ11))/V11 -> 132.5 | BH11: =+(AZ11+BA11)/(S11+T11) -> 100 | BI11: =+BD11/V11 -> 141.59091
A12: 10 | B12: PLANILLA | C12: 76768818 | D12: MANAYAY TANTARICO JHONATAN WILFER | E12: 37200 | F12: Operador de Maquinaria Agricola N2 | G12: SPP INTEGRA | H12: 671981JMTAT4 | I12: BCP | J12: 30500970418007 | L12: 46146 | M12: 46143 | N12: 46157 | O12: =+TEXT(M12,"mmmm")&" - "&YEAR(M12)&MONTH(M12) -> Mayo - 20265 | P12: NO | Q12: 1300 | R12: 80 | S12: =+COUNTIFS('BD Asistencia'!$E:$E,"A",'BD Asistencia'!$C:$C,'Planilla Mensual'!$D12,'BD Asistencia'!$D:$D,"<"&'Planilla Mensual'!L12) -> 1 | T12: =+COUNTIFS('BD Asistencia'!$E:$E,"DR",'BD Asistencia'!$C:$C,'Planilla Mensual'!$D12,'BD Asistencia'!$D:$D,"<"&L12) -> 0 | U12: =+COUNTIFS('BD Asistencia'!$H:$H,"NO REMUNERADO",'BD Asistencia'!$C:$C,'Planilla Mensual'!$D12,'BD Asistencia'!$D:$D,"<"&L12) -> 2 | V12: =+COUNTIFS('BD Asistencia'!$E:$E,"A",'BD Asistencia'!$C:$C,'Planilla Mensual'!$D12,'BD Asistencia'!$D:$D,">="&'Planilla Mensual'!M12,'BD Asistencia'!$D:$D,"<="&'Planilla Mensual'!N12)-S12 -> 11 | W12: =+COUNTIFS('BD Asistencia'!$E:$E,"DR",'BD Asistencia'!$C:$C,'Planilla Mensual'!$D12,'BD Asistencia'!$D:$D,">="&'Planilla Mensual'!M12,'BD Asistencia'!$D:$D,"<="&'Planilla Mensual'!N12)-T12 -> 1 | X12: =+COUNTIFS('BD Asistencia'!$E:$E,"h",'BD Asistencia'!$C:$C,'Planilla Mensual'!$D12,'BD Asistencia'!$D:$D,">="&'Planilla Mensual'!M12,'BD Asistencia'!$D:$D,"<="&'Planilla Mensual'!N12) -> 0 | Y12: =+COUNTIFS('BD Asistencia'!$E:$E,"h/A",'BD Asistencia'!$C:$C,'Planilla Mensual'!$D12,'BD Asistencia'!$D:$D,">="&'Planilla Mensual'!M12,'BD Asistencia'!$D:$D,"<="&'Planilla Mensual'!N12) -> 0 | Z12: =+COUNTIFS('BD Asistencia'!$H:$H,"NO REMUNERADO",'BD Asistencia'!$C:$C,'Planilla Mensual'!$D12,'BD Asistencia'!$D:$D,">="&'Planilla Mensual'!M12,'BD Asistencia'!$D:$D,"<="&'Planilla Mensual'!N12)-U12 -> 0 | AA12: =+COUNTIFS('BD Asistencia'!$E:$E,"F",'BD Asistencia'!$C:$C,'Planilla Mensual'!$D12,'BD Asistencia'!$D:$D,">="&'Planilla Mensual'!M12,'BD Asistencia'!$D:$D,"<="&'Planilla Mensual'!N12) -> 0 | AB12: =+SUM(S12:AA12) -> 15 | AC12: 3 | AD12: =+Q12/30*SUM(V12:Y12) -> 520 | AE12: =IF(P12="SI",113/2,0) -> 0 | AF12: =+(Q12/30*Y12)*2 -> 0 | AG12: 200 | AH12: =+AC12*A12 -> 30 | AI12: =+SUM(AD12:AH12) -> 750 | AJ12: =+V12*IF(RIGHT(F12,2)="N3",16,IF(RIGHT(F12,2)="N2",8,4)) -> 88 | AK12: =V12*30 -> 330 | AL12: =IF(G12="ONP",0,AI12*0.1) -> 75 | AM12: =IF(G12="ONP",0,AI12*1.37%) -> 10.275 | AN12: =+IF(G12="ONP",AI12*0.13,0) -> 0 | AO12: 0 | AQ12: 300 | AR12: =+SUM(AL12:AQ12) -> 385.275 | AS12: =AI12-SUM(AL12:AQ12) -> 364.725 | AT12: =AJ12+AK12 -> 418 | AV12: =AS12+AT12 -> 782.725 | AX12: =+IF(RIGHT(F12,2)="N3",300,0) -> 0 | AY12: =+AX12/30*SUM(V12:Y12) -> 0 | AZ12: =+R12*(S12+T12) -> 80 | BA12: 0 | BC12: =+AY12+AV12+AZ12+BA12+BB12 -> 862.725 | BD12: =AI12+AU12+AT12+AY12+AZ12+BA12+BB12 -> 1248 | BE12: =(BC12+AQ12)/(V12+S12) -> 96.89375 | BF12: =+BE12*26 -> 2519.2375 | BG12: =(AV12+AY12+SUM(AL12:AQ12))/V12 -> 106.18182 | BH12: =+(AZ12+BA12)/(S12+T12) -> 80 | BI12: =+BD12/V12 -> 113.45455
A13: 10 | B13: PLANILLA | C13: 41758826 | D13: FARROÑAN YOVERA LUIS ALBERTO | E13: 30279 | F13: Operador de Maquinaria Agricola N2 | G13: SPP PRIMA | H13: 602771LFYRE8 | I13: BCP | J13: 30513491010070 | L13: 46146 | M13: 46143 | N13: 46157 | O13: =+TEXT(M13,"mmmm")&" - "&YEAR(M13)&MONTH(M13) -> Mayo - 20265 | P13: SI | Q13: 1300 | R13: 80 | S13: =+COUNTIFS('BD Asistencia'!$E:$E,"A",'BD Asistencia'!$C:$C,'Planilla Mensual'!$D13,'BD Asistencia'!$D:$D,"<"&'Planilla Mensual'!L13) -> 1 | T13: =+COUNTIFS('BD Asistencia'!$E:$E,"DR",'BD Asistencia'!$C:$C,'Planilla Mensual'!$D13,'BD Asistencia'!$D:$D,"<"&L13) -> 0 | U13: =+COUNTIFS('BD Asistencia'!$H:$H,"NO REMUNERADO",'BD Asistencia'!$C:$C,'Planilla Mensual'!$D13,'BD Asistencia'!$D:$D,"<"&L13) -> 2 | V13: =+COUNTIFS('BD Asistencia'!$E:$E,"A",'BD Asistencia'!$C:$C,'Planilla Mensual'!$D13,'BD Asistencia'!$D:$D,">="&'Planilla Mensual'!M13,'BD Asistencia'!$D:$D,"<="&'Planilla Mensual'!N13)-S13 -> 10 | W13: =+COUNTIFS('BD Asistencia'!$E:$E,"DR",'BD Asistencia'!$C:$C,'Planilla Mensual'!$D13,'BD Asistencia'!$D:$D,">="&'Planilla Mensual'!M13,'BD Asistencia'!$D:$D,"<="&'Planilla Mensual'!N13)-T13 -> 1 | X13: =+COUNTIFS('BD Asistencia'!$E:$E,"h",'BD Asistencia'!$C:$C,'Planilla Mensual'!$D13,'BD Asistencia'!$D:$D,">="&'Planilla Mensual'!M13,'BD Asistencia'!$D:$D,"<="&'Planilla Mensual'!N13) -> 0 | Y13: =+COUNTIFS('BD Asistencia'!$E:$E,"h/A",'BD Asistencia'!$C:$C,'Planilla Mensual'!$D13,'BD Asistencia'!$D:$D,">="&'Planilla Mensual'!M13,'BD Asistencia'!$D:$D,"<="&'Planilla Mensual'!N13) -> 0 | Z13: =+COUNTIFS('BD Asistencia'!$H:$H,"NO REMUNERADO",'BD Asistencia'!$C:$C,'Planilla Mensual'!$D13,'BD Asistencia'!$D:$D,">="&'Planilla Mensual'!M13,'BD Asistencia'!$D:$D,"<="&'Planilla Mensual'!N13)-U13 -> 0 | AA13: =+COUNTIFS('BD Asistencia'!$E:$E,"F",'BD Asistencia'!$C:$C,'Planilla Mensual'!$D13,'BD Asistencia'!$D:$D,">="&'Planilla Mensual'!M13,'BD Asistencia'!$D:$D,"<="&'Planilla Mensual'!N13) -> 1 | AB13: =+SUM(S13:AA13) -> 15 | AC13: 12 | AD13: =+Q13/30*SUM(V13:Y13) -> 476.66667 | AE13: =IF(P13="SI",113/2,0) -> 56.5 | AF13: =+(Q13/30*Y13)*2 -> 0 | AG13: 100 | AH13: =+AC13*A13 -> 120 | AI13: =+SUM(AD13:AH13) -> 753.16667 | AJ13: =+V13*IF(RIGHT(F13,2)="N3",16,IF(RIGHT(F13,2)="N2",8,4)) -> 80 | AK13: =V13*30 -> 300 | AL13: =IF(G13="ONP",0,AI13*0.1) -> 75.316667 | AM13: =IF(G13="ONP",0,AI13*1.37%) -> 10.318383 | AN13: =+IF(G13="ONP",AI13*0.13,0) -> 0 | AO13: 0 | AQ13: 280 | AR13: =+SUM(AL13:AQ13) -> 365.63505 | AS13: =AI13-SUM(AL13:AQ13) -> 387.53162 | AT13: =AJ13+AK13 -> 380 | AV13: =AS13+AT13 -> 767.53162 | AX13: =+IF(RIGHT(F13,2)="N3",300,0) -> 0 | AY13: =+AX13/30*SUM(V13:Y13) -> 0 | AZ13: =+R13*(S13+T13) -> 80 | BA13: 0 | BC13: =+AY13+AV13+AZ13+BA13+BB13 -> 847.53162 | BD13: =AI13+AU13+AT13+AY13+AZ13+BA13+BB13 -> 1213.1667 | BE13: =(BC13+AQ13)/(V13+S13) -> 102.50287 | BF13: =+BE13*26 -> 2665.0747 | BG13: =(AV13+AY13+SUM(AL13:AQ13))/V13 -> 113.31667 | BH13: =+(AZ13+BA13)/(S13+T13) -> 80 | BI13: =+BD13/V13 -> 121.31667
A14: 10 | B14: PLANILLA | C14: 71983929 | D14: CHUICA ADANAQUE ANDERSON XAVIER | E14: 33973 | F14: Operador de Maquinaria Agricola N3 | G14: ONP | I14: BCP | J14: 47525665591096 | L14: 46146 | M14: 46143 | N14: 46157 | O14: =+TEXT(M14,"mmmm")&" - "&YEAR(M14)&MONTH(M14) -> Mayo - 20265 | P14: SI | Q14: 1300 | S14: =+COUNTIFS('BD Asistencia'!$E:$E,"A",'BD Asistencia'!$C:$C,'Planilla Mensual'!$D14,'BD Asistencia'!$D:$D,"<"&'Planilla Mensual'!L14) -> 0 | T14: =+COUNTIFS('BD Asistencia'!$E:$E,"DR",'BD Asistencia'!$C:$C,'Planilla Mensual'!$D14,'BD Asistencia'!$D:$D,"<"&L14) -> 0 | U14: =+COUNTIFS('BD Asistencia'!$H:$H,"NO REMUNERADO",'BD Asistencia'!$C:$C,'Planilla Mensual'!$D14,'BD Asistencia'!$D:$D,"<"&L14) -> 3 | V14: =+COUNTIFS('BD Asistencia'!$E:$E,"A",'BD Asistencia'!$C:$C,'Planilla Mensual'!$D14,'BD Asistencia'!$D:$D,">="&'Planilla Mensual'!M14,'BD Asistencia'!$D:$D,"<="&'Planilla Mensual'!N14)-S14 -> 11 | W14: =+COUNTIFS('BD Asistencia'!$E:$E,"DR",'BD Asistencia'!$C:$C,'Planilla Mensual'!$D14,'BD Asistencia'!$D:$D,">="&'Planilla Mensual'!M14,'BD Asistencia'!$D:$D,"<="&'Planilla Mensual'!N14)-T14 -> 1 | X14: =+COUNTIFS('BD Asistencia'!$E:$E,"h",'BD Asistencia'!$C:$C,'Planilla Mensual'!$D14,'BD Asistencia'!$D:$D,">="&'Planilla Mensual'!M14,'BD Asistencia'!$D:$D,"<="&'Planilla Mensual'!N14) -> 0 | Y14: =+COUNTIFS('BD Asistencia'!$E:$E,"h/A",'BD Asistencia'!$C:$C,'Planilla Mensual'!$D14,'BD Asistencia'!$D:$D,">="&'Planilla Mensual'!M14,'BD Asistencia'!$D:$D,"<="&'Planilla Mensual'!N14) -> 0 | Z14: =+COUNTIFS('BD Asistencia'!$H:$H,"NO REMUNERADO",'BD Asistencia'!$C:$C,'Planilla Mensual'!$D14,'BD Asistencia'!$D:$D,">="&'Planilla Mensual'!M14,'BD Asistencia'!$D:$D,"<="&'Planilla Mensual'!N14)-U14 -> 0 | AA14: =+COUNTIFS('BD Asistencia'!$E:$E,"F",'BD Asistencia'!$C:$C,'Planilla Mensual'!$D14,'BD Asistencia'!$D:$D,">="&'Planilla Mensual'!M14,'BD Asistencia'!$D:$D,"<="&'Planilla Mensual'!N14) -> 0 | AB14: =+SUM(S14:AA14) -> 15 | AC14: 4.05 | AD14: =+Q14/30*SUM(V14:Y14) -> 520 | AE14: =IF(P14="SI",113/2,0) -> 56.5 | AF14: =+(Q14/30*Y14)*2 -> 0 | AG14: 200 | AH14: =+AC14*A14 -> 40.5 | AI14: =+SUM(AD14:AH14) -> 817 | AJ14: =+V14*IF(RIGHT(F14,2)="N3",16,IF(RIGHT(F14,2)="N2",8,4)) -> 176 | AK14: =V14*30 -> 330 | AL14: =IF(G14="ONP",0,AI14*0.1) -> 0 | AM14: =IF(G14="ONP",0,AI14*1.37%) -> 0 | AN14: =+IF(G14="ONP",AI14*0.13,0) -> 106.21 | AO14: 0 | AQ14: =180+120 -> 300 | AR14: =+SUM(AL14:AQ14) -> 406.21 | AS14: =AI14-SUM(AL14:AQ14) -> 410.79 | AT14: =AJ14+AK14 -> 506 | AV14: =AS14+AT14 -> 916.79 | AX14: =+IF(RIGHT(F14,2)="N3",300,0) -> 300 | AY14: =+AX14/30*SUM(V14:Y14) -> 120 | AZ14: =+R14*(S14+T14) -> 0 | BA14: 0 | BC14: =+AY14+AV14+AZ14+BA14+BB14 -> 1036.79 | BD14: =AI14+AU14+AT14+AY14+AZ14+BA14+BB14 -> 1443 | BE14: =(BC14+AQ14)/(V14+S14) -> 121.52636 | BF14: =+BE14*26 -> 3159.6855 | BG14: =(AV14+AY14+SUM(AL14:AQ14))/V14 -> 131.18182 | BH14: =+(AZ14+BA14)/(S14+T14) -> #DIV/0! | BI14: =+BD14/V14 -> 131.18182
A15: 10 | B15: PLANILLA | C15: 45952951 | D15: GARCIA RAMOS SEGUNDO MIGUEL | E15: 32777 | F15: Operador de Maquinaria Agricola N3 | G15: SPP PRIMA | H15: 627751SGRCO7 | I15: BCP | J15: 47531606418032 | L15: 46146 | M15: 46143 | N15: 46157 | O15: =+TEXT(M15,"mmmm")&" - "&YEAR(M15)&MONTH(M15) -> Mayo - 20265 | P15: SI | Q15: 1300 | S15: =+COUNTIFS('BD Asistencia'!$E:$E,"A",'BD Asistencia'!$C:$C,'Planilla Mensual'!$D15,'BD Asistencia'!$D:$D,"<"&'Planilla Mensual'!L15) -> 0 | T15: =+COUNTIFS('BD Asistencia'!$E:$E,"DR",'BD Asistencia'!$C:$C,'Planilla Mensual'!$D15,'BD Asistencia'!$D:$D,"<"&L15) -> 0 | U15: =+COUNTIFS('BD Asistencia'!$H:$H,"NO REMUNERADO",'BD Asistencia'!$C:$C,'Planilla Mensual'!$D15,'BD Asistencia'!$D:$D,"<"&L15) -> 3 | V15: =+COUNTIFS('BD Asistencia'!$E:$E,"A",'BD Asistencia'!$C:$C,'Planilla Mensual'!$D15,'BD Asistencia'!$D:$D,">="&'Planilla Mensual'!M15,'BD Asistencia'!$D:$D,"<="&'Planilla Mensual'!N15)-S15 -> 11 | W15: =+COUNTIFS('BD Asistencia'!$E:$E,"DR",'BD Asistencia'!$C:$C,'Planilla Mensual'!$D15,'BD Asistencia'!$D:$D,">="&'Planilla Mensual'!M15,'BD Asistencia'!$D:$D,"<="&'Planilla Mensual'!N15)-T15 -> 1 | X15: =+COUNTIFS('BD Asistencia'!$E:$E,"h",'BD Asistencia'!$C:$C,'Planilla Mensual'!$D15,'BD Asistencia'!$D:$D,">="&'Planilla Mensual'!M15,'BD Asistencia'!$D:$D,"<="&'Planilla Mensual'!N15) -> 0 | Y15: =+COUNTIFS('BD Asistencia'!$E:$E,"h/A",'BD Asistencia'!$C:$C,'Planilla Mensual'!$D15,'BD Asistencia'!$D:$D,">="&'Planilla Mensual'!M15,'BD Asistencia'!$D:$D,"<="&'Planilla Mensual'!N15) -> 0 | Z15: =+COUNTIFS('BD Asistencia'!$H:$H,"NO REMUNERADO",'BD Asistencia'!$C:$C,'Planilla Mensual'!$D15,'BD Asistencia'!$D:$D,">="&'Planilla Mensual'!M15,'BD Asistencia'!$D:$D,"<="&'Planilla Mensual'!N15)-U15 -> 0 | AA15: =+COUNTIFS('BD Asistencia'!$E:$E,"F",'BD Asistencia'!$C:$C,'Planilla Mensual'!$D15,'BD Asistencia'!$D:$D,">="&'Planilla Mensual'!M15,'BD Asistencia'!$D:$D,"<="&'Planilla Mensual'!N15) -> 0 | AB15: =+SUM(S15:AA15) -> 15 | AC15: 4.8 | AD15: =+Q15/30*SUM(V15:Y15) -> 520 | AE15: =IF(P15="SI",113/2,0) -> 56.5 | AF15: =+(Q15/30*Y15)*2 -> 0 | AG15: 200 | AH15: =+AC15*A15 -> 48 | AI15: =+SUM(AD15:AH15) -> 824.5 | AJ15: =+V15*IF(RIGHT(F15,2)="N3",16,IF(RIGHT(F15,2)="N2",8,4)) -> 176 | AK15: =V15*30 -> 330 | AL15: =IF(G15="ONP",0,AI15*0.1) -> 82.45 | AM15: =IF(G15="ONP",0,AI15*1.37%) -> 11.29565 | AN15: =+IF(G15="ONP",AI15*0.13,0) -> 0 | AO15: 0 | AQ15: =180+20 -> 200 | AR15: =+SUM(AL15:AQ15) -> 293.74565 | AS15: =AI15-SUM(AL15:AQ15) -> 530.75435 | AT15: =AJ15+AK15 -> 506 | AV15: =AS15+AT15 -> 1036.7543 | AX15: 300 | AY15: =+AX15/30*SUM(V15:Y15) -> 120 | AZ15: =+R15*(S15+T15) -> 0 | BA15: 0 | BC15: =+AY15+AV15+AZ15+BA15+BB15 -> 1156.7543 | BD15: =AI15+AU15+AT15+AY15+AZ15+BA15+BB15 -> 1450.5 | BE15: =(BC15+AQ15)/(V15+S15) -> 123.3413 | BF15: =+BE15*26 -> 3206.8739 | BG15: =(AV15+AY15+SUM(AL15:AQ15))/V15 -> 131.86364 | BH15: =+(AZ15+BA15)/(S15+T15) -> #DIV/0! | BI15: =+BD15/V15 -> 131.86364
A16: 10 | B16: PLANILLA | C16: 48187021 | D16: CARLOS ROQUE JUNIOR ABEL | E16: 34283 | F16: Operador de Maquinaria Agricola N3 | G16: SPP INTEGRA | H16: 342811JCRLU0 | I16: BCP | J16: 41599043973014 | L16: 46146 | M16: 46143 | N16: 46157 | O16: =+TEXT(M16,"mmmm")&" - "&YEAR(M16)&MONTH(M16) -> Mayo - 20265 | P16: SI | Q16: 1300 | S16: =+COUNTIFS('BD Asistencia'!$E:$E,"A",'BD Asistencia'!$C:$C,'Planilla Mensual'!$D16,'BD Asistencia'!$D:$D,"<"&'Planilla Mensual'!L16) -> 0 | T16: =+COUNTIFS('BD Asistencia'!$E:$E,"DR",'BD Asistencia'!$C:$C,'Planilla Mensual'!$D16,'BD Asistencia'!$D:$D,"<"&L16) -> 0 | U16: =+COUNTIFS('BD Asistencia'!$H:$H,"NO REMUNERADO",'BD Asistencia'!$C:$C,'Planilla Mensual'!$D16,'BD Asistencia'!$D:$D,"<"&L16) -> 3 | V16: =+COUNTIFS('BD Asistencia'!$E:$E,"A",'BD Asistencia'!$C:$C,'Planilla Mensual'!$D16,'BD Asistencia'!$D:$D,">="&'Planilla Mensual'!M16,'BD Asistencia'!$D:$D,"<="&'Planilla Mensual'!N16)-S16 -> 10 | W16: =+COUNTIFS('BD Asistencia'!$E:$E,"DR",'BD Asistencia'!$C:$C,'Planilla Mensual'!$D16,'BD Asistencia'!$D:$D,">="&'Planilla Mensual'!M16,'BD Asistencia'!$D:$D,"<="&'Planilla Mensual'!N16)-T16 -> 1 | X16: =+COUNTIFS('BD Asistencia'!$E:$E,"h",'BD Asistencia'!$C:$C,'Planilla Mensual'!$D16,'BD Asistencia'!$D:$D,">="&'Planilla Mensual'!M16,'BD Asistencia'!$D:$D,"<="&'Planilla Mensual'!N16) -> 0 | Y16: =+COUNTIFS('BD Asistencia'!$E:$E,"h/A",'BD Asistencia'!$C:$C,'Planilla Mensual'!$D16,'BD Asistencia'!$D:$D,">="&'Planilla Mensual'!M16,'BD Asistencia'!$D:$D,"<="&'Planilla Mensual'!N16) -> 0 | Z16: =+COUNTIFS('BD Asistencia'!$H:$H,"NO REMUNERADO",'BD Asistencia'!$C:$C,'Planilla Mensual'!$D16,'BD Asistencia'!$D:$D,">="&'Planilla Mensual'!M16,'BD Asistencia'!$D:$D,"<="&'Planilla Mensual'!N16)-U16 -> 1 | AA16: =+COUNTIFS('BD Asistencia'!$E:$E,"F",'BD Asistencia'!$C:$C,'Planilla Mensual'!$D16,'BD Asistencia'!$D:$D,">="&'Planilla Mensual'!M16,'BD Asistencia'!$D:$D,"<="&'Planilla Mensual'!N16) -> 0 | AB16: =+SUM(S16:AA16) -> 15 | AC16: 8.5 | AD16: =+Q16/30*SUM(V16:Y16) -> 476.66667 | AE16: =IF(P16="SI",113/2,0) -> 56.5 | AF16: =+(Q16/30*Y16)*2 -> 0 | AG16: 200 | AH16: =+AC16*A16 -> 85 | AI16: =+SUM(AD16:AH16) -> 818.16667 | AJ16: =+V16*IF(RIGHT(F16,2)="N3",16,IF(RIGHT(F16,2)="N2",8,4)) -> 160 | AK16: =V16*30 -> 300 | AL16: =IF(G16="ONP",0,AI16*0.1) -> 81.816667 | AM16: =IF(G16="ONP",0,AI16*1.37%) -> 11.208883 | AN16: =+IF(G16="ONP",AI16*0.13,0) -> 0 | AO16: 0 | AQ16: =180+20 -> 200 | AR16: =+SUM(AL16:AQ16) -> 293.02555 | AS16: =AI16-SUM(AL16:AQ16) -> 525.14112 | AT16: =AJ16+AK16 -> 460 | AV16: =AS16+AT16 -> 985.14112 | AX16: =+IF(RIGHT(F16,2)="N3",300,0) -> 300 | AY16: =+AX16/30*SUM(V16:Y16) -> 110 | AZ16: =+R16*(S16+T16) -> 0 | BA16: 0 | BC16: =+AY16+AV16+AZ16+BA16+BB16 -> 1095.1411 | BD16: =AI16+AU16+AT16+AY16+AZ16+BA16+BB16 -> 1388.1667 | BE16: =(BC16+AQ16)/(V16+S16) -> 129.51411 | BF16: =+BE16*26 -> 3367.3669 | BG16: =(AV16+AY16+SUM(AL16:AQ16))/V16 -> 138.81667 | BH16: =+(AZ16+BA16)/(S16+T16) -> #DIV/0! | BI16: =+BD16/V16 -> 138.81667
A17: 10 | B17: PLANILLA | C17: 77709008 | D17: CRUZ VARGAS MARCO ANTONIO | E17: 35588 | F17: Operador de Maquinaria Agricola N3 | G17: SPP INTEGRA | H17: 655861MCVZG3 | I17: BCP | J17: 57073429072032 | L17: 46146 | M17: 46143 | N17: 46157 | O17: =+TEXT(M17,"mmmm")&" - "&YEAR(M17)&MONTH(M17) -> Mayo - 20265 | P17: SI | Q17: 1300 | S17: =+COUNTIFS('BD Asistencia'!$E:$E,"A",'BD Asistencia'!$C:$C,'Planilla Mensual'!$D17,'BD Asistencia'!$D:$D,"<"&'Planilla Mensual'!L17) -> 0 | T17: =+COUNTIFS('BD Asistencia'!$E:$E,"DR",'BD Asistencia'!$C:$C,'Planilla Mensual'!$D17,'BD Asistencia'!$D:$D,"<"&L17) -> 0 | U17: =+COUNTIFS('BD Asistencia'!$H:$H,"NO REMUNERADO",'BD Asistencia'!$C:$C,'Planilla Mensual'!$D17,'BD Asistencia'!$D:$D,"<"&L17) -> 3 | V17: 7 | W17: 1 | X17: =+COUNTIFS('BD Asistencia'!$E:$E,"h",'BD Asistencia'!$C:$C,'Planilla Mensual'!$D17,'BD Asistencia'!$D:$D,">="&'Planilla Mensual'!M17,'BD Asistencia'!$D:$D,"<="&'Planilla Mensual'!N17) -> 0 | Y17: =+COUNTIFS('BD Asistencia'!$E:$E,"h/A",'BD Asistencia'!$C:$C,'Planilla Mensual'!$D17,'BD Asistencia'!$D:$D,">="&'Planilla Mensual'!M17,'BD Asistencia'!$D:$D,"<="&'Planilla Mensual'!N17) -> 0 | Z17: 4 | AA17: =+COUNTIFS('BD Asistencia'!$E:$E,"F",'BD Asistencia'!$C:$C,'Planilla Mensual'!$D17,'BD Asistencia'!$D:$D,">="&'Planilla Mensual'!M17,'BD Asistencia'!$D:$D,"<="&'Planilla Mensual'!N17) -> 0 | AB17: =+SUM(S17:AA17) -> 15 | AD17: =+Q17/30*SUM(V17:Y17) -> 346.66667 | AE17: =IF(P17="SI",113/2,0) -> 56.5 | AF17: =+(Q17/30*Y17)*2 -> 0 | AG17: 0 | AH17: =+AC17*A17 -> 0 | AI17: =+SUM(AD17:AH17) -> 403.16667 | AJ17: =+V17*IF(RIGHT(F17,2)="N3",16,IF(RIGHT(F17,2)="N2",8,4)) -> 112 | AK17: =V17*30 -> 210 | AL17: =IF(G17="ONP",0,AI17*0.1) -> 40.316667 | AM17: =IF(G17="ONP",0,AI17*1.37%) -> 5.5233833 | AN17: =+IF(G17="ONP",AI17*0.13,0) -> 0 | AO17: 0 | AQ17: =30+64 -> 94 | AR17: =+SUM(AL17:AQ17) -> 139.84005 | AS17: =AI17-SUM(AL17:AQ17) -> 263.32662 | AT17: =AJ17+AK17 -> 322 | AV17: =AS17+AT17 -> 585.32662 | AX17: =+IF(RIGHT(F17,2)="N3",300,0) -> 300 | AY17: =+AX17/30*SUM(V17:Y17) -> 80 | AZ17: =+R17*(S17+T17) -> 0 | BA17: 0 | BC17: =+AY17+AV17+AZ17+BA17+BB17 -> 665.32662 | BD17: =AI17+AU17+AT17+AY17+AZ17+BA17+BB17 -> 805.16667 | BE17: =(BC17+AQ17)/(V17+S17) -> 108.47523 | BF17: =+BE17*26 -> 2820.356 | BG17: =(AV17+AY17+SUM(AL17:AQ17))/V17 -> 115.02381 | BH17: =+(AZ17+BA17)/(S17+T17) -> #DIV/0! | BI17: =+BD17/V17 -> 115.02381
A18: 10 | B18: PLANILLA | C18: 77236592 | D18: BERNA TANTARICO BENJAMIN | E18: 34712 | F18: Operador de Maquinaria Agricola N2 | G18: SPP HABITAT | H18: 647101BBTNT4 | I18: BCP | J18: 30593206658025 | L18: 46153 | M18: 46143 | N18: 46157 | O18: =+TEXT(M18,"mmmm")&" - "&YEAR(M18)&MONTH(M18) -> Mayo - 20265 | P18: NO | Q18: 1300 | R18: 80 | S18: =+COUNTIFS('BD Asistencia'!$E:$E,"A",'BD Asistencia'!$C:$C,'Planilla Mensual'!$D18,'BD Asistencia'!$D:$D,"<"&'Planilla Mensual'!L18) -> 1 | T18: =+COUNTIFS('BD Asistencia'!$E:$E,"DR",'BD Asistencia'!$C:$C,'Planilla Mensual'!$D18,'BD Asistencia'!$D:$D,"<"&L18) -> 0 | U18: =+COUNTIFS('BD Asistencia'!$H:$H,"NO REMUNERADO",'BD Asistencia'!$C:$C,'Planilla Mensual'!$D18,'BD Asistencia'!$D:$D,"<"&L18) -> 9 | V18: 5 | W18: =+COUNTIFS('BD Asistencia'!$E:$E,"DR",'BD Asistencia'!$C:$C,'Planilla Mensual'!$D18,'BD Asistencia'!$D:$D,">="&'Planilla Mensual'!M18,'BD Asistencia'!$D:$D,"<="&'Planilla Mensual'!N18)-T18 -> 0 | X18: =+COUNTIFS('BD Asistencia'!$E:$E,"h",'BD Asistencia'!$C:$C,'Planilla Mensual'!$D18,'BD Asistencia'!$D:$D,">="&'Planilla Mensual'!M18,'BD Asistencia'!$D:$D,"<="&'Planilla Mensual'!N18) -> 0 | Y18: =+COUNTIFS('BD Asistencia'!$E:$E,"h/A",'BD Asistencia'!$C:$C,'Planilla Mensual'!$D18,'BD Asistencia'!$D:$D,">="&'Planilla Mensual'!M18,'BD Asistencia'!$D:$D,"<="&'Planilla Mensual'!N18) -> 0 | Z18: =+COUNTIFS('BD Asistencia'!$H:$H,"NO REMUNERADO",'BD Asistencia'!$C:$C,'Planilla Mensual'!$D18,'BD Asistencia'!$D:$D,">="&'Planilla Mensual'!M18,'BD Asistencia'!$D:$D,"<="&'Planilla Mensual'!N18)-U18 -> 0 | AA18: =+COUNTIFS('BD Asistencia'!$E:$E,"F",'BD Asistencia'!$C:$C,'Planilla Mensual'!$D18,'BD Asistencia'!$D:$D,">="&'Planilla Mensual'!M18,'BD Asistencia'!$D:$D,"<="&'Planilla Mensual'!N18) -> 0 | AB18: =+SUM(S18:AA18) -> 15 | AC18: 7 | AD18: =+Q18/30*SUM(V18:Y18) -> 216.66667 | AE18: =IF(P18="SI",113/2,0) -> 0 | AF18: =+(Q18/30*Y18)*2 -> 0 | AG18: 100 | AH18: =+AC18*A18 -> 70 | AI18: =+SUM(AD18:AH18) -> 386.66667 | AJ18: =+V18*IF(RIGHT(F18,2)="N3",16,IF(RIGHT(F18,2)="N2",8,4)) -> 40 | AK18: =V18*30 -> 150 | AL18: =IF(G18="ONP",0,AI18*0.1) -> 38.666667 | AM18: =IF(G18="ONP",0,AI18*1.37%) -> 5.2973333 | AN18: =+IF(G18="ONP",AI18*0.13,0) -> 0 | AO18: 0 | AQ18: 140 | AR18: =+SUM(AL18:AQ18) -> 183.964 | AS18: =AI18-SUM(AL18:AQ18) -> 202.70267 | AT18: =AJ18+AK18 -> 190 | AV18: =AS18+AT18 -> 392.70267 | AX18: =+IF(RIGHT(F18,2)="N3",300,0) -> 0 | AY18: =+AX18/30*SUM(V18:Y18) -> 0 | AZ18: =+R18*(S18+T18) -> 80 | BA18: 0 | BC18: =+AY18+AV18+AZ18+BA18+BB18 -> 472.70267 | BD18: =AI18+AU18+AT18+AY18+AZ18+BA18+BB18 -> 656.66667 | BE18: =(BC18+AQ18)/(V18+S18) -> 102.11711 | BF18: =+BE18*26 -> 2655.0449 | BG18: =(AV18+AY18+SUM(AL18:AQ18))/V18 -> 115.33333 | BH18: =+(AZ18+BA18)/(S18+T18) -> 80 | BI18: =+BD18/V18 -> 131.33333
A19: 10 | B19: PLANILLA | C19: 70828937 | D19: HERNANDEZ GOMEZ LUIS JHONATAN | E19: 36383 | F19: Operador de Maquinaria Agricola N3 | G19: SPP PRIMA | H19: 663811LHGNE7 | I19: BCP | J19: 47515071114006 | L19: 46153 | M19: 46143 | N19: 46157 | O19: =+TEXT(M19,"mmmm")&" - "&YEAR(M19)&MONTH(M19) -> Mayo - 20265 | P19: SI | Q19: 1300 | S19: =+COUNTIFS('BD Asistencia'!$E:$E,"A",'BD Asistencia'!$C:$C,'Planilla Mensual'!$D19,'BD Asistencia'!$D:$D,"<"&'Planilla Mensual'!L19) -> 0 | T19: =+COUNTIFS('BD Asistencia'!$E:$E,"DR",'BD Asistencia'!$C:$C,'Planilla Mensual'!$D19,'BD Asistencia'!$D:$D,"<"&L19) -> 0 | U19: =+COUNTIFS('BD Asistencia'!$H:$H,"NO REMUNERADO",'BD Asistencia'!$C:$C,'Planilla Mensual'!$D19,'BD Asistencia'!$D:$D,"<"&L19) -> 10 | V19: =+COUNTIFS('BD Asistencia'!$E:$E,"A",'BD Asistencia'!$C:$C,'Planilla Mensual'!$D19,'BD Asistencia'!$D:$D,">="&'Planilla Mensual'!M19,'BD Asistencia'!$D:$D,"<="&'Planilla Mensual'!N19)-S19 -> 5 | W19: =+COUNTIFS('BD Asistencia'!$E:$E,"DR",'BD Asistencia'!$C:$C,'Planilla Mensual'!$D19,'BD Asistencia'!$D:$D,">="&'Planilla Mensual'!M19,'BD Asistencia'!$D:$D,"<="&'Planilla Mensual'!N19)-T19 -> 0 | X19: =+COUNTIFS('BD Asistencia'!$E:$E,"h",'BD Asistencia'!$C:$C,'Planilla Mensual'!$D19,'BD Asistencia'!$D:$D,">="&'Planilla Mensual'!M19,'BD Asistencia'!$D:$D,"<="&'Planilla Mensual'!N19) -> 0 | Y19: =+COUNTIFS('BD Asistencia'!$E:$E,"h/A",'BD Asistencia'!$C:$C,'Planilla Mensual'!$D19,'BD Asistencia'!$D:$D,">="&'Planilla Mensual'!M19,'BD Asistencia'!$D:$D,"<="&'Planilla Mensual'!N19) -> 0 | Z19: =+COUNTIFS('BD Asistencia'!$H:$H,"NO REMUNERADO",'BD Asistencia'!$C:$C,'Planilla Mensual'!$D19,'BD Asistencia'!$D:$D,">="&'Planilla Mensual'!M19,'BD Asistencia'!$D:$D,"<="&'Planilla Mensual'!N19)-U19 -> 0 | AA19: =+COUNTIFS('BD Asistencia'!$E:$E,"F",'BD Asistencia'!$C:$C,'Planilla Mensual'!$D19,'BD Asistencia'!$D:$D,">="&'Planilla Mensual'!M19,'BD Asistencia'!$D:$D,"<="&'Planilla Mensual'!N19) -> 0 | AB19: =+SUM(S19:AA19) -> 15 | AD19: =+Q19/30*SUM(V19:Y19) -> 216.66667 | AE19: =IF(P19="SI",113/2,0) -> 56.5 | AF19: =+(Q19/30*Y19)*2 -> 0 | AG19: 100 | AH19: =+AC19*A19 -> 0 | AI19: =+SUM(AD19:AH19) -> 373.16667 | AJ19: =+V19*IF(RIGHT(F19,2)="N3",16,IF(RIGHT(F19,2)="N2",8,4)) -> 80 | AK19: =V19*30 -> 150 | AL19: =IF(G19="ONP",0,AI19*0.1) -> 37.316667 | AM19: =IF(G19="ONP",0,AI19*1.37%) -> 5.1123833 | AN19: =+IF(G19="ONP",AI19*0.13,0) -> 0 | AO19: 0 | AQ19: 80 | AR19: =+SUM(AL19:AQ19) -> 122.42905 | AS19: =AI19-SUM(AL19:AQ19) -> 250.73762 | AT19: =AJ19+AK19 -> 230 | AV19: =AS19+AT19 -> 480.73762 | AX19: =+IF(RIGHT(F19,2)="N3",300,0) -> 300 | AY19: =+AX19/30*SUM(V19:Y19) -> 50 | AZ19: =+R19*(S19+T19) -> 0 | BA19: 0 | BC19: =+AY19+AV19+AZ19+BA19+BB19 -> 530.73762 | BD19: =AI19+AU19+AT19+AY19+AZ19+BA19+BB19 -> 653.16667 | BE19: =(BC19+AQ19)/(V19+S19) -> 122.14752 | BF19: =+BE19*26 -> 3175.8356 | BG19: =(AV19+AY19+SUM(AL19:AQ19))/V19 -> 130.63333 | BH19: =+(AZ19+BA19)/(S19+T19) -> #DIV/0! | BI19: =+BD19/V19 -> 130.63333
A20: 10 | B20: PENDIENTE | C20: 43070165 | D20: CURO PAZ FELIPE | E20: 45784 | I20: BCP | J20: 57098472871099 | L20: 46158 | M20: 46143 | N20: 46157 | O20: =+TEXT(M20,"mmmm")&" - "&YEAR(M20)&MONTH(M20) -> Mayo - 20265 | P20: SI | R20: 90 | S20: =+COUNTIFS('BD Asistencia'!$E:$E,"A",'BD Asistencia'!$C:$C,'Planilla Mensual'!$D20,'BD Asistencia'!$D:$D,"<"&'Planilla Mensual'!L20) -> 12 | T20: =+COUNTIFS('BD Asistencia'!$E:$E,"DR",'BD Asistencia'!$C:$C,'Planilla Mensual'!$D20,'BD Asistencia'!$D:$D,"<"&L20) -> 3 | U20: =+COUNTIFS('BD Asistencia'!$H:$H,"NO REMUNERADO",'BD Asistencia'!$C:$C,'Planilla Mensual'!$D20,'BD Asistencia'!$D:$D,"<"&L20) -> 0 | V20: =+COUNTIFS('BD Asistencia'!$E:$E,"A",'BD Asistencia'!$C:$C,'Planilla Mensual'!$D20,'BD Asistencia'!$D:$D,">="&'Planilla Mensual'!M20,'BD Asistencia'!$D:$D,"<="&'Planilla Mensual'!N20)-S20 -> 0 | W20: =+COUNTIFS('BD Asistencia'!$E:$E,"DR",'BD Asistencia'!$C:$C,'Planilla Mensual'!$D20,'BD Asistencia'!$D:$D,">="&'Planilla Mensual'!M20,'BD Asistencia'!$D:$D,"<="&'Planilla Mensual'!N20)-T20 -> 0 | X20: =+COUNTIFS('BD Asistencia'!$E:$E,"h",'BD Asistencia'!$C:$C,'Planilla Mensual'!$D20,'BD Asistencia'!$D:$D,">="&'Planilla Mensual'!M20,'BD Asistencia'!$D:$D,"<="&'Planilla Mensual'!N20) -> 0 | Y20: =+COUNTIFS('BD Asistencia'!$E:$E,"h/A",'BD Asistencia'!$C:$C,'Planilla Mensual'!$D20,'BD Asistencia'!$D:$D,">="&'Planilla Mensual'!M20,'BD Asistencia'!$D:$D,"<="&'Planilla Mensual'!N20) -> 0 | Z20: =+COUNTIFS('BD Asistencia'!$H:$H,"NO REMUNERADO",'BD Asistencia'!$C:$C,'Planilla Mensual'!$D20,'BD Asistencia'!$D:$D,">="&'Planilla Mensual'!M20,'BD Asistencia'!$D:$D,"<="&'Planilla Mensual'!N20)-U20 -> 0 | AA20: =+COUNTIFS('BD Asistencia'!$E:$E,"F",'BD Asistencia'!$C:$C,'Planilla Mensual'!$D20,'BD Asistencia'!$D:$D,">="&'Planilla Mensual'!M20,'BD Asistencia'!$D:$D,"<="&'Planilla Mensual'!N20) -> 0 | AB20: =+SUM(S20:AA20) -> 15 | AR20: =+SUM(AL20:AQ20) -> 0 | AS20: =AI20-SUM(AL20:AQ20) -> 0 | AT20: =AJ20+AK20 -> 0 | AV20: =AS20+AT20 -> 0 | AZ20: =+R20*(S20+T20) -> 1350 | BB20: =+AC20*A20 -> 0 | BC20: =+AY20+AV20+AZ20+BA20+BB20 -> 1350 | BD20: =AI20+AU20+AT20+AY20+AZ20+BA20+BB20 -> 1350 | BG20: =(AV20+AY20+SUM(AL20:AQ20))/V20 -> #DIV/0! | BH20: =+(AZ20+BA20)/(S20+T20) -> 90 | BI20: =25+15 -> 40
A21: 18 | B21: PENDIENTE | C21: 47665126 | D21: GARCIA RAMOS JOSE ISMAEL | E21: 33994 | I21: BCP | J21: 47538222882029 | L21: 46158 | M21: 46143 | N21: 46157 | O21: =+TEXT(M21,"mmmm")&" - "&YEAR(M21)&MONTH(M21) -> Mayo - 20265 | P21: SI | R21: 80 | S21: =+COUNTIFS('BD Asistencia'!$E:$E,"A",'BD Asistencia'!$C:$C,'Planilla Mensual'!$D21,'BD Asistencia'!$D:$D,"<"&'Planilla Mensual'!L21) -> 14 | T21: =+COUNTIFS('BD Asistencia'!$E:$E,"DR",'BD Asistencia'!$C:$C,'Planilla Mensual'!$D21,'BD Asistencia'!$D:$D,"<"&L21) -> 1 | U21: =+COUNTIFS('BD Asistencia'!$H:$H,"NO REMUNERADO",'BD Asistencia'!$C:$C,'Planilla Mensual'!$D21,'BD Asistencia'!$D:$D,"<"&L21) -> 0 | V21: =+COUNTIFS('BD Asistencia'!$E:$E,"A",'BD Asistencia'!$C:$C,'Planilla Mensual'!$D21,'BD Asistencia'!$D:$D,">="&'Planilla Mensual'!M21,'BD Asistencia'!$D:$D,"<="&'Planilla Mensual'!N21)-S21 -> 0 | W21: =+COUNTIFS('BD Asistencia'!$E:$E,"DR",'BD Asistencia'!$C:$C,'Planilla Mensual'!$D21,'BD Asistencia'!$D:$D,">="&'Planilla Mensual'!M21,'BD Asistencia'!$D:$D,"<="&'Planilla Mensual'!N21)-T21 -> 0 | X21: =+COUNTIFS('BD Asistencia'!$E:$E,"h",'BD Asistencia'!$C:$C,'Planilla Mensual'!$D21,'BD Asistencia'!$D:$D,">="&'Planilla Mensual'!M21,'BD Asistencia'!$D:$D,"<="&'Planilla Mensual'!N21) -> 0 | Y21: =+COUNTIFS('BD Asistencia'!$E:$E,"h/A",'BD Asistencia'!$C:$C,'Planilla Mensual'!$D21,'BD Asistencia'!$D:$D,">="&'Planilla Mensual'!M21,'BD Asistencia'!$D:$D,"<="&'Planilla Mensual'!N21) -> 0 | Z21: =+COUNTIFS('BD Asistencia'!$H:$H,"NO REMUNERADO",'BD Asistencia'!$C:$C,'Planilla Mensual'!$D21,'BD Asistencia'!$D:$D,">="&'Planilla Mensual'!M21,'BD Asistencia'!$D:$D,"<="&'Planilla Mensual'!N21)-U21 -> 0 | AA21: =+COUNTIFS('BD Asistencia'!$E:$E,"F",'BD Asistencia'!$C:$C,'Planilla Mensual'!$D21,'BD Asistencia'!$D:$D,">="&'Planilla Mensual'!M21,'BD Asistencia'!$D:$D,"<="&'Planilla Mensual'!N21) -> 0 | AB21: =+SUM(S21:AA21) -> 15 | AC21: 3 | AR21: =+SUM(AL21:AQ21) -> 0 | AS21: =AI21-SUM(AL21:AQ21) -> 0 | AT21: =AJ21+AK21 -> 0 | AV21: =AS21+AT21 -> 0 | AZ21: =+R21*(S21+T21) -> 1200 | BB21: =+AC21*A21 -> 54 | BC21: =+AY21+AV21+AZ21+BA21+BB21 -> 1254 | BD21: =AI21+AU21+AT21+AY21+AZ21+BA21+BB21 -> 1254 | BG21: =(AV21+AY21+SUM(AL21:AQ21))/V21 -> #DIV/0! | BH21: =+(AZ21+BA21)/(S21+T21) -> 80
A22: 10 | B22: PENDIENTE | C22: 8123707 | D22: GOLINDANO MARQUEZ JUAN CARLOS | E22: 32714 | I22: BCP | J22: 57007918639078 | L22: 46158 | M22: 46143 | N22: 46157 | O22: =+TEXT(M22,"mmmm")&" - "&YEAR(M22)&MONTH(M22) -> Mayo - 20265 | P22: SI | R22: 80 | S22: =+COUNTIFS('BD Asistencia'!$E:$E,"A",'BD Asistencia'!$C:$C,'Planilla Mensual'!$D22,'BD Asistencia'!$D:$D,"<"&'Planilla Mensual'!L22) -> 7 | T22: =+COUNTIFS('BD Asistencia'!$E:$E,"DR",'BD Asistencia'!$C:$C,'Planilla Mensual'!$D22,'BD Asistencia'!$D:$D,"<"&L22) -> 4 | U22: =+COUNTIFS('BD Asistencia'!$H:$H,"NO REMUNERADO",'BD Asistencia'!$C:$C,'Planilla Mensual'!$D22,'BD Asistencia'!$D:$D,"<"&L22) -> 4 | V22: =+COUNTIFS('BD Asistencia'!$E:$E,"A",'BD Asistencia'!$C:$C,'Planilla Mensual'!$D22,'BD Asistencia'!$D:$D,">="&'Planilla Mensual'!M22,'BD Asistencia'!$D:$D,"<="&'Planilla Mensual'!N22)-S22 -> 0 | W22: =+COUNTIFS('BD Asistencia'!$E:$E,"DR",'BD Asistencia'!$C:$C,'Planilla Mensual'!$D22,'BD Asistencia'!$D:$D,">="&'Planilla Mensual'!M22,'BD Asistencia'!$D:$D,"<="&'Planilla Mensual'!N22)-T22 -> 0 | X22: =+COUNTIFS('BD Asistencia'!$E:$E,"h",'BD Asistencia'!$C:$C,'Planilla Mensual'!$D22,'BD Asistencia'!$D:$D,">="&'Planilla Mensual'!M22,'BD Asistencia'!$D:$D,"<="&'Planilla Mensual'!N22) -> 0 | Y22: =+COUNTIFS('BD Asistencia'!$E:$E,"h/A",'BD Asistencia'!$C:$C,'Planilla Mensual'!$D22,'BD Asistencia'!$D:$D,">="&'Planilla Mensual'!M22,'BD Asistencia'!$D:$D,"<="&'Planilla Mensual'!N22) -> 0 | Z22: =+COUNTIFS('BD Asistencia'!$H:$H,"NO REMUNERADO",'BD Asistencia'!$C:$C,'Planilla Mensual'!$D22,'BD Asistencia'!$D:$D,">="&'Planilla Mensual'!M22,'BD Asistencia'!$D:$D,"<="&'Planilla Mensual'!N22)-U22 -> 0 | AA22: =+COUNTIFS('BD Asistencia'!$E:$E,"F",'BD Asistencia'!$C:$C,'Planilla Mensual'!$D22,'BD Asistencia'!$D:$D,">="&'Planilla Mensual'!M22,'BD Asistencia'!$D:$D,"<="&'Planilla Mensual'!N22) -> 0 | AB22: =+SUM(S22:AA22) -> 15 | AR22: =+SUM(AL22:AQ22) -> 0 | AS22: =AI22-SUM(AL22:AQ22) -> 0 | AT22: =AJ22+AK22 -> 0 | AV22: =AS22+AT22 -> 0 | AZ22: =+R22*(S22+T22) -> 880 | BB22: =+AC22*A22 -> 0 | BC22: =+AY22+AV22+AZ22+BA22+BB22 -> 880 | BD22: =AI22+AU22+AT22+AY22+AZ22+BA22+BB22 -> 880 | BG22: =(AV22+AY22+SUM(AL22:AQ22))/V22 -> #DIV/0! | BH22: =+(AZ22+BA22)/(S22+T22) -> 80
A23: 10 | B23: PENDIENTE | D23: YUNCA ALFARO JOSE LUIS | I23: BBVA | J23: 1100300200308710 | L23: 46158 | M23: 46143 | N23: 46157 | O23: =+TEXT(M23,"mmmm")&" - "&YEAR(M23)&MONTH(M23) -> Mayo - 20265 | R23: 100 | S23: =+COUNTIFS('BD Asistencia'!$E:$E,"A",'BD Asistencia'!$C:$C,'Planilla Mensual'!$D23,'BD Asistencia'!$D:$D,"<"&'Planilla Mensual'!L23) -> 2 | T23: =+COUNTIFS('BD Asistencia'!$E:$E,"DR",'BD Asistencia'!$C:$C,'Planilla Mensual'!$D23,'BD Asistencia'!$D:$D,"<"&L23) -> 0 | U23: =+COUNTIFS('BD Asistencia'!$H:$H,"NO REMUNERADO",'BD Asistencia'!$C:$C,'Planilla Mensual'!$D23,'BD Asistencia'!$D:$D,"<"&L23) -> 13 | V23: =+COUNTIFS('BD Asistencia'!$E:$E,"A",'BD Asistencia'!$C:$C,'Planilla Mensual'!$D23,'BD Asistencia'!$D:$D,">="&'Planilla Mensual'!M23,'BD Asistencia'!$D:$D,"<="&'Planilla Mensual'!N23)-S23 -> 0 | W23: =+COUNTIFS('BD Asistencia'!$E:$E,"DR",'BD Asistencia'!$C:$C,'Planilla Mensual'!$D23,'BD Asistencia'!$D:$D,">="&'Planilla Mensual'!M23,'BD Asistencia'!$D:$D,"<="&'Planilla Mensual'!N23)-T23 -> 0 | X23: =+COUNTIFS('BD Asistencia'!$E:$E,"h",'BD Asistencia'!$C:$C,'Planilla Mensual'!$D23,'BD Asistencia'!$D:$D,">="&'Planilla Mensual'!M23,'BD Asistencia'!$D:$D,"<="&'Planilla Mensual'!N23) -> 0 | Y23: =+COUNTIFS('BD Asistencia'!$E:$E,"h/A",'BD Asistencia'!$C:$C,'Planilla Mensual'!$D23,'BD Asistencia'!$D:$D,">="&'Planilla Mensual'!M23,'BD Asistencia'!$D:$D,"<="&'Planilla Mensual'!N23) -> 0 | Z23: =+COUNTIFS('BD Asistencia'!$H:$H,"NO REMUNERADO",'BD Asistencia'!$C:$C,'Planilla Mensual'!$D23,'BD Asistencia'!$D:$D,">="&'Planilla Mensual'!M23,'BD Asistencia'!$D:$D,"<="&'Planilla Mensual'!N23)-U23 -> 0 | AA23: =+COUNTIFS('BD Asistencia'!$E:$E,"F",'BD Asistencia'!$C:$C,'Planilla Mensual'!$D23,'BD Asistencia'!$D:$D,">="&'Planilla Mensual'!M23,'BD Asistencia'!$D:$D,"<="&'Planilla Mensual'!N23) -> 0 | AB23: =+SUM(S23:AA23) -> 15 | AC23: 1 | AR23: =+SUM(AL23:AQ23) -> 0 | AS23: =AI23-SUM(AL23:AQ23) -> 0 | AT23: =AJ23+AK23 -> 0 | AV23: =AS23+AT23 -> 0 | AZ23: =+R23*(S23+T23) -> 200 | BB23: =+AC23*A23 -> 10 | BC23: =+AY23+AV23+AZ23+BA23+BB23 -> 210 | BD23: =AI23+AU23+AT23+AY23+AZ23+BA23+BB23 -> 210 | BG23: =(AV23+AY23+SUM(AL23:AQ23))/V23 -> #DIV/0! | BH23: =+(AZ23+BA23)/(S23+T23) -> 100
A24: 18 | B24: PENDIENTE | C24: 75460380 | D24: LALUPU ZAPATA CARLOS JAVIER | E24: 37038 | I24: BCP | J24: 47574561946054 | L24: 46158 | M24: 46143 | N24: 46157 | O24: =+TEXT(M24,"mmmm")&" - "&YEAR(M24)&MONTH(M24) -> Mayo - 20265 | P24: NO | R24: 80 | S24: =+COUNTIFS('BD Asistencia'!$E:$E,"A",'BD Asistencia'!$C:$C,'Planilla Mensual'!$D24,'BD Asistencia'!$D:$D,"<"&'Planilla Mensual'!L24) -> 14 | T24: =+COUNTIFS('BD Asistencia'!$E:$E,"DR",'BD Asistencia'!$C:$C,'Planilla Mensual'!$D24,'BD Asistencia'!$D:$D,"<"&L24) -> 1 | U24: =+COUNTIFS('BD Asistencia'!$H:$H,"NO REMUNERADO",'BD Asistencia'!$C:$C,'Planilla Mensual'!$D24,'BD Asistencia'!$D:$D,"<"&L24) -> 0 | V24: =+COUNTIFS('BD Asistencia'!$E:$E,"A",'BD Asistencia'!$C:$C,'Planilla Mensual'!$D24,'BD Asistencia'!$D:$D,">="&'Planilla Mensual'!M24,'BD Asistencia'!$D:$D,"<="&'Planilla Mensual'!N24)-S24 -> 0 | W24: =+COUNTIFS('BD Asistencia'!$E:$E,"DR",'BD Asistencia'!$C:$C,'Planilla Mensual'!$D24,'BD Asistencia'!$D:$D,">="&'Planilla Mensual'!M24,'BD Asistencia'!$D:$D,"<="&'Planilla Mensual'!N24)-T24 -> 0 | X24: =+COUNTIFS('BD Asistencia'!$E:$E,"h",'BD Asistencia'!$C:$C,'Planilla Mensual'!$D24,'BD Asistencia'!$D:$D,">="&'Planilla Mensual'!M24,'BD Asistencia'!$D:$D,"<="&'Planilla Mensual'!N24) -> 0 | Y24: =+COUNTIFS('BD Asistencia'!$E:$E,"h/A",'BD Asistencia'!$C:$C,'Planilla Mensual'!$D24,'BD Asistencia'!$D:$D,">="&'Planilla Mensual'!M24,'BD Asistencia'!$D:$D,"<="&'Planilla Mensual'!N24) -> 0 | Z24: =+COUNTIFS('BD Asistencia'!$H:$H,"NO REMUNERADO",'BD Asistencia'!$C:$C,'Planilla Mensual'!$D24,'BD Asistencia'!$D:$D,">="&'Planilla Mensual'!M24,'BD Asistencia'!$D:$D,"<="&'Planilla Mensual'!N24)-U24 -> 0 | AA24: =+COUNTIFS('BD Asistencia'!$E:$E,"F",'BD Asistencia'!$C:$C,'Planilla Mensual'!$D24,'BD Asistencia'!$D:$D,">="&'Planilla Mensual'!M24,'BD Asistencia'!$D:$D,"<="&'Planilla Mensual'!N24) -> 0 | AB24: =+SUM(S24:AA24) -> 15 | AR24: =+SUM(AL24:AQ24) -> 0 | AS24: =AI24-SUM(AL24:AQ24) -> 0 | AT24: =AJ24+AK24 -> 0 | AV24: =AS24+AT24 -> 0 | AZ24: =+R24*(S24+T24) -> 1200 | BB24: =+AC24*A24 -> 0 | BC24: =+AY24+AV24+AZ24+BA24+BB24 -> 1200 | BD24: =AI24+AU24+AT24+AY24+AZ24+BA24+BB24 -> 1200 | BG24: =(AV24+AY24+SUM(AL24:AQ24))/V24 -> #DIV/0! | BH24: =+(AZ24+BA24)/(S24+T24) -> 80
A25: 18 | B25: PENDIENTE | C25: 74658514 | D25: LEYVA CARRERA MARIANO YOEL | E25: 37418 | I25: BBVA | J25: 1105790208095370 | L25: 46158 | M25: 46143 | N25: 46157 | O25: =+TEXT(M25,"mmmm")&" - "&YEAR(M25)&MONTH(M25) -> Mayo - 20265 | P25: NO | R25: 80 | S25: =+COUNTIFS('BD Asistencia'!$E:$E,"A",'BD Asistencia'!$C:$C,'Planilla Mensual'!$D25,'BD Asistencia'!$D:$D,"<"&'Planilla Mensual'!L25) -> 14 | T25: =+COUNTIFS('BD Asistencia'!$E:$E,"DR",'BD Asistencia'!$C:$C,'Planilla Mensual'!$D25,'BD Asistencia'!$D:$D,"<"&L25) -> 1 | U25: =+COUNTIFS('BD Asistencia'!$H:$H,"NO REMUNERADO",'BD Asistencia'!$C:$C,'Planilla Mensual'!$D25,'BD Asistencia'!$D:$D,"<"&L25) -> 0 | V25: =+COUNTIFS('BD Asistencia'!$E:$E,"A",'BD Asistencia'!$C:$C,'Planilla Mensual'!$D25,'BD Asistencia'!$D:$D,">="&'Planilla Mensual'!M25,'BD Asistencia'!$D:$D,"<="&'Planilla Mensual'!N25)-S25 -> 0 | W25: =+COUNTIFS('BD Asistencia'!$E:$E,"DR",'BD Asistencia'!$C:$C,'Planilla Mensual'!$D25,'BD Asistencia'!$D:$D,">="&'Planilla Mensual'!M25,'BD Asistencia'!$D:$D,"<="&'Planilla Mensual'!N25)-T25 -> 0 | X25: =+COUNTIFS('BD Asistencia'!$E:$E,"h",'BD Asistencia'!$C:$C,'Planilla Mensual'!$D25,'BD Asistencia'!$D:$D,">="&'Planilla Mensual'!M25,'BD Asistencia'!$D:$D,"<="&'Planilla Mensual'!N25) -> 0 | Y25: =+COUNTIFS('BD Asistencia'!$E:$E,"h/A",'BD Asistencia'!$C:$C,'Planilla Mensual'!$D25,'BD Asistencia'!$D:$D,">="&'Planilla Mensual'!M25,'BD Asistencia'!$D:$D,"<="&'Planilla Mensual'!N25) -> 0 | Z25: =+COUNTIFS('BD Asistencia'!$H:$H,"NO REMUNERADO",'BD Asistencia'!$C:$C,'Planilla Mensual'!$D25,'BD Asistencia'!$D:$D,">="&'Planilla Mensual'!M25,'BD Asistencia'!$D:$D,"<="&'Planilla Mensual'!N25)-U25 -> 0 | AA25: =+COUNTIFS('BD Asistencia'!$E:$E,"F",'BD Asistencia'!$C:$C,'Planilla Mensual'!$D25,'BD Asistencia'!$D:$D,">="&'Planilla Mensual'!M25,'BD Asistencia'!$D:$D,"<="&'Planilla Mensual'!N25) -> 0 | AB25: =+SUM(S25:AA25) -> 15 | AR25: =+SUM(AL25:AQ25) -> 0 | AS25: =AI25-SUM(AL25:AQ25) -> 0 | AT25: =AJ25+AK25 -> 0 | AV25: =AS25+AT25 -> 0 | AZ25: =+R25*(S25+T25) -> 1200 | BB25: =+AC25*A25 -> 0 | BC25: =+AY25+AV25+AZ25+BA25+BB25 -> 1200 | BD25: =AI25+AU25+AT25+AY25+AZ25+BA25+BB25 -> 1200 | BG25: =(AV25+AY25+SUM(AL25:AQ25))/V25 -> #DIV/0! | BH25: =+(AZ25+BA25)/(S25+T25) -> 80
A26: 10 | B26: HONORARIOS | C26: 71622939 | D26: SALIRROSAS CONTRERAS NILSON LINDER | E26: 36785 | I26: INTERBANK | J26: 6003128946327 | K26: 00360001312894632748 | L26: 46158 | M26: 46143 | N26: 46157 | O26: =+TEXT(M26,"mmmm")&" - "&YEAR(M26)&MONTH(M26) -> Mayo - 20265 | P26: NO | R26: 105 | S26: =+COUNTIFS('BD Asistencia'!$E:$E,"A",'BD Asistencia'!$C:$C,'Planilla Mensual'!$D26,'BD Asistencia'!$D:$D,"<"&'Planilla Mensual'!L26) -> 12 | T26: =+COUNTIFS('BD Asistencia'!$E:$E,"DR",'BD Asistencia'!$C:$C,'Planilla Mensual'!$D26,'BD Asistencia'!$D:$D,"<"&L26) -> 1 | U26: =+COUNTIFS('BD Asistencia'!$H:$H,"NO REMUNERADO",'BD Asistencia'!$C:$C,'Planilla Mensual'!$D26,'BD Asistencia'!$D:$D,"<"&L26) -> 2 | V26: =+COUNTIFS('BD Asistencia'!$E:$E,"A",'BD Asistencia'!$C:$C,'Planilla Mensual'!$D26,'BD Asistencia'!$D:$D,">="&'Planilla Mensual'!M26,'BD Asistencia'!$D:$D,"<="&'Planilla Mensual'!N26)-S26 -> 0 | W26: =+COUNTIFS('BD Asistencia'!$E:$E,"DR",'BD Asistencia'!$C:$C,'Planilla Mensual'!$D26,'BD Asistencia'!$D:$D,">="&'Planilla Mensual'!M26,'BD Asistencia'!$D:$D,"<="&'Planilla Mensual'!N26)-T26 -> 0 | X26: =+COUNTIFS('BD Asistencia'!$E:$E,"h",'BD Asistencia'!$C:$C,'Planilla Mensual'!$D26,'BD Asistencia'!$D:$D,">="&'Planilla Mensual'!M26,'BD Asistencia'!$D:$D,"<="&'Planilla Mensual'!N26) -> 0 | Y26: =+COUNTIFS('BD Asistencia'!$E:$E,"h/A",'BD Asistencia'!$C:$C,'Planilla Mensual'!$D26,'BD Asistencia'!$D:$D,">="&'Planilla Mensual'!M26,'BD Asistencia'!$D:$D,"<="&'Planilla Mensual'!N26) -> 0 | Z26: =+COUNTIFS('BD Asistencia'!$H:$H,"NO REMUNERADO",'BD Asistencia'!$C:$C,'Planilla Mensual'!$D26,'BD Asistencia'!$D:$D,">="&'Planilla Mensual'!M26,'BD Asistencia'!$D:$D,"<="&'Planilla Mensual'!N26)-U26 -> 0 | AA26: =+COUNTIFS('BD Asistencia'!$E:$E,"F",'BD Asistencia'!$C:$C,'Planilla Mensual'!$D26,'BD Asistencia'!$D:$D,">="&'Planilla Mensual'!M26,'BD Asistencia'!$D:$D,"<="&'Planilla Mensual'!N26) -> 0 | AB26: =+SUM(S26:AA26) -> 15 | AC26: 4.5 | AR26: =+SUM(AL26:AQ26) -> 0 | AS26: =AI26-SUM(AL26:AQ26) -> 0 | AT26: =AJ26+AK26 -> 0 | AV26: =AS26+AT26 -> 0 | AZ26: =+R26*S26 -> 1260 | BB26: =+AC26*A26 -> 45 | BC26: =+AY26+AV26+AZ26+BA26+BB26 -> 1305 | BD26: =AI26+AU26+AT26+AY26+AZ26+BA26+BB26 -> 1305 | BG26: =(AV26+AY26+SUM(AL26:AQ26))/V26 -> #DIV/0! | BH26: =+(AZ26+BA26)/(S26+T26) -> 96.923077
B27: PENDIENTE | C27: 74231869 | D27: MOYA NAMOC PERCY LUIS | E27: 35092 | I27: BCP | K27: 973497771 | L27: 46158 | M27: 46143 | N27: 46157 | O27: =+TEXT(M27,"mmmm")&" - "&YEAR(M27)&MONTH(M27) -> Mayo - 20265 | P27: SI | Q27: =1425*2 -> 2850 | R27: =+Q27/30 -> 95 | S27: =+COUNTIFS('BD Asistencia'!$E:$E,"A",'BD Asistencia'!$C:$C,'Planilla Mensual'!$D27,'BD Asistencia'!$D:$D,"<"&'Planilla Mensual'!L27) -> 13 | T27: =+COUNTIFS('BD Asistencia'!$E:$E,"DR",'BD Asistencia'!$C:$C,'Planilla Mensual'!$D27,'BD Asistencia'!$D:$D,"<"&L27) -> 2 | U27: =+COUNTIFS('BD Asistencia'!$H:$H,"NO REMUNERADO",'BD Asistencia'!$C:$C,'Planilla Mensual'!$D27,'BD Asistencia'!$D:$D,"<"&L27) -> 0 | V27: =+COUNTIFS('BD Asistencia'!$E:$E,"A",'BD Asistencia'!$C:$C,'Planilla Mensual'!$D27,'BD Asistencia'!$D:$D,">="&'Planilla Mensual'!M27,'BD Asistencia'!$D:$D,"<="&'Planilla Mensual'!N27)-S27 -> 0 | W27: =+COUNTIFS('BD Asistencia'!$E:$E,"DR",'BD Asistencia'!$C:$C,'Planilla Mensual'!$D27,'BD Asistencia'!$D:$D,">="&'Planilla Mensual'!M27,'BD Asistencia'!$D:$D,"<="&'Planilla Mensual'!N27)-T27 -> 0 | X27: =+COUNTIFS('BD Asistencia'!$E:$E,"h",'BD Asistencia'!$C:$C,'Planilla Mensual'!$D27,'BD Asistencia'!$D:$D,">="&'Planilla Mensual'!M27,'BD Asistencia'!$D:$D,"<="&'Planilla Mensual'!N27) -> 0 | Y27: =+COUNTIFS('BD Asistencia'!$E:$E,"h/A",'BD Asistencia'!$C:$C,'Planilla Mensual'!$D27,'BD Asistencia'!$D:$D,">="&'Planilla Mensual'!M27,'BD Asistencia'!$D:$D,"<="&'Planilla Mensual'!N27) -> 0 | Z27: =+COUNTIFS('BD Asistencia'!$H:$H,"NO REMUNERADO",'BD Asistencia'!$C:$C,'Planilla Mensual'!$D27,'BD Asistencia'!$D:$D,">="&'Planilla Mensual'!M27,'BD Asistencia'!$D:$D,"<="&'Planilla Mensual'!N27)-U27 -> 0 | AA27: =+COUNTIFS('BD Asistencia'!$E:$E,"F",'BD Asistencia'!$C:$C,'Planilla Mensual'!$D27,'BD Asistencia'!$D:$D,">="&'Planilla Mensual'!M27,'BD Asistencia'!$D:$D,"<="&'Planilla Mensual'!N27) -> 0 | AB27: =+SUM(S27:AA27) -> 15 | AP27: 150 | AR27: =+SUM(AL27:AQ27) -> 150 | AS27: =AI27-SUM(AL27:AQ27) -> -150 | AT27: =AJ27+AK27 -> 0 | AV27: =AS27+AT27 -> -150 | AZ27: =+R27*(S27+T27) -> 1425 | BC27: =+AY27+AV27+AZ27+BA27+BB27 -> 1275 | BD27: =AI27+AU27+AT27+AY27+AZ27+BA27+BB27 -> 1425 | BG27: =(AV27+AY27+SUM(AL27:AQ27))/V27 -> #DIV/0! | BH27: =+(AZ27+BA27)/(S27+T27) -> 95
B28: PENDIENTE | C28: 47738777 | D28: PRADO MENDOZA GONZALO | E28: 34092 | I28: BCP | J28: 45006443272088 | L28: 46158 | M28: 46143 | N28: 46157 | O28: =+TEXT(M28,"mmmm")&" - "&YEAR(M28)&MONTH(M28) -> Mayo - 20265 | P28: SI | Q28: 3000 | R28: =+Q28/30 -> 100 | S28: =+COUNTIFS('BD Asistencia'!$E:$E,"A",'BD Asistencia'!$C:$C,'Planilla Mensual'!$D28,'BD Asistencia'!$D:$D,"<"&'Planilla Mensual'!L28) -> 14 | T28: =+COUNTIFS('BD Asistencia'!$E:$E,"DR",'BD Asistencia'!$C:$C,'Planilla Mensual'!$D28,'BD Asistencia'!$D:$D,"<"&L28) -> 1 | U28: =+COUNTIFS('BD Asistencia'!$H:$H,"NO REMUNERADO",'BD Asistencia'!$C:$C,'Planilla Mensual'!$D28,'BD Asistencia'!$D:$D,"<"&L28) -> 0 | V28: =+COUNTIFS('BD Asistencia'!$E:$E,"A",'BD Asistencia'!$C:$C,'Planilla Mensual'!$D28,'BD Asistencia'!$D:$D,">="&'Planilla Mensual'!M28,'BD Asistencia'!$D:$D,"<="&'Planilla Mensual'!N28)-S28 -> 0 | W28: =+COUNTIFS('BD Asistencia'!$E:$E,"DR",'BD Asistencia'!$C:$C,'Planilla Mensual'!$D28,'BD Asistencia'!$D:$D,">="&'Planilla Mensual'!M28,'BD Asistencia'!$D:$D,"<="&'Planilla Mensual'!N28)-T28 -> 0 | X28: =+COUNTIFS('BD Asistencia'!$E:$E,"h",'BD Asistencia'!$C:$C,'Planilla Mensual'!$D28,'BD Asistencia'!$D:$D,">="&'Planilla Mensual'!M28,'BD Asistencia'!$D:$D,"<="&'Planilla Mensual'!N28) -> 0 | Y28: =+COUNTIFS('BD Asistencia'!$E:$E,"h/A",'BD Asistencia'!$C:$C,'Planilla Mensual'!$D28,'BD Asistencia'!$D:$D,">="&'Planilla Mensual'!M28,'BD Asistencia'!$D:$D,"<="&'Planilla Mensual'!N28) -> 0 | Z28: =+COUNTIFS('BD Asistencia'!$H:$H,"NO REMUNERADO",'BD Asistencia'!$C:$C,'Planilla Mensual'!$D28,'BD Asistencia'!$D:$D,">="&'Planilla Mensual'!M28,'BD Asistencia'!$D:$D,"<="&'Planilla Mensual'!N28)-U28 -> 0 | AA28: =+COUNTIFS('BD Asistencia'!$E:$E,"F",'BD Asistencia'!$C:$C,'Planilla Mensual'!$D28,'BD Asistencia'!$D:$D,">="&'Planilla Mensual'!M28,'BD Asistencia'!$D:$D,"<="&'Planilla Mensual'!N28) -> 0 | AB28: =+SUM(S28:AA28) -> 15 | AR28: =+SUM(AL28:AQ28) -> 0 | AS28: =AI28-SUM(AL28:AQ28) -> 0 | AT28: =AJ28+AK28 -> 0 | AV28: =AS28+AT28 -> 0 | AZ28: =+R28*(S28+T28) -> 1500 | BC28: =+AY28+AV28+AZ28+BA28+BB28 -> 1500 | BD28: =AI28+AU28+AT28+AY28+AZ28+BA28+BB28 -> 1500 | BG28: =(AV28+AY28+SUM(AL28:AQ28))/V28 -> #DIV/0! | BH28: =+(AZ28+BA28)/(S28+T28) -> 100
B29: PENDIENTE | C29: 42633744 | D29: VELA NEYRA JOSE VICTOR | E29: 29117 | I29: BCP | J29: 57090022817092 | L29: 46158 | M29: 46143 | N29: 46157 | O29: =+TEXT(M29,"mmmm")&" - "&YEAR(M29)&MONTH(M29) -> Mayo - 20265 | Q29: 3000 | R29: =+Q29/30 -> 100 | S29: =+COUNTIFS('BD Asistencia'!$E:$E,"A",'BD Asistencia'!$C:$C,'Planilla Mensual'!$D29,'BD Asistencia'!$D:$D,"<"&'Planilla Mensual'!L29) -> 14 | T29: =+COUNTIFS('BD Asistencia'!$E:$E,"DR",'BD Asistencia'!$C:$C,'Planilla Mensual'!$D29,'BD Asistencia'!$D:$D,"<"&L29) -> 1 | U29: =+COUNTIFS('BD Asistencia'!$H:$H,"NO REMUNERADO",'BD Asistencia'!$C:$C,'Planilla Mensual'!$D29,'BD Asistencia'!$D:$D,"<"&L29) -> 0 | V29: =+COUNTIFS('BD Asistencia'!$E:$E,"A",'BD Asistencia'!$C:$C,'Planilla Mensual'!$D29,'BD Asistencia'!$D:$D,">="&'Planilla Mensual'!M29,'BD Asistencia'!$D:$D,"<="&'Planilla Mensual'!N29)-S29 -> 0 | W29: =+COUNTIFS('BD Asistencia'!$E:$E,"DR",'BD Asistencia'!$C:$C,'Planilla Mensual'!$D29,'BD Asistencia'!$D:$D,">="&'Planilla Mensual'!M29,'BD Asistencia'!$D:$D,"<="&'Planilla Mensual'!N29)-T29 -> 0 | X29: =+COUNTIFS('BD Asistencia'!$E:$E,"h",'BD Asistencia'!$C:$C,'Planilla Mensual'!$D29,'BD Asistencia'!$D:$D,">="&'Planilla Mensual'!M29,'BD Asistencia'!$D:$D,"<="&'Planilla Mensual'!N29) -> 0 | Y29: =+COUNTIFS('BD Asistencia'!$E:$E,"h/A",'BD Asistencia'!$C:$C,'Planilla Mensual'!$D29,'BD Asistencia'!$D:$D,">="&'Planilla Mensual'!M29,'BD Asistencia'!$D:$D,"<="&'Planilla Mensual'!N29) -> 0 | Z29: =+COUNTIFS('BD Asistencia'!$H:$H,"NO REMUNERADO",'BD Asistencia'!$C:$C,'Planilla Mensual'!$D29,'BD Asistencia'!$D:$D,">="&'Planilla Mensual'!M29,'BD Asistencia'!$D:$D,"<="&'Planilla Mensual'!N29)-U29 -> 0 | AA29: =+COUNTIFS('BD Asistencia'!$E:$E,"F",'BD Asistencia'!$C:$C,'Planilla Mensual'!$D29,'BD Asistencia'!$D:$D,">="&'Planilla Mensual'!M29,'BD Asistencia'!$D:$D,"<="&'Planilla Mensual'!N29) -> 0 | AB29: =+SUM(S29:AA29) -> 15 | AR29: =+SUM(AL29:AQ29) -> 0 | AS29: =AI29-SUM(AL29:AQ29) -> 0 | AT29: =AJ29+AK29 -> 0 | AV29: =AS29+AT29 -> 0 | AZ29: =+R29*(S29+T29) -> 1500 | BC29: =+AY29+AV29+AZ29+BA29+BB29 -> 1500 | BD29: =AI29+AU29+AT29+AY29+AZ29+BA29+BB29 -> 1500 | BG29: =(AV29+AY29+SUM(AL29:AQ29))/V29 -> #DIV/0! | BH29: =+(AZ29+BA29)/(S29+T29) -> 100
B30: PENDIENTE | C30: REFUGIO | D30: RAFAEL MATOS DANNY | E30: 25868 | I30: BCP | J30: 19104659937005 | L30: 46158 | M30: 46143 | N30: 46157 | O30: =+TEXT(M30,"mmmm")&" - "&YEAR(M30)&MONTH(M30) -> Mayo - 20265 | P30: NO | Q30: 2500 | R30: =+Q30/30 -> 83.333333 | S30: =+COUNTIFS('BD Asistencia'!$E:$E,"A",'BD Asistencia'!$C:$C,'Planilla Mensual'!$D30,'BD Asistencia'!$D:$D,"<"&'Planilla Mensual'!L30) -> 14 | T30: =+COUNTIFS('BD Asistencia'!$E:$E,"DR",'BD Asistencia'!$C:$C,'Planilla Mensual'!$D30,'BD Asistencia'!$D:$D,"<"&L30) -> 1 | U30: =+COUNTIFS('BD Asistencia'!$H:$H,"NO REMUNERADO",'BD Asistencia'!$C:$C,'Planilla Mensual'!$D30,'BD Asistencia'!$D:$D,"<"&L30) -> 0 | V30: =+COUNTIFS('BD Asistencia'!$E:$E,"A",'BD Asistencia'!$C:$C,'Planilla Mensual'!$D30,'BD Asistencia'!$D:$D,">="&'Planilla Mensual'!M30,'BD Asistencia'!$D:$D,"<="&'Planilla Mensual'!N30)-S30 -> 0 | W30: =+COUNTIFS('BD Asistencia'!$E:$E,"DR",'BD Asistencia'!$C:$C,'Planilla Mensual'!$D30,'BD Asistencia'!$D:$D,">="&'Planilla Mensual'!M30,'BD Asistencia'!$D:$D,"<="&'Planilla Mensual'!N30)-T30 -> 0 | X30: =+COUNTIFS('BD Asistencia'!$E:$E,"h",'BD Asistencia'!$C:$C,'Planilla Mensual'!$D30,'BD Asistencia'!$D:$D,">="&'Planilla Mensual'!M30,'BD Asistencia'!$D:$D,"<="&'Planilla Mensual'!N30) -> 0 | Y30: =+COUNTIFS('BD Asistencia'!$E:$E,"h/A",'BD Asistencia'!$C:$C,'Planilla Mensual'!$D30,'BD Asistencia'!$D:$D,">="&'Planilla Mensual'!M30,'BD Asistencia'!$D:$D,"<="&'Planilla Mensual'!N30) -> 0 | Z30: =+COUNTIFS('BD Asistencia'!$H:$H,"NO REMUNERADO",'BD Asistencia'!$C:$C,'Planilla Mensual'!$D30,'BD Asistencia'!$D:$D,">="&'Planilla Mensual'!M30,'BD Asistencia'!$D:$D,"<="&'Planilla Mensual'!N30)-U30 -> 0 | AA30: =+COUNTIFS('BD Asistencia'!$E:$E,"F",'BD Asistencia'!$C:$C,'Planilla Mensual'!$D30,'BD Asistencia'!$D:$D,">="&'Planilla Mensual'!M30,'BD Asistencia'!$D:$D,"<="&'Planilla Mensual'!N30) -> 0 | AB30: =+SUM(S30:AA30) -> 15 | AR30: =+SUM(AL30:AQ30) -> 0 | AS30: =AI30-SUM(AL30:AQ30) -> 0 | AT30: =AJ30+AK30 -> 0 | AV30: =AS30+AT30 -> 0 | AZ30: =+R30*(S30+T30) -> 1250 | BC30: =+AY30+AV30+AZ30+BA30+BB30 -> 1250 | BD30: =AI30+AU30+AT30+AY30+AZ30+BA30+BB30 -> 1250 | BG30: =(AV30+AY30+SUM(AL30:AQ30))/V30 -> #DIV/0! | BH30: =+(AZ30+BA30)/(S30+T30) -> 83.333333
B31: PENDIENTE | C31: 72904798 | D31: LEON GUANILO DIANA CAROLINA | E31: 38290 | I31: BCP | J31: 45095677205073 | L31: 46158 | M31: 46143 | N31: 46157 | O31: =+TEXT(M31,"mmmm")&" - "&YEAR(M31)&MONTH(M31) -> Mayo - 20265 | P31: NO | Q31: 1200 | R31: =+Q31/30 -> 40 | S31: 13 | T31: 2 | U31: =+COUNTIFS('BD Asistencia'!$H:$H,"NO REMUNERADO",'BD Asistencia'!$C:$C,'Planilla Mensual'!$D31,'BD Asistencia'!$D:$D,"<"&L31) -> 0 | V31: 0 | W31: 0 | X31: =+COUNTIFS('BD Asistencia'!$E:$E,"h",'BD Asistencia'!$C:$C,'Planilla Mensual'!$D31,'BD Asistencia'!$D:$D,">="&'Planilla Mensual'!M31,'BD Asistencia'!$D:$D,"<="&'Planilla Mensual'!N31) -> 0 | Y31: =+COUNTIFS('BD Asistencia'!$E:$E,"h/A",'BD Asistencia'!$C:$C,'Planilla Mensual'!$D31,'BD Asistencia'!$D:$D,">="&'Planilla Mensual'!M31,'BD Asistencia'!$D:$D,"<="&'Planilla Mensual'!N31) -> 0 | Z31: =+COUNTIFS('BD Asistencia'!$H:$H,"NO REMUNERADO",'BD Asistencia'!$C:$C,'Planilla Mensual'!$D31,'BD Asistencia'!$D:$D,">="&'Planilla Mensual'!M31,'BD Asistencia'!$D:$D,"<="&'Planilla Mensual'!N31)-U31 -> 0 | AA31: =+COUNTIFS('BD Asistencia'!$E:$E,"F",'BD Asistencia'!$C:$C,'Planilla Mensual'!$D31,'BD Asistencia'!$D:$D,">="&'Planilla Mensual'!M31,'BD Asistencia'!$D:$D,"<="&'Planilla Mensual'!N31) -> 0 | AB31: =+SUM(S31:AA31) -> 15 | AR31: =+SUM(AL31:AQ31) -> 0 | AS31: =AI31-SUM(AL31:AQ31) -> 0 | AT31: =AJ31+AK31 -> 0 | AV31: =AS31+AT31 -> 0 | AZ31: =+R31*(S31+T31) -> 600 | BC31: =+AY31+AV31+AZ31+BA31+BB31 -> 600 | BD31: =AI31+AU31+AT31+AY31+AZ31+BA31+BB31 -> 600 | BG31: =(AV31+AY31+SUM(AL31:AQ31))/V31 -> #DIV/0! | BH31: =+(AZ31+BA31)/(S31+T31) -> 40
B32: PENDIENTE | C32: 73984945 | D32: HONORIO CARRANZA SARA GIMENA | E32: 38268 | K32: 936698467 | L32: 46158 | M32: 46143 | N32: 46157 | O32: =+TEXT(M32,"mmmm")&" - "&YEAR(M32)&MONTH(M32) -> Mayo - 20265 | P32: NO | Q32: 1200 | R32: =+Q32/30 -> 40 | S32: =+COUNTIFS('BD Asistencia'!$E:$E,"A",'BD Asistencia'!$C:$C,'Planilla Mensual'!$D32,'BD Asistencia'!$D:$D,"<"&'Planilla Mensual'!L32) -> 4 | T32: =+COUNTIFS('BD Asistencia'!$E:$E,"DR",'BD Asistencia'!$C:$C,'Planilla Mensual'!$D32,'BD Asistencia'!$D:$D,"<"&L32) -> 0 | U32: =+COUNTIFS('BD Asistencia'!$H:$H,"NO REMUNERADO",'BD Asistencia'!$C:$C,'Planilla Mensual'!$D32,'BD Asistencia'!$D:$D,"<"&L32) -> 11 | V32: =+COUNTIFS('BD Asistencia'!$E:$E,"A",'BD Asistencia'!$C:$C,'Planilla Mensual'!$D32,'BD Asistencia'!$D:$D,">="&'Planilla Mensual'!M32,'BD Asistencia'!$D:$D,"<="&'Planilla Mensual'!N32)-S32 -> 0 | W32: =+COUNTIFS('BD Asistencia'!$E:$E,"DR",'BD Asistencia'!$C:$C,'Planilla Mensual'!$D32,'BD Asistencia'!$D:$D,">="&'Planilla Mensual'!M32,'BD Asistencia'!$D:$D,"<="&'Planilla Mensual'!N32)-T32 -> 0 | X32: =+COUNTIFS('BD Asistencia'!$E:$E,"h",'BD Asistencia'!$C:$C,'Planilla Mensual'!$D32,'BD Asistencia'!$D:$D,">="&'Planilla Mensual'!M32,'BD Asistencia'!$D:$D,"<="&'Planilla Mensual'!N32) -> 0 | Y32: =+COUNTIFS('BD Asistencia'!$E:$E,"h/A",'BD Asistencia'!$C:$C,'Planilla Mensual'!$D32,'BD Asistencia'!$D:$D,">="&'Planilla Mensual'!M32,'BD Asistencia'!$D:$D,"<="&'Planilla Mensual'!N32) -> 0 | Z32: =+COUNTIFS('BD Asistencia'!$H:$H,"NO REMUNERADO",'BD Asistencia'!$C:$C,'Planilla Mensual'!$D32,'BD Asistencia'!$D:$D,">="&'Planilla Mensual'!M32,'BD Asistencia'!$D:$D,"<="&'Planilla Mensual'!N32)-U32 -> 0 | AA32: =+COUNTIFS('BD Asistencia'!$E:$E,"F",'BD Asistencia'!$C:$C,'Planilla Mensual'!$D32,'BD Asistencia'!$D:$D,">="&'Planilla Mensual'!M32,'BD Asistencia'!$D:$D,"<="&'Planilla Mensual'!N32) -> 0 | AB32: =+SUM(S32:AA32) -> 15 | AR32: =+SUM(AL32:AQ32) -> 0 | AS32: =AI32-SUM(AL32:AQ32) -> 0 | AT32: =AJ32+AK32 -> 0 | AV32: =AS32+AT32 -> 0 | AZ32: =+R32*(S32+T32) -> 160 | BC32: =+AY32+AV32+AZ32+BA32+BB32 -> 160 | BD32: =AI32+AU32+AT32+AY32+AZ32+BA32+BB32 -> 160 | BG32: =(AV32+AY32+SUM(AL32:AQ32))/V32 -> #DIV/0! | BH32: =+(AZ32+BA32)/(S32+T32) -> 40
B33: PENDIENTE | D33: YOVERA CHAVEZ JORGE LUIS | K33: 936528185 | L33: 46158 | M33: 46143 | N33: 46157 | O33: =+TEXT(M33,"mmmm")&" - "&YEAR(M33)&MONTH(M33) -> Mayo - 20265 | P33: NO | Q33: 1200 | R33: =+Q33/30 -> 40 | S33: 13 | T33: 2 | U33: =+COUNTIFS('BD Asistencia'!$H:$H,"NO REMUNERADO",'BD Asistencia'!$C:$C,'Planilla Mensual'!$D33,'BD Asistencia'!$D:$D,"<"&L33) -> 0 | V33: 0 | W33: 0 | X33: =+COUNTIFS('BD Asistencia'!$E:$E,"h",'BD Asistencia'!$C:$C,'Planilla Mensual'!$D33,'BD Asistencia'!$D:$D,">="&'Planilla Mensual'!M33,'BD Asistencia'!$D:$D,"<="&'Planilla Mensual'!N33) -> 0 | Y33: =+COUNTIFS('BD Asistencia'!$E:$E,"h/A",'BD Asistencia'!$C:$C,'Planilla Mensual'!$D33,'BD Asistencia'!$D:$D,">="&'Planilla Mensual'!M33,'BD Asistencia'!$D:$D,"<="&'Planilla Mensual'!N33) -> 0 | Z33: =+COUNTIFS('BD Asistencia'!$H:$H,"NO REMUNERADO",'BD Asistencia'!$C:$C,'Planilla Mensual'!$D33,'BD Asistencia'!$D:$D,">="&'Planilla Mensual'!M33,'BD Asistencia'!$D:$D,"<="&'Planilla Mensual'!N33)-U33 -> 0 | AA33: =+COUNTIFS('BD Asistencia'!$E:$E,"F",'BD Asistencia'!$C:$C,'Planilla Mensual'!$D33,'BD Asistencia'!$D:$D,">="&'Planilla Mensual'!M33,'BD Asistencia'!$D:$D,"<="&'Planilla Mensual'!N33) -> 0 | AB33: =+SUM(S33:AA33) -> 15 | AR33: =+SUM(AL33:AQ33) -> 0 | AS33: =AI33-SUM(AL33:AQ33) -> 0 | AT33: =AJ33+AK33 -> 0 | AV33: =AS33+AT33 -> 0 | AZ33: =+R33*(S33+T33) -> 600 | BC33: =+AY33+AV33+AZ33+BA33+BB33 -> 600 | BD33: =AI33+AU33+AT33+AY33+AZ33+BA33+BB33 -> 600 | BG33: =(AV33+AY33+SUM(AL33:AQ33))/V33 -> #DIV/0! | BH33: =+(AZ33+BA33)/(S33+T33) -> 40
B34: PENDIENTE | C34: 74209005 | D34: YSLA VILLACORTA LILIANA RAQUEL | E34: 34562 | I34: BCP | J34: 19497473102077 | L34: 46158 | M34: 46143 | N34: 46157 | O34: =+TEXT(M34,"mmmm")&" - "&YEAR(M34)&MONTH(M34) -> Mayo - 20265 | P34: NO | Q34: 2500 | R34: =+Q34/30 -> 83.333333 | S34: 11 | T34: 1 | U34: 3 | V34: 0 | W34: 0 | X34: =+COUNTIFS('BD Asistencia'!$E:$E,"h",'BD Asistencia'!$C:$C,'Planilla Mensual'!$D34,'BD Asistencia'!$D:$D,">="&'Planilla Mensual'!M34,'BD Asistencia'!$D:$D,"<="&'Planilla Mensual'!N34) -> 0 | Y34: =+COUNTIFS('BD Asistencia'!$E:$E,"h/A",'BD Asistencia'!$C:$C,'Planilla Mensual'!$D34,'BD Asistencia'!$D:$D,">="&'Planilla Mensual'!M34,'BD Asistencia'!$D:$D,"<="&'Planilla Mensual'!N34) -> 0 | Z34: 0 | AA34: =+COUNTIFS('BD Asistencia'!$E:$E,"F",'BD Asistencia'!$C:$C,'Planilla Mensual'!$D34,'BD Asistencia'!$D:$D,">="&'Planilla Mensual'!M34,'BD Asistencia'!$D:$D,"<="&'Planilla Mensual'!N34) -> 0 | AB34: =+SUM(S34:AA34) -> 15 | AR34: =+SUM(AL34:AQ34) -> 0 | AS34: =AI34-SUM(AL34:AQ34) -> 0 | AT34: =AJ34+AK34 -> 0 | AV34: =AS34+AT34 -> 0 | AZ34: =+R34*(S34+T34) -> 1000 | BC34: =+AY34+AV34+AZ34+BA34+BB34 -> 1000 | BD34: =AI34+AU34+AT34+AY34+AZ34+BA34+BB34 -> 1000 | BG34: =(AV34+AY34+SUM(AL34:AQ34))/V34 -> #DIV/0! | BH34: =+(AZ34+BA34)/(S34+T34) -> 83.333333
B35: PENDIENTE | C35: 70901195 | D35: YOVERA CHAVEZ MARYORIE KATIUSKA | E35: 35029 | I35: BCP | J35: 57078579082062 | L35: 46158 | M35: 46143 | N35: 46157 | P35: NO | Q35: 4500 | R35: =+Q35/30 -> 150 | S35: 13 | T35: 2 | U35: =+COUNTIFS('BD Asistencia'!$H:$H,"NO REMUNERADO",'BD Asistencia'!$C:$C,'Planilla Mensual'!$D35,'BD Asistencia'!$D:$D,"<"&L35) -> 0 | V35: 0 | W35: 0 | X35: =+COUNTIFS('BD Asistencia'!$E:$E,"h",'BD Asistencia'!$C:$C,'Planilla Mensual'!$D35,'BD Asistencia'!$D:$D,">="&'Planilla Mensual'!M35,'BD Asistencia'!$D:$D,"<="&'Planilla Mensual'!N35) -> 0 | Y35: =+COUNTIFS('BD Asistencia'!$E:$E,"h/A",'BD Asistencia'!$C:$C,'Planilla Mensual'!$D35,'BD Asistencia'!$D:$D,">="&'Planilla Mensual'!M35,'BD Asistencia'!$D:$D,"<="&'Planilla Mensual'!N35) -> 0 | Z35: =+COUNTIFS('BD Asistencia'!$H:$H,"NO REMUNERADO",'BD Asistencia'!$C:$C,'Planilla Mensual'!$D35,'BD Asistencia'!$D:$D,">="&'Planilla Mensual'!M35,'BD Asistencia'!$D:$D,"<="&'Planilla Mensual'!N35)-U35 -> 0 | AA35: =+COUNTIFS('BD Asistencia'!$E:$E,"F",'BD Asistencia'!$C:$C,'Planilla Mensual'!$D35,'BD Asistencia'!$D:$D,">="&'Planilla Mensual'!M35,'BD Asistencia'!$D:$D,"<="&'Planilla Mensual'!N35) -> 0 | AB35: =+SUM(S35:AA35) -> 15 | AR35: =+SUM(AL35:AQ35) -> 0 | AS35: =AI35-SUM(AL35:AQ35) -> 0 | AT35: =AJ35+AK35 -> 0 | AV35: =AS35+AT35 -> 0 | AZ35: =+R35*(S35+T35) -> 2250 | BC35: =+AY35+AV35+AZ35+BA35+BB35 -> 2250 | BD35: =AI35+AU35+AT35+AY35+AZ35+BA35+BB35 -> 2250 | BG35: =(AV35+AY35+SUM(AL35:AQ35))/V35 -> #DIV/0! | BH35: =+(AZ35+BA35)/(S35+T35) -> 150
B36: PENDIENTE | C36: 72530933 | D36: OBERLUIS CABRERA ABNER DUWIENSER | E36: 35031 | L36: 46158 | M36: 46143 | N36: 46157 | P36: NO | Q36: 5000 | R36: =+Q36/30 -> 166.66667 | S36: 13 | T36: 2 | U36: =+COUNTIFS('BD Asistencia'!$H:$H,"NO REMUNERADO",'BD Asistencia'!$C:$C,'Planilla Mensual'!$D36,'BD Asistencia'!$D:$D,"<"&L36) -> 0 | V36: 0 | W36: 0 | X36: =+COUNTIFS('BD Asistencia'!$E:$E,"h",'BD Asistencia'!$C:$C,'Planilla Mensual'!$D36,'BD Asistencia'!$D:$D,">="&'Planilla Mensual'!M36,'BD Asistencia'!$D:$D,"<="&'Planilla Mensual'!N36) -> 0 | Y36: =+COUNTIFS('BD Asistencia'!$E:$E,"h/A",'BD Asistencia'!$C:$C,'Planilla Mensual'!$D36,'BD Asistencia'!$D:$D,">="&'Planilla Mensual'!M36,'BD Asistencia'!$D:$D,"<="&'Planilla Mensual'!N36) -> 0 | Z36: =+COUNTIFS('BD Asistencia'!$H:$H,"NO REMUNERADO",'BD Asistencia'!$C:$C,'Planilla Mensual'!$D36,'BD Asistencia'!$D:$D,">="&'Planilla Mensual'!M36,'BD Asistencia'!$D:$D,"<="&'Planilla Mensual'!N36)-U36 -> 0 | AA36: =+COUNTIFS('BD Asistencia'!$E:$E,"F",'BD Asistencia'!$C:$C,'Planilla Mensual'!$D36,'BD Asistencia'!$D:$D,">="&'Planilla Mensual'!M36,'BD Asistencia'!$D:$D,"<="&'Planilla Mensual'!N36) -> 0 | AB36: =+SUM(S36:AA36) -> 15 | AR36: =+SUM(AL36:AQ36) -> 0 | AS36: =AI36-SUM(AL36:AQ36) -> 0 | AT36: =AJ36+AK36 -> 0 | AV36: =AS36+AT36 -> 0 | AZ36: =+R36*(S36+T36) -> 2500 | BC36: =+AY36+AV36+AZ36+BA36+BB36 -> 2500 | BD36: =AI36+AU36+AT36+AY36+AZ36+BA36+BB36 -> 2500 | BG36: =(AV36+AY36+SUM(AL36:AQ36))/V36 -> #DIV/0! | BH36: =+(AZ36+BA36)/(S36+T36) -> 166.66667
BC37: =+SUBTOTAL(9,BC2:BC36) -> 38891.021 | BD37: =+SUBTOTAL(9,BD2:BD36) -> 42946.7

Sheet Base costo planilla
A1: PLANILLA | B1: INICIO1 | C1: FIN1 | D1: TOTAL 1 | E1: NOMBRES Y APELLIDOS
A2: REQUELME BACON CESAR DAVID | B2: 46143 | C2: 46157 | D2: =+SUMIFS('Planilla Mensual'!BC:BC,'Planilla Mensual'!D:D,'Base costo planilla'!A2,'Planilla Mensual'!M:M,'Base costo planilla'!B2) -> 1381.1979 | E2: CESAR DAVID REQUELME BACON
A3: CONCEPCIÓN ZEVALLOS ARMANDO | B3: 46143 | C3: 46157 | D3: =+SUMIFS('Planilla Mensual'!BC:BC,'Planilla Mensual'!D:D,'Base costo planilla'!A3,'Planilla Mensual'!M:M,'Base costo planilla'!B3) -> 1591.995 | E3: ARMANDO CONCEPCIÓN ZEVALLOS
A4: TERRONES JARA FREDY | B4: 46143 | C4: 46157 | D4: =+SUMIFS('Planilla Mensual'!BC:BC,'Planilla Mensual'!D:D,'Base costo planilla'!A4,'Planilla Mensual'!M:M,'Base costo planilla'!B4) -> 1497.8913 | E4: FREDY TERRONES JARA
A5: MONTOYA NAMOC JORGE LUIS | B5: 46143 | C5: 46157 | D5: =+SUMIFS('Planilla Mensual'!BC:BC,'Planilla Mensual'!D:D,'Base costo planilla'!A5,'Planilla Mensual'!M:M,'Base costo planilla'!B5) -> 1554.7716 | E5: JORGE LUIS MONTOYA NAMOC
A6: DIAZ DIAZ JUNNIOR | B6: 46143 | C6: 46157 | D6: =+SUMIFS('Planilla Mensual'!BC:BC,'Planilla Mensual'!D:D,'Base costo planilla'!A6,'Planilla Mensual'!M:M,'Base costo planilla'!B6) -> 1504.0372 | E6: JUNNIOR DIAZ DIAZ
A7: SIFUENTES PAREDES EDUARDO JAVIER | B7: 46143 | C7: 46157 | D7: =+SUMIFS('Planilla Mensual'!BC:BC,'Planilla Mensual'!D:D,'Base costo planilla'!A7,'Planilla Mensual'!M:M,'Base costo planilla'!B7) -> 1246.76 | E7: EDUARDO JAVIER SIFUENTES PAREDES
A8: TERRONES JARA LEYDER | B8: 46143 | C8: 46157 | D8: =+SUMIFS('Planilla Mensual'!BC:BC,'Planilla Mensual'!D:D,'Base costo planilla'!A8,'Planilla Mensual'!M:M,'Base costo planilla'!B8) -> 1000.6 | E8: LEYDER TERRONES JARA
A9: CALLE HUAMAN LEODAN JOEL | B9: 46143 | C9: 46157 | D9: =+SUMIFS('Planilla Mensual'!BC:BC,'Planilla Mensual'!D:D,'Base costo planilla'!A9,'Planilla Mensual'!M:M,'Base costo planilla'!B9) -> 1422.9585 | E9: LEODAN JOEL CALLE HUAMAN
A10: MANAYAY TANTARICO JHONATAN WILFER | B10: 46143 | C10: 46157 | D10: =+SUMIFS('Planilla Mensual'!BC:BC,'Planilla Mensual'!D:D,'Base costo planilla'!A10,'Planilla Mensual'!M:M,'Base costo planilla'!B10) -> 862.725 | E10: JHONATAN WILFER MANAYAY TANTARICO
A11: FARROÑAN YOVERA LUIS ALBERTO | B11: 46143 | C11: 46157 | D11: =+SUMIFS('Planilla Mensual'!BC:BC,'Planilla Mensual'!D:D,'Base costo planilla'!A11,'Planilla Mensual'!M:M,'Base costo planilla'!B11) -> 847.53162 | E11: LUIS ALBERTO FARROÑAN YOVERA
A12: CHUICA ADANAQUE ANDERSON XAVIER | B12: 46143 | C12: 46157 | D12: =+SUMIFS('Planilla Mensual'!BC:BC,'Planilla Mensual'!D:D,'Base costo planilla'!A12,'Planilla Mensual'!M:M,'Base costo planilla'!B12) -> 1036.79 | E12: ANDERSON XAVIER CHUICA ADANAQUE
A13: GARCIA RAMOS SEGUNDO MIGUEL | B13: 46143 | C13: 46157 | D13: =+SUMIFS('Planilla Mensual'!BC:BC,'Planilla Mensual'!D:D,'Base costo planilla'!A13,'Planilla Mensual'!M:M,'Base costo planilla'!B13) -> 1156.7543 | E13: SEGUNDO MIGUEL GARCIA RAMOS
... A34: OBERLUIS CABRERA ABNER DUWIENSER | B34: 46143 | C34: 46157 | D34: =+SUMIFS('Planilla Mensual'!BC:BC,'Planilla Mensual'!D:D,'Base costo planilla'!A34,'Planilla Mensual'!M:M,'Base costo planilla'!B34) -> 2500 | E34: OBERLUIS CABRERA ABNER DUWIENSER

Sheet BD Asistencia
A1: Condicion | B1: empresa | C1: Nombre | D1: Fecha | E1: Valor | F1: Semana | G1: año | H1: tipo
A2: ACTIVO | B2: AGROIMPORTADORA | C2: HONORIO CARRANZA SARA GIMENA | D2: 46143 | E2: DNR | F2: =+_xlfn.ISOWEEKNUM(export?format_csv_gid_612082435[[#This Row],[Fecha]]) -> 18 | G2: =+YEAR(export?format_csv_gid_612082435[[#This Row],[Fecha]]) -> 2026 | H2: =+VLOOKUP(export?format_csv_gid_612082435[[#This Row],[Valor]],Listas!A:B,2,FALSE) -> No Remunerado
A3: ACTIVO | B3: AGROIMPORTADORA | C3: HONORIO CARRANZA SARA GIMENA | D3: 46144 | E3: DNR | F3: =+_xlfn.ISOWEEKNUM(export?format_csv_gid_612082435[[#This Row],[Fecha]]) -> 18 | G3: =+YEAR(export?format_csv_gid_612082435[[#This Row],[Fecha]]) -> 2026 | H3: =+VLOOKUP(export?format_csv_gid_612082435[[#This Row],[Valor]],Listas!A:B,2,FALSE) -> No Remunerado
A4: ACTIVO | B4: AGROIMPORTADORA | C4: HONORIO CARRANZA SARA GIMENA | D4: 46145 | E4: DNR | F4: =+_xlfn.ISOWEEKNUM(export?format_csv_gid_612082435[[#This Row],[Fecha]]) -> 18 | G4: =+YEAR(export?format_csv_gid_612082435[[#This Row],[Fecha]]) -> 2026 | H4: =+VLOOKUP(export?format_csv_gid_612082435[[#This Row],[Valor]],Listas!A:B,2,FALSE) -> No Remunerado
A5: ACTIVO | B5: AGROIMPORTADORA | C5: HONORIO CARRANZA SARA GIMENA | D5: 46146 | E5: DNR | F5: =+_xlfn.ISOWEEKNUM(export?format_csv_gid_612082435[[#This Row],[Fecha]]) -> 19 | G5: =+YEAR(export?format_csv_gid_612082435[[#This Row],[Fecha]]) -> 2026 | H5: =+VLOOKUP(export?format_csv_gid_612082435[[#This Row],[Valor]],Listas!A:B,2,FALSE) -> No Remunerado
A6: ACTIVO | B6: AGROIMPORTADORA | C6: HONORIO CARRANZA SARA GIMENA | D6: 46147 | E6: DNR | F6: =+_xlfn.ISOWEEKNUM(export?format_csv_gid_612082435[[#This Row],[Fecha]]) -> 19 | G6: =+YEAR(export?format_csv_gid_612082435[[#This Row],[Fecha]]) -> 2026 | H6: =+VLOOKUP(export?format_csv_gid_612082435[[#This Row],[Valor]],Listas!A:B,2,FALSE) -> No Remunerado
A7: ACTIVO | B7: AGROIMPORTADORA | C7: HONORIO CARRANZA SARA GIMENA | D7: 46148 | E7: DNR | F7: =+_xlfn.ISOWEEKNUM(export?format_csv_gid_612082435[[#This Row],[Fecha]]) -> 19 | G7: =+YEAR(export?format_csv_gid_612082435[[#This Row],[Fecha]]) -> 2026 | H7: =+VLOOKUP(export?format_csv_gid_612082435[[#This Row],[Valor]],Listas!A:B,2,FALSE) -> No Remunerado
A8: ACTIVO | B8: AGROIMPORTADORA | C8: HONORIO CARRANZA SARA GIMENA | D8: 46149 | E8: DNR | F8: =+_xlfn.ISOWEEKNUM(export?format_csv_gid_612082435[[#This Row],[Fecha]]) -> 19 | G8: =+YEAR(export?format_csv_gid_612082435[[#This Row],[Fecha]]) -> 2026 | H8: =+VLOOKUP(export?format_csv_gid_612082435[[#This Row],[Valor]],Listas!A:B,2,FALSE) -> No Remunerado
A9: ACTIVO | B9: AGROIMPORTADORA | C9: HONORIO CARRANZA SARA GIMENA | D9: 46150 | E9: DNR | F9: =+_xlfn.ISOWEEKNUM(export?format_csv_gid_612082435[[#This Row],[Fecha]]) -> 19 | G9: =+YEAR(export?format_csv_gid_612082435[[#This Row],[Fecha]]) -> 2026 | H9: =+VLOOKUP(export?format_csv_gid_612082435[[#This Row],[Valor]],Listas!A:B,2,FALSE) -> No Remunerado
A10: ACTIVO | B10: AGROIMPORTADORA | C10: HONORIO CARRANZA SARA GIMENA | D10: 46151 | E10: DNR | F10: =+_xlfn.ISOWEEKNUM(export?format_csv_gid_612082435[[#This Row],[Fecha]]) -> 19 | G10: =+YEAR(export?format_csv_gid_612082435[[#This Row],[Fecha]]) -> 2026 | H10: =+VLOOKUP(export?format_csv_gid_612082435[[#This Row],[Valor]],Listas!A:B,2,FALSE) -> No Remunerado
A11: ACTIVO | B11: AGROIMPORTADORA | C11: HONORIO CARRANZA SARA GIMENA | D11: 46152 | E11: DNR | F11: =+_xlfn.ISOWEEKNUM(export?format_csv_gid_612082435[[#This Row],[Fecha]]) -> 19 | G11: =+YEAR(export?format_csv_gid_612082435[[#This Row],[Fecha]]) -> 2026 | H11: =+VLOOKUP(export?format_csv_gid_612082435[[#This Row],[Valor]],Listas!A:B,2,FALSE) -> No Remunerado
A12: ACTIVO | B12: AGROIMPORTADORA | C12: HONORIO CARRANZA SARA GIMENA | D12: 46153 | E12: A | F12: =+_xlfn.ISOWEEKNUM(export?format_csv_gid_612082435[[#This Row],[Fecha]]) -> 20 | G12: =+YEAR(export?format_csv_gid_612082435[[#This Row],[Fecha]]) -> 2026 | H12: =+VLOOKUP(export?format_csv_gid_612082435[[#This Row],[Valor]],Listas!A:B,2,FALSE) -> Asistencia
A13: ACTIVO | B13: AGROIMPORTADORA | C13: HONORIO CARRANZA SARA GIMENA | D13: 46154 | E13: DNR | F13: =+_xlfn.ISOWEEKNUM(export?format_csv_gid_612082435[[#This Row],[Fecha]]) -> 20 | G13: =+YEAR(export?format_csv_gid_612082435[[#This Row],[Fecha]]) -> 2026 | H13: =+VLOOKUP(export?format_csv_gid_612082435[[#This Row],[Valor]],Listas!A:B,2,FALSE) -> No Remunerado
... A16: ACTIVO | B16: AGROIMPORTADORA | C16: HONORIO CARRANZA SARA GIMENA | D16: 46157 | E16: A | F16: =+_xlfn.ISOWEEKNUM(export?format_csv_gid_612082435[[#This Row],[Fecha]]) -> 20 | G16: =+YEAR(export?format_csv_gid_612082435[[#This Row],[Fecha]]) -> 2026 | H16: =+VLOOKUP(export?format_csv_gid_612082435[[#This Row],[Valor]],Listas!A:B,2,FALSE) -> Asistencia
A17: ACTIVO | B17: AGROIMPORTADORA | C17: HONORIO CARRANZA SARA GIMENA | D17: 46158 | F17: =+_xlfn.ISOWEEKNUM(export?format_csv_gid_612082435[[#This Row],[Fecha]]) -> 20 | G17: =+YEAR(export?format_csv_gid_612082435[[#This Row],[Fecha]]) -> 2026 | H17: =+VLOOKUP(export?format_csv_gid_612082435[[#This Row],[Valor]],Listas!A:B,2,FALSE) -> #N/A
A18: ACTIVO | B18: AGROIMPORTADORA | C18: HONORIO CARRANZA SARA GIMENA | D18: 46159 | F18: =+_xlfn.ISOWEEKNUM(export?format_csv_gid_612082435[[#This Row],[Fecha]]) -> 20 | G18: =+YEAR(export?format_csv_gid_612082435[[#This Row],[Fecha]]) -> 2026 | H18: =+VLOOKUP(export?format_csv_gid_612082435[[#This Row],[Valor]],Listas!A:B,2,FALSE) -> #N/A
A19: ACTIVO | B19: AGROIMPORTADORA | C19: HONORIO CARRANZA SARA GIMENA | D19: 46160 | F19: =+_xlfn.ISOWEEKNUM(export?format_csv_gid_612082435[[#This Row],[Fecha]]) -> 21 | G19: =+YEAR(export?format_csv_gid_612082435[[#This Row],[Fecha]]) -> 2026 | H19: =+VLOOKUP(export?format_csv_gid_612082435[[#This Row],[Valor]],Listas!A:B,2,FALSE) -> #N/A
A20: ACTIVO | B20: AGROIMPORTADORA | C20: HONORIO CARRANZA SARA GIMENA | D20: 46161 | F20: =+_xlfn.ISOWEEKNUM(export?format_csv_gid_612082435[[#This Row],[Fecha]]) -> 21 | G20: =+YEAR(export?format_csv_gid_612082435[[#This Row],[Fecha]]) -> 2026 | H20: =+VLOOKUP(export?format_csv_gid_612082435[[#This Row],[Valor]],Listas!A:B,2,FALSE) -> #N/A
A21: ACTIVO | B21: AGROIMPORTADORA | C21: HONORIO CARRANZA SARA GIMENA | D21: 46162 | F21: =+_xlfn.ISOWEEKNUM(export?format_csv_gid_612082435[[#This Row],[Fecha]]) -> 21 | G21: =+YEAR(export?format_csv_gid_612082435[[#This Row],[Fecha]]) -> 2026 | H21: =+VLOOKUP(export?format_csv_gid_612082435[[#This Row],[Valor]],Listas!A:B,2,FALSE) -> #N/A
A22: ACTIVO | B22: AGROIMPORTADORA | C22: HONORIO CARRANZA SARA GIMENA | D22: 46163 | F22: =+_xlfn.ISOWEEKNUM(export?format_csv_gid_612082435[[#This Row],[Fecha]]) -> 21 | G22: =+YEAR(export?format_csv_gid_612082435[[#This Row],[Fecha]]) -> 2026 | H22: =+VLOOKUP(export?format_csv_gid_612082435[[#This Row],[Valor]],Listas!A:B,2,FALSE) -> #N/A
A23: ACTIVO | B23: AGROIMPORTADORA | C23: HONORIO CARRANZA SARA GIMENA | D23: 46164 | F23: =+_xlfn.ISOWEEKNUM(export?format_csv_gid_612082435[[#This Row],[Fecha]]) -> 21 | G23: =+YEAR(export?format_csv_gid_612082435[[#This Row],[Fecha]]) -> 2026 | H23: =+VLOOKUP(export?format_csv_gid_612082435[[#This Row],[Valor]],Listas!A:B,2,FALSE) -> #N/A
A24: ACTIVO | B24: AGROIMPORTADORA | C24: HONORIO CARRANZA SARA GIMENA | D24: 46165 | F24: =+_xlfn.ISOWEEKNUM(export?format_csv_gid_612082435[[#This Row],[Fecha]]) -> 21 | G24: =+YEAR(export?format_csv_gid_612082435[[#This Row],[Fecha]]) -> 2026 | H24: =+VLOOKUP(export?format_csv_gid_612082435[[#This Row],[Valor]],Listas!A:B,2,FALSE) -> #N/A
A25: ACTIVO | B25: AGROIMPORTADORA | C25: HONORIO CARRANZA SARA GIMENA | D25: 46166 | F25: =+_xlfn.ISOWEEKNUM(export?format_csv_gid_612082435[[#This Row],[Fecha]]) -> 21 | G25: =+YEAR(export?format_csv_gid_612082435[[#This Row],[Fecha]]) -> 2026 | H25: =+VLOOKUP(export?format_csv_gid_612082435[[#This Row],[Valor]],Listas!A:B,2,FALSE) -> #N/A
A26: ACTIVO | B26: AGROIMPORTADORA | C26: HONORIO CARRANZA SARA GIMENA | D26: 46167 | F26: =+_xlfn.ISOWEEKNUM(export?format_csv_gid_612082435[[#This Row],[Fecha]]) -> 22 | G26: =+YEAR(export?format_csv_gid_612082435[[#This Row],[Fecha]]) -> 2026 | H26: =+VLOOKUP(export?format_csv_gid_612082435[[#This Row],[Valor]],Listas!A:B,2,FALSE) -> #N/A
A27: ACTIVO | B27: AGROIMPORTADORA | C27: HONORIO CARRANZA SARA GIMENA | D27: 46168 | F27: =+_xlfn.ISOWEEKNUM(export?format_csv_gid_612082435[[#This Row],[Fecha]]) -> 22 | G27: =+YEAR(export?format_csv_gid_612082435[[#This Row],[Fecha]]) -> 2026 | H27: =+VLOOKUP(export?format_csv_gid_612082435[[#This Row],[Valor]],Listas!A:B,2,FALSE) -> #N/A
A28: ACTIVO | B28: AGROIMPORTADORA | C28: HONORIO CARRANZA SARA GIMENA | D28: 46169 | F28: =+_xlfn.ISOWEEKNUM(export?format_csv_gid_612082435[[#This Row],[Fecha]]) -> 22 | G28: =+YEAR(export?format_csv_gid_612082435[[#This Row],[Fecha]]) -> 2026 | H28: =+VLOOKUP(export?format_csv_gid_612082435[[#This Row],[Valor]],Listas!A:B,2,FALSE) -> #N/A
... A32: ACTIVO | B32: AGROIMPORTADORA | C32: HONORIO CARRANZA SARA GIMENA | D32: 46173 | F32: =+_xlfn.ISOWEEKNUM(export?format_csv_gid_612082435[[#This Row],[Fecha]]) -> 22 | G32: =+YEAR(export?format_csv_gid_612082435[[#This Row],[Fecha]]) -> 2026 | H32: =+VLOOKUP(export?format_csv_gid_612082435[[#This Row],[Valor]],Listas!A:B,2,FALSE) -> #N/A
A33: ACTIVO | B33: AGROIMPORTADORA | C33: RAFAEL MATOS DANNY | D33: 46143 | E33: A | F33: =+_xlfn.ISOWEEKNUM(export?format_csv_gid_612082435[[#This Row],[Fecha]]) -> 18 | G33: =+YEAR(export?format_csv_gid_612082435[[#This Row],[Fecha]]) -> 2026 | H33: =+VLOOKUP(export?format_csv_gid_612082435[[#This Row],[Valor]],Listas!A:B,2,FALSE) -> Asistencia
A34: ACTIVO | B34: AGROIMPORTADORA | C34: RAFAEL MATOS DANNY | D34: 46144 | E34: A | F34: =+_xlfn.ISOWEEKNUM(export?format_csv_gid_612082435[[#This Row],[Fecha]]) -> 18 | G34: =+YEAR(export?format_csv_gid_612082435[[#This Row],[Fecha]]) -> 2026 | H34: =+VLOOKUP(export?format_csv_gid_612082435[[#This Row],[Valor]],Listas!A:B,2,FALSE) -> Asistencia
A35: ACTIVO | B35: AGROIMPORTADORA | C35: RAFAEL MATOS DANNY | D35: 46145 | E35: A | F35: =+_xlfn.ISOWEEKNUM(export?format_csv_gid_612082435[[#This Row],[Fecha]]) -> 18 | G35: =+YEAR(export?format_csv_gid_612082435[[#This Row],[Fecha]]) -> 2026 | H35: =+VLOOKUP(export?format_csv_gid_612082435[[#This Row],[Valor]],Listas!A:B,2,FALSE) -> Asistencia
A36: ACTIVO | B36: AGROIMPORTADORA | C36: RAFAEL MATOS DANNY | D36: 46146 | E36: A | F36: =+_xlfn.ISOWEEKNUM(export?format_csv_gid_612082435[[#This Row],[Fecha]]) -> 19 | G36: =+YEAR(export?format_csv_gid_612082435[[#This Row],[Fecha]]) -> 2026 | H36: =+VLOOKUP(export?format_csv_gid_612082435[[#This Row],[Valor]],Listas!A:B,2,FALSE) -> Asistencia
A37: ACTIVO | B37: AGROIMPORTADORA | C37: RAFAEL MATOS DANNY | D37: 46147 | E37: A | F37: =+_xlfn.ISOWEEKNUM(export?format_csv_gid_612082435[[#This Row],[Fecha]]) -> 19 | G37: =+YEAR(export?format_csv_gid_612082435[[#This Row],[Fecha]]) -> 2026 | H37: =+VLOOKUP(export?format_csv_gid_612082435[[#This Row],[Valor]],Listas!A:B,2,FALSE) -> Asistencia
A38: ACTIVO | B38: AGROIMPORTADORA | C38: RAFAEL MATOS DANNY | D38: 46148 | E38: A | F38: =+_xlfn.ISOWEEKNUM(export?format_csv_gid_612082435[[#This Row],[Fecha]]) -> 19 | G38: =+YEAR(export?format_csv_gid_612082435[[#This Row],[Fecha]]) -> 2026 | H38: =+VLOOKUP(export?format_csv_gid_612082435[[#This Row],[Valor]],Listas!A:B,2,FALSE) -> Asistencia
A39: ACTIVO | B39: AGROIMPORTADORA | C39: RAFAEL MATOS DANNY | D39: 46149 | E39: A | F39: =+_xlfn.ISOWEEKNUM(export?format_csv_gid_612082435[[#This Row],[Fecha]]) -> 19 | G39: =+YEAR(export?format_csv_gid_612082435[[#This Row],[Fecha]]) -> 2026 | H39: =+VLOOKUP(export?format_csv_gid_612082435[[#This Row],[Valor]],Listas!A:B,2,FALSE) -> Asistencia
A40: ACTIVO | B40: AGROIMPORTADORA | C40: RAFAEL MATOS DANNY | D40: 46150 | E40: A | F40: =+_xlfn.ISOWEEKNUM(export?format_csv_gid_612082435[[#This Row],[Fecha]]) -> 19 | G40: =+YEAR(export?format_csv_gid_612082435[[#This Row],[Fecha]]) -> 2026 | H40: =+VLOOKUP(export?format_csv_gid_612082435[[#This Row],[Valor]],Listas!A:B,2,FALSE) -> Asistencia
A41: ACTIVO | B41: AGROIMPORTADORA | C41: RAFAEL MATOS DANNY | D41: 46151 | E41: A | F41: =+_xlfn.ISOWEEKNUM(export?format_csv_gid_612082435[[#This Row],[Fecha]]) -> 19 | G41: =+YEAR(export?format_csv_gid_612082435[[#This Row],[Fecha]]) -> 2026 | H41: =+VLOOKUP(export?format_csv_gid_612082435[[#This Row],[Valor]],Listas!A:B,2,FALSE) -> Asistencia
A42: ACTIVO | B42: AGROIMPORTADORA | C42: RAFAEL MATOS DANNY | D42: 46152 | E42: DR | F42: =+_xlfn.ISOWEEKNUM(export?format_csv_gid_612082435[[#This Row],[Fecha]]) -> 19 | G42: =+YEAR(export?format_csv_gid_612082435[[#This Row],[Fecha]]) -> 2026 | H42: =+VLOOKUP(export?format_csv_gid_612082435[[#This Row],[Valor]],Listas!A:B,2,FALSE) -> D. Remunerado
A43: ACTIVO | B43: AGROIMPORTADORA | C43: RAFAEL MATOS DANNY | D43: 46153 | E43: A | F43: =+_xlfn.ISOWEEKNUM(export?format_csv_gid_612082435[[#This Row],[Fecha]]) -> 20 | G43: =+YEAR(export?format_csv_gid_612082435[[#This Row],[Fecha]]) -> 2026 | H43: =+VLOOKUP(export?format_csv_gid_612082435[[#This Row],[Valor]],Listas!A:B,2,FALSE) -> Asistencia
A44: ACTIVO | B44: AGROIMPORTADORA | C44: RAFAEL MATOS DANNY | D44: 46154 | E44: A | F44: =+_xlfn.ISOWEEKNUM(export?format_csv_gid_612082435[[#This Row],[Fecha]]) -> 20 | G44: =+YEAR(export?format_csv_gid_612082435[[#This Row],[Fecha]]) -> 2026 | H44: =+VLOOKUP(export?format_csv_gid_612082435[[#This Row],[Valor]],Listas!A:B,2,FALSE) -> Asistencia
... A47: ACTIVO | B47: AGROIMPORTADORA | C47: RAFAEL MATOS DANNY | D47: 46157 | E47: A | F47: =+_xlfn.ISOWEEKNUM(export?format_csv_gid_612082435[[#This Row],[Fecha]]) -> 20 | G47: =+YEAR(export?format_csv_gid_612082435[[#This Row],[Fecha]]) -> 2026 | H47: =+VLOOKUP(export?format_csv_gid_612082435[[#This Row],[Valor]],Listas!A:B,2,FALSE) -> Asistencia
A48: ACTIVO | B48: AGROIMPORTADORA | C48: RAFAEL MATOS DANNY | D48: 46158 | F48: =+_xlfn.ISOWEEKNUM(export?format_csv_gid_612082435[[#This Row],[Fecha]]) -> 20 | G48: =+YEAR(export?format_csv_gid_612082435[[#This Row],[Fecha]]) -> 2026 | H48: =+VLOOKUP(export?format_csv_gid_612082435[[#This Row],[Valor]],Listas!A:B,2,FALSE) -> #N/A
A49: ACTIVO | B49: AGROIMPORTADORA | C49: RAFAEL MATOS DANNY | D49: 46159 | F49: =+_xlfn.ISOWEEKNUM(export?format_csv_gid_612082435[[#This Row],[Fecha]]) -> 20 | G49: =+YEAR(export?format_csv_gid_612082435[[#This Row],[Fecha]]) -> 2026 | H49: =+VLOOKUP(export?format_csv_gid_612082435[[#This Row],[Valor]],Listas!A:B,2,FALSE) -> #N/A
A50: ACTIVO | B50: AGROIMPORTADORA | C50: RAFAEL MATOS DANNY | D50: 46160 | F50: =+_xlfn.ISOWEEKNUM(export?format_csv_gid_612082435[[#This Row],[Fecha]]) -> 21 | G50: =+YEAR(export?format_csv_gid_612082435[[#This Row],[Fecha]]) -> 2026 | H50: =+VLOOKUP(export?format_csv_gid_612082435[[#This Row],[Valor]],Listas!A:B,2,FALSE) -> #N/A
A51: ACTIVO | B51: AGROIMPORTADORA | C51: RAFAEL MATOS DANNY | D51: 46161 | F51: =+_xlfn.ISOWEEKNUM(export?format_csv_gid_612082435[[#This Row],[Fecha]]) -> 21 | G51: =+YEAR(export?format_csv_gid_612082435[[#This Row],[Fecha]]) -> 2026 | H51: =+VLOOKUP(export?format_csv_gid_612082435[[#This Row],[Valor]],Listas!A:B,2,FALSE) -> #N/A
A52: ACTIVO | B52: AGROIMPORTADORA | C52: RAFAEL MATOS DANNY | D52: 46162 | F52: =+_xlfn.ISOWEEKNUM(export?format_csv_gid_612082435[[#This Row],[Fecha]]) -> 21 | G52: =+YEAR(export?format_csv_gid_612082435[[#This Row],[Fecha]]) -> 2026 | H52: =+VLOOKUP(export?format_csv_gid_612082435[[#This Row],[Valor]],Listas!A:B,2,FALSE) -> #N/A
A53: ACTIVO | B53: AGROIMPORTADORA | C53: RAFAEL MATOS DANNY | D53: 46163 | F53: =+_xlfn.ISOWEEKNUM(export?format_csv_gid_612082435[[#This Row],[Fecha]]) -> 21 | G53: =+YEAR(export?format_csv_gid_612082435[[#This Row],[Fecha]]) -> 2026 | H53: =+VLOOKUP(export?format_csv_gid_612082435[[#This Row],[Valor]],Listas!A:B,2,FALSE) -> #N/A
A54: ACTIVO | B54: AGROIMPORTADORA | C54: RAFAEL MATOS DANNY | D54: 46164 | F54: =+_xlfn.ISOWEEKNUM(export?format_csv_gid_612082435[[#This Row],[Fecha]]) -> 21 | G54: =+YEAR(export?format_csv_gid_612082435[[#This Row],[Fecha]]) -> 2026 | H54: =+VLOOKUP(export?format_csv_gid_612082435[[#This Row],[Valor]],Listas!A:B,2,FALSE) -> #N/A
A55: ACTIVO | B55: AGROIMPORTADORA | C55: RAFAEL MATOS DANNY | D55: 46165 | F55: =+_xlfn.ISOWEEKNUM(export?format_csv_gid_612082435[[#This Row],[Fecha]]) -> 21 | G55: =+YEAR(export?format_csv_gid_612082435[[#This Row],[Fecha]]) -> 2026 | H55: =+VLOOKUP(export?format_csv_gid_612082435[[#This Row],[Valor]],Listas!A:B,2,FALSE) -> #N/A
A56: ACTIVO | B56: AGROIMPORTADORA | C56: RAFAEL MATOS DANNY | D56: 46166 | F56: =+_xlfn.ISOWEEKNUM(export?format_csv_gid_612082435[[#This Row],[Fecha]]) -> 21 | G56: =+YEAR(export?format_csv_gid_612082435[[#This Row],[Fecha]]) -> 2026 | H56: =+VLOOKUP(export?format_csv_gid_612082435[[#This Row],[Valor]],Listas!A:B,2,FALSE) -> #N/A
A57: ACTIVO | B57: AGROIMPORTADORA | C57: RAFAEL MATOS DANNY | D57: 46167 | F57: =+_xlfn.ISOWEEKNUM(export?format_csv_gid_612082435[[#This Row],[Fecha]]) -> 22 | G57: =+YEAR(export?format_csv_gid_612082435[[#This Row],[Fecha]]) -> 2026 | H57: =+VLOOKUP(export?format_csv_gid_612082435[[#This Row],[Valor]],Listas!A:B,2,FALSE) -> #N/A
A58: ACTIVO | B58: AGROIMPORTADORA | C58: RAFAEL MATOS DANNY | D58: 46168 | F58: =+_xlfn.ISOWEEKNUM(export?format_csv_gid_612082435[[#This Row],[Fecha]]) -> 22 | G58: =+YEAR(export?format_csv_gid_612082435[[#This Row],[Fecha]]) -> 2026 | H58: =+VLOOKUP(export?format_csv_gid_612082435[[#This Row],[Valor]],Listas!A:B,2,FALSE) -> #N/A
A59: ACTIVO | B59: AGROIMPORTADORA | C59: RAFAEL MATOS DANNY | D59: 46169 | F59: =+_xlfn.ISOWEEKNUM(export?format_csv_gid_612082435[[#This Row],[Fecha]]) -> 22 | G59: =+YEAR(export?format_csv_gid_612082435[[#This Row],[Fecha]]) -> 2026 | H59: =+VLOOKUP(export?format_csv_gid_612082435[[#This Row],[Valor]],Listas!A:B,2,FALSE) -> #N/A
... A63: ACTIVO | B63: AGROIMPORTADORA | C63: RAFAEL MATOS DANNY | D63: 46173 | F63: =+_xlfn.ISOWEEKNUM(export?format_csv_gid_612082435[[#This Row],[Fecha]]) -> 22 | G63: =+YEAR(export?format_csv_gid_612082435[[#This Row],[Fecha]]) -> 2026 | H63: =+VLOOKUP(export?format_csv_gid_612082435[[#This Row],[Valor]],Listas!A:B,2,FALSE) -> #N/A
A64: ACTIVO | B64: AGROIMPORTADORA | C64: VELA NEYRA JOSE VICTOR | D64: 46143 | E64: A | F64: =+_xlfn.ISOWEEKNUM(export?format_csv_gid_612082435[[#This Row],[Fecha]]) -> 18 | G64: =+YEAR(export?format_csv_gid_612082435[[#This Row],[Fecha]]) -> 2026 | H64: =+VLOOKUP(export?format_csv_gid_612082435[[#This Row],[Valor]],Listas!A:B,2,FALSE) -> Asistencia
A65: ACTIVO | B65: AGROIMPORTADORA | C65: VELA NEYRA JOSE VICTOR | D65: 46144 | E65: A | F65: =+_xlfn.ISOWEEKNUM(export?format_csv_gid_612082435[[#This Row],[Fecha]]) -> 18 | G65: =+YEAR(export?format_csv_gid_612082435[[#This Row],[Fecha]]) -> 2026 | H65: =+VLOOKUP(export?format_csv_gid_612082435[[#This Row],[Valor]],Listas!A:B,2,FALSE) -> Asistencia
A66: ACTIVO | B66: AGROIMPORTADORA | C66: VELA NEYRA JOSE VICTOR | D66: 46145 | E66: A | F66: =+_xlfn.ISOWEEKNUM(export?format_csv_gid_612082435[[#This Row],[Fecha]]) -> 18 | G66: =+YEAR(export?format_csv_gid_612082435[[#This Row],[Fecha]]) -> 2026 | H66: =+VLOOKUP(export?format_csv_gid_612082435[[#This Row],[Valor]],Listas!A:B,2,FALSE) -> Asistencia
A67: ACTIVO | B67: AGROIMPORTADORA | C67: VELA NEYRA JOSE VICTOR | D67: 46146 | E67: A | F67: =+_xlfn.ISOWEEKNUM(export?format_csv_gid_612082435[[#This Row],[Fecha]]) -> 19 | G67: =+YEAR(export?format_csv_gid_612082435[[#This Row],[Fecha]]) -> 2026 | H67: =+VLOOKUP(export?format_csv_gid_612082435[[#This Row],[Valor]],Listas!A:B,2,FALSE) -> Asistencia
A68: ACTIVO | B68: AGROIMPORTADORA | C68: VELA NEYRA JOSE VICTOR | D68: 46147 | E68: A | F68: =+_xlfn.ISOWEEKNUM(export?format_csv_gid_612082435[[#This Row],[Fecha]]) -> 19 | G68: =+YEAR(export?format_csv_gid_612082435[[#This Row],[Fecha]]) -> 2026 | H68: =+VLOOKUP(export?format_csv_gid_612082435[[#This Row],[Valor]],Listas!A:B,2,FALSE) -> Asistencia
A69: ACTIVO | B69: AGROIMPORTADORA | C69: VELA NEYRA JOSE VICTOR | D69: 46148 | E69: A | F69: =+_xlfn.ISOWEEKNUM(export?format_csv_gid_612082435[[#This Row],[Fecha]]) -> 19 | G69: =+YEAR(export?format_csv_gid_612082435[[#This Row],[Fecha]]) -> 2026 | H69: =+VLOOKUP(export?format_csv_gid_612082435[[#This Row],[Valor]],Listas!A:B,2,FALSE) -> Asistencia
A70: ACTIVO | B70: AGROIMPORTADORA | C70: VELA NEYRA JOSE VICTOR | D70: 46149 | E70: A | F70: =+_xlfn.ISOWEEKNUM(export?format_csv_gid_612082435[[#This Row],[Fecha]]) -> 19 | G70: =+YEAR(export?format_csv_gid_612082435[[#This Row],[Fecha]]) -> 2026 | H70: =+VLOOKUP(export?format_csv_gid_612082435[[#This Row],[Valor]],Listas!A:B,2,FALSE) -> Asistencia
A71: ACTIVO | B71: AGROIMPORTADORA | C71: VELA NEYRA JOSE VICTOR | D71: 46150 | E71: A | F71: =+_xlfn.ISOWEEKNUM(export?format_csv_gid_612082435[[#This Row],[Fecha]]) -> 19 | G71: =+YEAR(export?format_csv_gid_612082435[[#This Row],[Fecha]]) -> 2026 | H71: =+VLOOKUP(export?format_csv_gid_612082435[[#This Row],[Valor]],Listas!A:B,2,FALSE) -> Asistencia
A72: ACTIVO | B72: AGROIMPORTADORA | C72: VELA NEYRA JOSE VICTOR | D72: 46151 | E72: A | F72: =+_xlfn.ISOWEEKNUM(export?format_csv_gid_612082435[[#This Row],[Fecha]]) -> 19 | G72: =+YEAR(export?format_csv_gid_612082435[[#This Row],[Fecha]]) -> 2026 | H72: =+VLOOKUP(export?format_csv_gid_612082435[[#This Row],[Valor]],Listas!A:B,2,FALSE) -> Asistencia
A73: ACTIVO | B73: AGROIMPORTADORA | C73: VELA NEYRA JOSE VICTOR | D73: 46152 | E73: DR | F73: =+_xlfn.ISOWEEKNUM(export?format_csv_gid_612082435[[#This Row],[Fecha]]) -> 19 | G73: =+YEAR(export?format_csv_gid_612082435[[#This Row],[Fecha]]) -> 2026 | H73: =+VLOOKUP(export?format_csv_gid_612082435[[#This Row],[Valor]],Listas!A:B,2,FALSE) -> D. Remunerado
A74: ACTIVO | B74: AGROIMPORTADORA | C74: VELA NEYRA JOSE VICTOR | D74: 46153 | E74: A | F74: =+_xlfn.ISOWEEKNUM(export?format_csv_gid_612082435[[#This Row],[Fecha]]) -> 20 | G74: =+YEAR(export?format_csv_gid_612082435[[#This Row],[Fecha]]) -> 2026 | H74: =+VLOOKUP(export?format_csv_gid_612082435[[#This Row],[Valor]],Listas!A:B,2,FALSE) -> Asistencia
A75: ACTIVO | B75: AGROIMPORTADORA | C75: VELA NEYRA JOSE VICTOR | D75: 46154 | E75: A | F75: =+_xlfn.ISOWEEKNUM(export?format_csv_gid_612082435[[#This Row],[Fecha]]) -> 20 | G75: =+YEAR(export?format_csv_gid_612082435[[#This Row],[Fecha]]) -> 2026 | H75: =+VLOOKUP(export?format_csv_gid_612082435[[#This Row],[Valor]],Listas!A:B,2,FALSE) -> Asistencia
... A78: ACTIVO | B78: AGROIMPORTADORA | C78: VELA NEYRA JOSE VICTOR | D78: 46157 | E78: A | F78: =+_xlfn.ISOWEEKNUM(export?format_csv_gid_612082435[[#This Row],[Fecha]]) -> 20 | G78: =+YEAR(export?format_csv_gid_612082435[[#This Row],[Fecha]]) -> 2026 | H78: =+VLOOKUP(export?format_csv_gid_612082435[[#This Row],[Valor]],Listas!A:B,2,FALSE) -> Asistencia
A79: ACTIVO | B79: AGROIMPORTADORA | C79: VELA NEYRA JOSE VICTOR | D79: 46158 | F79: =+_xlfn.ISOWEEKNUM(export?format_csv_gid_612082435[[#This Row],[Fecha]]) -> 20 | G79: =+YEAR(export?format_csv_gid_612082435[[#This Row],[Fecha]]) -> 2026 | H79: =+VLOOKUP(export?format_csv_gid_612082435[[#This Row],[Valor]],Listas!A:B,2,FALSE) -> #N/A
A80: ACTIVO | B80: AGROIMPORTADORA | C80: VELA NEYRA JOSE VICTOR | D80: 46159 | F80: =+_xlfn.ISOWEEKNUM(export?format_csv_gid_612082435[[#This Row],[Fecha]]) -> 20 | G80: =+YEAR(export?format_csv_gid_612082435[[#This Row],[Fecha]]) -> 2026 | H80: =+VLOOKUP(export?format_csv_gid_612082435[[#This Row],[Valor]],Listas!A:B,2,FALSE) -> #N/A
A81: ACTIVO | B81: AGROIMPORTADORA | C81: VELA NEYRA JOSE VICTOR | D81: 46160 | F81: =+_xlfn.ISOWEEKNUM(export?format_csv_gid_612082435[[#This Row],[Fecha]]) -> 21 | G81: =+YEAR(export?format_csv_gid_612082435[[#This Row],[Fecha]]) -> 2026 | H81: =+VLOOKUP(export?format_csv_gid_612082435[[#This Row],[Valor]],Listas!A:B,2,FALSE) -> #N/A
A82: ACTIVO | B82: AGROIMPORTADORA | C82: VELA NEYRA JOSE VICTOR | D82: 46161 | F82: =+_xlfn.ISOWEEKNUM(export?format_csv_gid_612082435[[#This Row],[Fecha]]) -> 21 | G82: =+YEAR(export?format_csv_gid_612082435[[#This Row],[Fecha]]) -> 2026 | H82: =+VLOOKUP(export?format_csv_gid_612082435[[#This Row],[Valor]],Listas!A:B,2,FALSE) -> #N/A
A83: ACTIVO | B83: AGROIMPORTADORA | C83: VELA NEYRA JOSE VICTOR | D83: 46162 | F83: =+_xlfn.ISOWEEKNUM(export?format_csv_gid_612082435[[#This Row],[Fecha]]) -> 21 | G83: =+YEAR(export?format_csv_gid_612082435[[#This Row],[Fecha]]) -> 2026 | H83: =+VLOOKUP(export?format_csv_gid_612082435[[#This Row],[Valor]],Listas!A:B,2,FALSE) -> #N/A
A84: ACTIVO | B84: AGROIMPORTADORA | C84: VELA NEYRA JOSE VICTOR | D84: 46163 | F84: =+_xlfn.ISOWEEKNUM(export?format_csv_gid_612082435[[#This Row],[Fecha]]) -> 21 | G84: =+YEAR(export?format_csv_gid_612082435[[#This Row],[Fecha]]) -> 2026 | H84: =+VLOOKUP(export?format_csv_gid_612082435[[#This Row],[Valor]],Listas!A:B,2,FALSE) -> #N/A
A85: ACTIVO | B85: AGROIMPORTADORA | C85: VELA NEYRA JOSE VICTOR | D85: 46164 | F85: =+_xlfn.ISOWEEKNUM(export?format_csv_gid_612082435[[#This Row],[Fecha]]) -> 21 | G85: =+YEAR(export?format_csv_gid_612082435[[#This Row],[Fecha]]) -> 2026 | H85: =+VLOOKUP(export?format_csv_gid_612082435[[#This Row],[Valor]],Listas!A:B,2,FALSE) -> #N/A
A86: ACTIVO | B86: AGROIMPORTADORA | C86: VELA NEYRA JOSE VICTOR | D86: 46165 | F86: =+_xlfn.ISOWEEKNUM(export?format_csv_gid_612082435[[#This Row],[Fecha]]) -> 21 | G86: =+YEAR(export?format_csv_gid_612082435[[#This Row],[Fecha]]) -> 2026 | H86: =+VLOOKUP(export?format_csv_gid_612082435[[#This Row],[Valor]],Listas!A:B,2,FALSE) -> #N/A
A87: ACTIVO | B87: AGROIMPORTADORA | C87: VELA NEYRA JOSE VICTOR | D87: 46166 | F87: =+_xlfn.ISOWEEKNUM(export?format_csv_gid_612082435[[#This Row],[Fecha]]) -> 21 | G87: =+YEAR(export?format_csv_gid_612082435[[#This Row],[Fecha]]) -> 2026 | H87: =+VLOOKUP(export?format_csv_gid_612082435[[#This Row],[Valor]],Listas!A:B,2,FALSE) -> #N/A
A88: ACTIVO | B88: AGROIMPORTADORA | C88: VELA NEYRA JOSE VICTOR | D88: 46167 | F88: =+_xlfn.ISOWEEKNUM(export?format_csv_gid_612082435[[#This Row],[Fecha]]) -> 22 | G88: =+YEAR(export?format_csv_gid_612082435[[#This Row],[Fecha]]) -> 2026 | H88: =+VLOOKUP(export?format_csv_gid_612082435[[#This Row],[Valor]],Listas!A:B,2,FALSE) -> #N/A
A89: ACTIVO | B89: AGROIMPORTADORA | C89: VELA NEYRA JOSE VICTOR | D89: 46168 | F89: =+_xlfn.ISOWEEKNUM(export?format_csv_gid_612082435[[#This Row],[Fecha]]) -> 22 | G89: =+YEAR(export?format_csv_gid_612082435[[#This Row],[Fecha]]) -> 2026 | H89: =+VLOOKUP(export?format_csv_gid_612082435[[#This Row],[Valor]],Listas!A:B,2,FALSE) -> #N/A
A90: ACTIVO | B90: AGROIMPORTADORA | C90: VELA NEYRA JOSE VICTOR | D90: 46169 | F90: =+_xlfn.ISOWEEKNUM(export?format_csv_gid_612082435[[#This Row],[Fecha]]) -> 22 | G90: =+YEAR(export?format_csv_gid_612082435[[#This Row],[Fecha]]) -> 2026 | H90: =+VLOOKUP(export?format_csv_gid_612082435[[#This Row],[Valor]],Listas!A:B,2,FALSE) -> #N/A
... A94: ACTIVO | B94: AGROIMPORTADORA | C94: VELA NEYRA JOSE VICTOR | D94: 46173 | F94: =+_xlfn.ISOWEEKNUM(export?format_csv_gid_612082435[[#This Row],[Fecha]]) -> 22 | G94: =+YEAR(export?format_csv_gid_612082435[[#This Row],[Fecha]]) -> 2026 | H94: =+VLOOKUP(export?format_csv_gid_612082435[[#This Row],[Valor]],Listas!A:B,2,FALSE) -> #N/A
A95: ACTIVO | B95: AGROIMPORTADORA | C95: PRADO MENDOZA GONZALO | D95: 46143 | E95: A | F95: =+_xlfn.ISOWEEKNUM(export?format_csv_gid_612082435[[#This Row],[Fecha]]) -> 18 | G95: =+YEAR(export?format_csv_gid_612082435[[#This Row],[Fecha]]) -> 2026 | H95: =+VLOOKUP(export?format_csv_gid_612082435[[#This Row],[Valor]],Listas!A:B,2,FALSE) -> Asistencia
A96: ACTIVO | B96: AGROIMPORTADORA | C96: PRADO MENDOZA GONZALO | D96: 46144 | E96: A | F96: =+_xlfn.ISOWEEKNUM(export?format_csv_gid_612082435[[#This Row],[Fecha]]) -> 18 | G96: =+YEAR(export?format_csv_gid_612082435[[#This Row],[Fecha]]) -> 2026 | H96: =+VLOOKUP(export?format_csv_gid_612082435[[#This Row],[Valor]],Listas!A:B,2,FALSE) -> Asistencia
A97: ACTIVO | B97: AGROIMPORTADORA | C97: PRADO MENDOZA GONZALO | D97: 46145 | E97: A | F97: =+_xlfn.ISOWEEKNUM(export?format_csv_gid_612082435[[#This Row],[Fecha]]) -> 18 | G97: =+YEAR(export?format_csv_gid_612082435[[#This Row],[Fecha]]) -> 2026 | H97: =+VLOOKUP(export?format_csv_gid_612082435[[#This Row],[Valor]],Listas!A:B,2,FALSE) -> Asistencia
A98: ACTIVO | B98: AGROIMPORTADORA | C98: PRADO MENDOZA GONZALO | D98: 46146 | E98: A | F98: =+_xlfn.ISOWEEKNUM(export?format_csv_gid_612082435[[#This Row],[Fecha]]) -> 19 | G98: =+YEAR(export?format_csv_gid_612082435[[#This Row],[Fecha]]) -> 2026 | H98: =+VLOOKUP(export?format_csv_gid_612082435[[#This Row],[Valor]],Listas!A:B,2,FALSE) -> Asistencia
A99: ACTIVO | B99: AGROIMPORTADORA | C99: PRADO MENDOZA GONZALO | D99: 46147 | E99: A | F99: =+_xlfn.ISOWEEKNUM(export?format_csv_gid_612082435[[#This Row],[Fecha]]) -> 19 | G99: =+YEAR(export?format_csv_gid_612082435[[#This Row],[Fecha]]) -> 2026 | H99: =+VLOOKUP(export?format_csv_gid_612082435[[#This Row],[Valor]],Listas!A:B,2,FALSE) -> Asistencia
A100: ACTIVO | B100: AGROIMPORTADORA | C100: PRADO MENDOZA GONZALO | D100: 46148 | E100: A | F100: =+_xlfn.ISOWEEKNUM(export?format_csv_gid_612082435[[#This Row],[Fecha]]) -> 19 | G100: =+YEAR(export?format_csv_gid_612082435[[#This Row],[Fecha]]) -> 2026 | H100: =+VLOOKUP(export?format_csv_gid_612082435[[#This Row],[Valor]],Listas!A:B,2,FALSE) -> Asistencia
A101: ACTIVO | B101: AGROIMPORTADORA | C101: PRADO MENDOZA GONZALO | D101: 46149 | E101: A | F101: =+_xlfn.ISOWEEKNUM(export?format_csv_gid_612082435[[#This Row],[Fecha]]) -> 19 | G101: =+YEAR(export?format_csv_gid_612082435[[#This Row],[Fecha]]) -> 2026 | H101: =+VLOOKUP(export?format_csv_gid_612082435[[#This Row],[Valor]],Listas!A:B,2,FALSE) -> Asistencia
A102: ACTIVO | B102: AGROIMPORTADORA | C102: PRADO MENDOZA GONZALO | D102: 46150 | E102: A | F102: =+_xlfn.ISOWEEKNUM(export?format_csv_gid_612082435[[#This Row],[Fecha]]) -> 19 | G102: =+YEAR(export?format_csv_gid_612082435[[#This Row],[Fecha]]) -> 2026 | H102: =+VLOOKUP(export?format_csv_gid_612082435[[#This Row],[Valor]],Listas!A:B,2,FALSE) -> Asistencia
A103: ACTIVO | B103: AGROIMPORTADORA | C103: PRADO MENDOZA GONZALO | D103: 46151 | E103: A | F103: =+_xlfn.ISOWEEKNUM(export?format_csv_gid_612082435[[#This Row],[Fecha]]) -> 19 | G103: =+YEAR(export?format_csv_gid_612082435[[#This Row],[Fecha]]) -> 2026 | H103: =+VLOOKUP(export?format_csv_gid_612082435[[#This Row],[Valor]],Listas!A:B,2,FALSE) -> Asistencia
A104: ACTIVO | B104: AGROIMPORTADORA | C104: PRADO MENDOZA GONZALO | D104: 46152 | E104: DR | F104: =+_xlfn.ISOWEEKNUM(export?format_csv_gid_612082435[[#This Row],[Fecha]]) -> 19 | G104: =+YEAR(export?format_csv_gid_612082435[[#This Row],[Fecha]]) -> 2026 | H104: =+VLOOKUP(export?format_csv_gid_612082435[[#This Row],[Valor]],Listas!A:B,2,FALSE) -> D. Remunerado
A105: ACTIVO | B105: AGROIMPORTADORA | C105: PRADO MENDOZA GONZALO | D105: 46153 | E105: A | F105: =+_xlfn.ISOWEEKNUM(export?format_csv_gid_612082435[[#This Row],[Fecha]]) -> 20 | G105: =+YEAR(export?format_csv_gid_612082435[[#This Row],[Fecha]]) -> 2026 | H105: =+VLOOKUP(export?format_csv_gid_612082435[[#This Row],[Valor]],Listas!A:B,2,FALSE) -> Asistencia
A106: ACTIVO | B106: AGROIMPORTADORA | C106: PRADO MENDOZA GONZALO | D106: 46154 | E106: A | F106: =+_xlfn.ISOWEEKNUM(export?format_csv_gid_612082435[[#This Row],[Fecha]]) -> 20 | G106: =+YEAR(export?format_csv_gid_612082435[[#This Row],[Fecha]]) -> 2026 | H106: =+VLOOKUP(export?format_csv_gid_612082435[[#This Row],[Valor]],Listas!A:B,2,FALSE) -> Asistencia
... A109: ACTIVO | B109: AGROIMPORTADORA | C109: PRADO MENDOZA GONZALO | D109: 46157 | E109: A | F109: =+_xlfn.ISOWEEKNUM(export?format_csv_gid_612082435[[#This Row],[Fecha]]) -> 20 | G109: =+YEAR(export?format_csv_gid_612082435[[#This Row],[Fecha]]) -> 2026 | H109: =+VLOOKUP(export?format_csv_gid_612082435[[#This Row],[Valor]],Listas!A:B,2,FALSE) -> Asistencia
A110: ACTIVO | B110: AGROIMPORTADORA | C110: PRADO MENDOZA GONZALO | D110: 46158 | F110: =+_xlfn.ISOWEEKNUM(export?format_csv_gid_612082435[[#This Row],[Fecha]]) -> 20 | G110: =+YEAR(export?format_csv_gid_612082435[[#This Row],[Fecha]]) -> 2026 | H110: =+VLOOKUP(export?format_csv_gid_612082435[[#This Row],[Valor]],Listas!A:B,2,FALSE) -> #N/A
A111: ACTIVO | B111: AGROIMPORTADORA | C111: PRADO MENDOZA GONZALO | D111: 46159 | F111: =+_xlfn.ISOWEEKNUM(export?format_csv_gid_612082435[[#This Row],[Fecha]]) -> 20 | G111: =+YEAR(export?format_csv_gid_612082435[[#This Row],[Fecha]]) -> 2026 | H111: =+VLOOKUP(export?format_csv_gid_612082435[[#This Row],[Valor]],Listas!A:B,2,FALSE) -> #N/A
A112: ACTIVO | B112: AGROIMPORTADORA | C112: PRADO MENDOZA GONZALO | D112: 46160 | F112: =+_xlfn.ISOWEEKNUM(export?format_csv_gid_612082435[[#This Row],[Fecha]]) -> 21 | G112: =+YEAR(export?format_csv_gid_612082435[[#This Row],[Fecha]]) -> 2026 | H112: =+VLOOKUP(export?format_csv_gid_612082435[[#This Row],[Valor]],Listas!A:B,2,FALSE) -> #N/A
A113: ACTIVO | B113: AGROIMPORTADORA | C113: PRADO MENDOZA GONZALO | D113: 46161 | F113: =+_xlfn.ISOWEEKNUM(export?format_csv_gid_612082435[[#This Row],[Fecha]]) -> 21 | G113: =+YEAR(export?format_csv_gid_612082435[[#This Row],[Fecha]]) -> 2026 | H113: =+VLOOKUP(export?format_csv_gid_612082435[[#This Row],[Valor]],Listas!A:B,2,FALSE) -> #N/A
A114: ACTIVO | B114: AGROIMPORTADORA | C114: PRADO MENDOZA GONZALO | D114: 46162 | F114: =+_xlfn.ISOWEEKNUM(export?format_csv_gid_612082435[[#This Row],[Fecha]]) -> 21 | G114: =+YEAR(export?format_csv_gid_612082435[[#This Row],[Fecha]]) -> 2026 | H114: =+VLOOKUP(export?format_csv_gid_612082435[[#This Row],[Valor]],Listas!A:B,2,FALSE) -> #N/A
A115: ACTIVO | B115: AGROIMPORTADORA | C115: PRADO MENDOZA GONZALO | D115: 46163 | F115: =+_xlfn.ISOWEEKNUM(export?format_csv_gid_612082435[[#This Row],[Fecha]]) -> 21 | G115: =+YEAR(export?format_csv_gid_612082435[[#This Row],[Fecha]]) -> 2026 | H115: =+VLOOKUP(export?format_csv_gid_612082435[[#This Row],[Valor]],Listas!A:B,2,FALSE) -> #N/A
A116: ACTIVO | B116: AGROIMPORTADORA | C116: PRADO MENDOZA GONZALO | D116: 46164 | F116: =+_xlfn.ISOWEEKNUM(export?format_csv_gid_612082435[[#This Row],[Fecha]]) -> 21 | G116: =+YEAR(export?format_csv_gid_612082435[[#This Row],[Fecha]]) -> 2026 | H116: =+VLOOKUP(export?format_csv_gid_612082435[[#This Row],[Valor]],Listas!A:B,2,FALSE) -> #N/A
A117: ACTIVO | B117: AGROIMPORTADORA | C117: PRADO MENDOZA GONZALO | D117: 46165 | F117: =+_xlfn.ISOWEEKNUM(export?format_csv_gid_612082435[[#This Row],[Fecha]]) -> 21 | G117: =+YEAR(export?format_csv_gid_612082435[[#This Row],[Fecha]]) -> 2026 | H117: =+VLOOKUP(export?format_csv_gid_612082435[[#This Row],[Valor]],Listas!A:B,2,FALSE) -> #N/A
...

Sheet Resumen asistencia
A1: Condicion | B1: ACTIVO | P1: Condicion | Q1: ACTIVO
A2: Fecha | B2: (Varios elementos) | P2: Fecha | Q2: (Varios elementos)
A4: Cuenta de Valor | B4: Etiquetas de columna | P4: Cuenta de Valor | Q4: Etiquetas de columna
A5: Etiquetas de fila | B5: A | C5: H | D5: DR | E5: DNR | F5: F | G5: N/A | I5: Total general | P5: Etiquetas de fila | Q5: A | R5: H | S5: DR | T5: DNR | U5: N/A | V5: Total general
A6: BERNA TANTARICO BENJAMIN | B6: 5 | E6: 9 | H6: 1 | I6: 15 | J6: =+SUM(B6:C6)+H6 -> 6 | K6: =+SUM(D6) -> 0 | L6: =+SUM(E6:F6) -> 9 | P6: BERNA TANTARICO BENJAMIN | T6: 3 | V6: 3 | W6: =+SUM(Q6:R6) -> 0 | X6: =+SUM(S6) -> 0 | Y6: =+SUM(T6:U6) -> 3
A7: CALLE HUAMAN LEODAN JOEL | B7: 12 | D7: 1 | E7: 2 | I7: 15 | J7: =+SUM(B7:C7)+H7 -> 12 | K7: =+SUM(D7) -> 1 | L7: =+SUM(E7:F7) -> 2 | P7: CALLE HUAMAN LEODAN JOEL | Q7: 1 | T7: 2 | V7: 3 | W7: =+SUM(Q7:R7) -> 1 | X7: =+SUM(S7) -> 0 | Y7: =+SUM(T7:U7) -> 2
A8: CARLOS ROQUE JUNIOR ABEL | B8: 10 | D8: 1 | E8: 1 | G8: 3 | I8: 15 | J8: =+SUM(B8:C8)+H8 -> 10 | K8: =+SUM(D8) -> 1 | L8: =+SUM(E8:F8) -> 1 | P8: CARLOS ROQUE JUNIOR ABEL | U8: 3 | V8: 3 | W8: =+SUM(Q8:R8) -> 0 | X8: =+SUM(S8) -> 0 | Y8: =+SUM(T8:U8) -> 3
A9: CHUICA ADANAQUE ANDERSON XAVIER | B9: 11 | D9: 1 | G9: 3 | I9: 15 | J9: =+SUM(B9:C9)+H9 -> 11 | K9: =+SUM(D9) -> 1 | L9: =+SUM(E9:F9) -> 0 | P9: CHUICA ADANAQUE ANDERSON XAVIER | U9: 3 | V9: 3 | W9: =+SUM(Q9:R9) -> 0 | X9: =+SUM(S9) -> 0 | Y9: =+SUM(T9:U9) -> 3
A10: CONCEPCIÓN ZEVALLOS ARMANDO | B10: 13 | D10: 1 | E10: 1 | I10: 15 | J10: =+SUM(B10:C10)+H10 -> 13 | K10: =+SUM(D10) -> 1 | L10: =+SUM(E10:F10) -> 1 | N10: 367.2 | P10: CONCEPCIÓN ZEVALLOS ARMANDO | Q10: 2 | T10: 1 | V10: 3 | W10: =+SUM(Q10:R10) -> 2 | X10: =+SUM(S10) -> 0 | Y10: =+SUM(T10:U10) -> 1
A11: CRUZ VARGAS MARCO ANTONIO | B11: 4 | E11: 11 | I11: 15 | J11: =+SUM(B11:C11)+H11 -> 4 | K11: =+SUM(D11) -> 0 | L11: =+SUM(E11:F11) -> 11 | N11: 340.5 | P11: CRUZ VARGAS MARCO ANTONIO | T11: 3 | V11: 3 | W11: =+SUM(Q11:R11) -> 0 | X11: =+SUM(S11) -> 0 | Y11: =+SUM(T11:U11) -> 3
A12: CURO PAZ FELIPE | B12: 12 | D12: 3 | I12: 15 | J12: =+SUM(B12:C12)+H12 -> 12 | K12: =+SUM(D12) -> 3 | L12: =+SUM(E12:F12) -> 0 | P12: CURO PAZ FELIPE | Q12: 3 | V12: 3 | W12: =+SUM(Q12:R12) -> 3 | X12: =+SUM(S12) -> 0 | Y12: =+SUM(T12:U12) -> 0
A13: DIAZ DIAZ JUNNIOR | B13: 11 | D13: 1 | E13: 2 | H13: 1 | I13: 15 | J13: =+SUM(B13:C13)+H13 -> 12 | K13: =+SUM(D13) -> 1 | L13: =+SUM(E13:F13) -> 2 | P13: DIAZ DIAZ JUNNIOR | Q13: 1 | T13: 2 | V13: 3 | W13: =+SUM(Q13:R13) -> 1 | X13: =+SUM(S13) -> 0 | Y13: =+SUM(T13:U13) -> 2
A14: FARROÑAN YOVERA LUIS ALBERTO | B14: 11 | D14: 1 | E14: 2 | F14: 1 | I14: 15 | J14: =+SUM(B14:C14)+H14 -> 11 | K14: =+SUM(D14) -> 1 | L14: =+SUM(E14:F14) -> 3 | P14: FARROÑAN YOVERA LUIS ALBERTO | Q14: 1 | T14: 2 | V14: 3 | W14: =+SUM(Q14:R14) -> 1 | X14: =+SUM(S14) -> 0 | Y14: =+SUM(T14:U14) -> 2
A15: GARCIA RAMOS JOSE ISMAEL | B15: 14 | D15: 1 | I15: 15 | J15: =+SUM(B15:C15)+H15 -> 14 | K15: =+SUM(D15) -> 1 | L15: =+SUM(E15:F15) -> 0 | P15: GARCIA RAMOS JOSE ISMAEL | Q15: 3 | V15: 3 | W15: =+SUM(Q15:R15) -> 3 | X15: =+SUM(S15) -> 0 | Y15: =+SUM(T15:U15) -> 0
A16: GARCIA RAMOS SEGUNDO MIGUEL | B16: 11 | D16: 1 | G16: 3 | I16: 15 | J16: =+SUM(B16:C16)+H16 -> 11 | K16: =+SUM(D16) -> 1 | L16: =+SUM(E16:F16) -> 0 | P16: GARCIA RAMOS SEGUNDO MIGUEL | U16: 3 | V16: 3 | W16: =+SUM(Q16:R16) -> 0 | X16: =+SUM(S16) -> 0 | Y16: =+SUM(T16:U16) -> 3
A17: GOLINDANO MARQUEZ JUAN CARLOS | B17: 7 | D17: 4 | E17: 4 | I17: 15 | J17: =+SUM(B17:C17)+H17 -> 7 | K17: =+SUM(D17) -> 4 | L17: =+SUM(E17:F17) -> 4 | P17: GOLINDANO MARQUEZ JUAN CARLOS | S17: 2 | T17: 1 | V17: 3 | W17: =+SUM(Q17:R17) -> 0 | X17: =+SUM(S17) -> 2 | Y17: =+SUM(T17:U17) -> 1
A18: HERNANDEZ GOMEZ LUIS JHONATAN | B18: 5 | G18: 10 | I18: 15 | J18: =+SUM(B18:C18)+H18 -> 5 | K18: =+SUM(D18) -> 0 | L18: =+SUM(E18:F18) -> 0 | P18: HERNANDEZ GOMEZ LUIS JHONATAN | U18: 3 | V18: 3 | W18: =+SUM(Q18:R18) -> 0 | X18: =+SUM(S18) -> 0 | Y18: =+SUM(T18:U18) -> 3
A19: HONORIO CARRANZA SARA GIMENA | B19: 4 | E19: 11 | I19: 15 | J19: =+SUM(B19:C19)+H19 -> 4 | K19: =+SUM(D19) -> 0 | L19: =+SUM(E19:F19) -> 11 | P19: HONORIO CARRANZA SARA GIMENA | T19: 3 | V19: 3 | W19: =+SUM(Q19:R19) -> 0 | X19: =+SUM(S19) -> 0 | Y19: =+SUM(T19:U19) -> 3
A20: LALUPU ZAPATA CARLOS JAVIER | B20: 14 | D20: 1 | I20: 15 | J20: =+SUM(B20:C20)+H20 -> 14 | K20: =+SUM(D20) -> 1 | L20: =+SUM(E20:F20) -> 0 | P20: LALUPU ZAPATA CARLOS JAVIER | Q20: 3 | V20: 3 | W20: =+SUM(Q20:R20) -> 3 | X20: =+SUM(S20) -> 0 | Y20: =+SUM(T20:U20) -> 0
A21: LEYVA CARRERA MARIANO YOEL | B21: 14 | D21: 1 | I21: 15 | J21: =+SUM(B21:C21)+H21 -> 14 | K21: =+SUM(D21) -> 1 | L21: =+SUM(E21:F21) -> 0 | P21: LEYVA CARRERA MARIANO YOEL | Q21: 3 | V21: 3 | W21: =+SUM(Q21:R21) -> 3 | X21: =+SUM(S21) -> 0 | Y21: =+SUM(T21:U21) -> 0
A22: MANAYAY TANTARICO JHONATAN WILFER | B22: 12 | D22: 1 | E22: 2 | I22: 15 | J22: =+SUM(B22:C22)+H22 -> 12 | K22: =+SUM(D22) -> 1 | L22: =+SUM(E22:F22) -> 2 | P22: MANAYAY TANTARICO JHONATAN WILFER | Q22: 1 | T22: 2 | V22: 3 | W22: =+SUM(Q22:R22) -> 1 | X22: =+SUM(S22) -> 0 | Y22: =+SUM(T22:U22) -> 2
A23: MONTOYA NAMOC JORGE LUIS | B23: 13 | D23: 1 | E23: 1 | I23: 15 | J23: =+SUM(B23:C23)+H23 -> 13 | K23: =+SUM(D23) -> 1 | L23: =+SUM(E23:F23) -> 1 | P23: MONTOYA NAMOC JORGE LUIS | Q23: 2 | T23: 1 | V23: 3 | W23: =+SUM(Q23:R23) -> 2 | X23: =+SUM(S23) -> 0 | Y23: =+SUM(T23:U23) -> 1
A24: MOYA NAMOC PERCY LUIS | B24: 12 | D24: 3 | I24: 15 | J24: =+SUM(B24:C24)+H24 -> 12 | K24: =+SUM(D24) -> 3 | L24: =+SUM(E24:F24) -> 0 | P24: MOYA NAMOC PERCY LUIS | Q24: 1 | S24: 2 | V24: 3 | W24: =+SUM(Q24:R24) -> 1 | X24: =+SUM(S24) -> 2 | Y24: =+SUM(T24:U24) -> 0
A25: PRADO MENDOZA GONZALO | B25: 13 | D25: 2 | I25: 15 | J25: =+SUM(B25:C25)+H25 -> 13 | K25: =+SUM(D25) -> 2 | L25: =+SUM(E25:F25) -> 0 | P25: PRADO MENDOZA GONZALO | Q25: 2 | S25: 1 | V25: 3 | W25: =+SUM(Q25:R25) -> 2 | X25: =+SUM(S25) -> 1 | Y25: =+SUM(T25:U25) -> 0
A26: RAFAEL MATOS DANNY | B26: 13 | D26: 2 | I26: 15 | J26: =+SUM(B26:C26)+H26 -> 13 | K26: =+SUM(D26) -> 2 | L26: =+SUM(E26:F26) -> 0 | P26: RAFAEL MATOS DANNY | Q26: 2 | S26: 1 | V26: 3 | W26: =+SUM(Q26:R26) -> 2 | X26: =+SUM(S26) -> 1 | Y26: =+SUM(T26:U26) -> 0
A27: REQUELME BACON CESAR DAVID | B27: 13 | C27: 1 | D27: 1 | I27: 15 | J27: =+SUM(B27:C27)+H27 -> 14 | K27: =+SUM(D27) -> 1 | L27: =+SUM(E27:F27) -> 0 | P27: REQUELME BACON CESAR DAVID | Q27: 1 | R27: 1 | S27: 1 | V27: 3 | W27: =+SUM(Q27:R27) -> 2 | X27: =+SUM(S27) -> 1 | Y27: =+SUM(T27:U27) -> 0
A28: SALIRROSAS CONTRERAS NILSON LINDER | B28: 12 | D28: 1 | E28: 2 | I28: 15 | J28: =+SUM(B28:C28)+H28 -> 12 | K28: =+SUM(D28) -> 1 | L28: =+SUM(E28:F28) -> 2 | P28: SALIRROSAS CONTRERAS NILSON LINDER | Q28: 1 | T28: 2 | V28: 3 | W28: =+SUM(Q28:R28) -> 1 | X28: =+SUM(S28) -> 0 | Y28: =+SUM(T28:U28) -> 2
A29: SIFUENTES PAREDES EDUARDO JAVIER | B29: 13 | D29: 1 | E29: 1 | I29: 15 | J29: =+SUM(B29:C29)+H29 -> 13 | K29: =+SUM(D29) -> 1 | L29: =+SUM(E29:F29) -> 1 | P29: SIFUENTES PAREDES EDUARDO JAVIER | Q29: 2 | T29: 1 | V29: 3 | W29: =+SUM(Q29:R29) -> 2 | X29: =+SUM(S29) -> 0 | Y29: =+SUM(T29:U29) -> 1
A30: TERRONES JARA FREDY | B30: 11 | D30: 1 | E30: 2 | H30: 1 | I30: 15 | J30: =+SUM(B30:C30)+H30 -> 12 | K30: =+SUM(D30) -> 1 | L30: =+SUM(E30:F30) -> 2 | P30: TERRONES JARA FREDY | Q30: 1 | T30: 2 | V30: 3 | W30: =+SUM(Q30:R30) -> 1 | X30: =+SUM(S30) -> 0 | Y30: =+SUM(T30:U30) -> 2
A31: TERRONES JARA LEYDER | B31: 11 | D31: 1 | E31: 2 | H31: 1 | I31: 15 | J31: =+SUM(B31:C31)+H31 -> 12 | K31: =+SUM(D31) -> 1 | L31: =+SUM(E31:F31) -> 2 | P31: TERRONES JARA LEYDER | Q31: 1 | T31: 2 | V31: 3 | W31: =+SUM(Q31:R31) -> 1 | X31: =+SUM(S31) -> 0 | Y31: =+SUM(T31:U31) -> 2
A32: VELA NEYRA JOSE VICTOR | B32: 13 | D32: 2 | I32: 15 | J32: =+SUM(B32:C32)+H32 -> 13 | K32: =+SUM(D32) -> 2 | L32: =+SUM(E32:F32) -> 0 | P32: VELA NEYRA JOSE VICTOR | Q32: 2 | S32: 1 | V32: 3 | W32: =+SUM(Q32:R32) -> 2 | X32: =+SUM(S32) -> 1 | Y32: =+SUM(T32:U32) -> 0
A33: YUNCA ALFARO JOSE LUIS | B33: 2 | E33: 13 | I33: 15 | J33: =+SUM(B33:C33)+H33 -> 2 | K33: =+SUM(D33) -> 0 | L33: =+SUM(E33:F33) -> 13 | P33: YUNCA ALFARO JOSE LUIS | T33: 3 | V33: 3 | W33: =+SUM(Q33:R33) -> 0 | X33: =+SUM(S33) -> 0 | Y33: =+SUM(T33:U33) -> 3
A34: Total general | B34: 296 | C34: 1 | D34: 33 | E34: 66 | F34: 1 | G34: 19 | H34: 4 | I34: 420 | P34: Total general | Q34: 33 | R34: 1 | S34: 8 | T34: 30 | U34: 12 | V34: 84

Sheet Gratificaciones
A1: Nombre | B1: Sueldo | C1: Asig Familiar | D1: Meses | E1: Base | F1: Grati 50% | G1: Bonif 9% | H1: Total
E2: =B2+C2 -> 0 | F2: =(E2*0.5/6)*D2 -> 0 | G2: =F2*0.09 -> 0 | H2: =F2+G2 -> 0

Sheet CTS
A1: Nombre | B1: Sueldo | C1: Asig Familiar | D1: Meses | E1: Base | F1: 1/6 Grati | G1: Rem Computable | H1: CTS
E2: =B2+C2 -> 0 | F2: =(B2*0.5)/6 -> 0 | G2: =E2+F2 -> 0 | H2: =(G2/12*D2)/2 -> 0

Sheet Resumen
A1: Total Planilla | B1: =SUM('Planilla Mensual'!AI:AI) -> 12469
A2: Total EsSalud | B2: =SUM('Planilla Mensual'!AU:AU) -> 101.7
A3: Total No Remunerativo | B3: =SUM('Planilla Mensual'!AT:AT) -> 7302
A4: Total Gratificaciones | B4: =SUM(Gratificaciones!H:H) -> 0
A5: Total CTS | B5: =SUM(CTS!H:H) -> 0
